Workbook
Name adelanto: datos!$B$111
Name adicionales: datos!$H$111
Name apellidos: datos!$D$13
Name autoconsumo: datos!$B$55
Name BUSCA: INDEX(FOTO,MATCH(t.est!$H$3,TIPO,0))
Name c_pmat: variables!$B$12
Name c_tasas: variables!$B$13
Name cap_bat: datos!$C$98
Name catastro: datos!$B$20
Name coefper: variables!$B$11
Name comision: datos!$B$113
Name consumo1: datos!$D$36
Name consumo2: datos!$B$50
Name cp: datos!$F$17
Name crecom: variables!$B$3
Name cups: datos!$H$11
Name curva: datos!$B$36
Name descuento: datos!$D$111
Name dioxido: variables!$B$7
Name direccion: datos!$B$17
Name ecovivienda: #REF!
Name email: datos!$H$13
Name empresa: datos!$F$11
Name estructura: datos!$B$102
Name fab_inv: datos!$B$72
Name fab_mod: datos!$B$62
Name fecha: datos!$D$3
Name fin120m: variables!$B$10
Name fin12m: variables!$B$8
Name fin24m: variables!$B$9
Name FOTO: t.est!$B$3:$B$11
Name idea: #REF!
Name imagentipo: INDEX(#REF!,MATCH(datos!#REF!,#REF!,0))
Name kwhkwp: variables!$B$2
Name licencia: datos!$F$113
Name localidad: datos!$D$17
Name margen_venta: variables!$B$16
Name mobateria: variables!$B$15
Name mod_bat: datos!$B$95
Name mod_bms: datos!$B$91
Name mod_inv1: datos!$B$69
Name mod_inv2: datos!$B$76
Name mod_meter: datos!$B$87
Name mod_mod: datos!$B$59
Name mod_opt: datos!$B$83
Name nif: datos!$D$11
Name nombre: datos!$B$13
Name num_bat: datos!$D$95
Name num_bms: datos!$D$91
Name num_cee: datos!$F$111
Name num_inv1: datos!$D$69
Name num_inv2: datos!$D$76
Name num_meter: datos!$D$87
Name num_mod: datos!$D$59
Name num_opt: datos!$D$83
Name p_cee: variables!$B$14
Name p_contratada: datos!$D$34
Name p_gen: datos!$C$64
Name p_mod: datos!$C$63
Name perfil: datos!$B$11

Sheet datos
B2: Canal de Entrada | D2: Fecha (fecha)
B3: Oficina Técnica | D3: =TODAY() -> 45568
B4: Nombre del Usuario
B5: Eduardo Rivera
B7: Cliente
B8: Datos de Contacto
B10: Tipo (perfil) | D10: NIF (nif) | F10: Nombre de Empresa (empresa) | H10: CUPS (cups)
B12: Nombre (nombre) | D12: Apellidos (apellidos) | F12: Teléfono (telefono) | H12: Email
B14: Dirección de la Instalación
B16: Dirección (direccion) | D16: Localidad (localidad) | F16: Código Postal (cp) | H16: Provincia (provincia)
B19: Referencia Catastral (catatro)
B21: Incentivos / Ayudas
B23: Programa de Incentivo (programa) | D23: Empresa (tamaño)
B24: Sinayuda | D24: Pequeña
B26: Validación (sólo en caso Ecovivienda)
H27: Potencia Mínima FV (kWp)
B28: Tipo de Vivienda | D28: Superficie Construída | F28: Número de plantas | H28: =IF(B29=ecov!N5, VLOOKUP(D29,ecov!B17:D26,MATCH(F29,ecov!B17:D17,0),), IF(B29=ecov!N6, VLOOKUP(D29,ecov!E17:G26,MATCH(F29,ecov!E17:G17,0),), IF(B29=ecov!N7, VLOOKUP(D29,ecov!H17:J26,MATCH(F29,ecov!H17:J17,0),), ))) -> 4.05
B29: Adosados de 2 Fachadas | D29: 125 | F29: 1 | H29: =IF(H28<=p_gen,"CUMPLE","NO CUMPLE") -> CUMPLE
B31: Consumo
B33: Tipo de Cálculo (tipo_calculo) | D33: Potencia contratada (kW) (p_contratada)
B34: Según Curvas Tipo | D34: 4
B35: Seleccionar Curva Tipo (curva) | D35: Consumo kWh/año (consumo1)
B36: Vivienda habitada todo el año | D36: 18171
B38: Consumos Mensuales (kWh/mes)
B40: Enero | D40: Mayo | F40: Septiembre
B41: 330 | D41: 212 | F41: 283
B42: Febrero | D42: Junio | F42: Octubre
B43: 276 | D43: 408 | F43: 320
B44: Marzo | D44: Julio | F44: Noviembre
B45: 232 | D45: 454 | F45: 469
B46: Abril | D46: Agosto | F46: Diciembre
B47: 154 | D47: 311 | F47: 569
B49: Consumo Total Anual (kWh/año) | C49: =SUM(C40:C48) -> 0
B50: =B41+B43+B45+B47+D41+D43+D45+D47+F41+F43+F45+F47 -> 4018
B52: Instalación Fotovoltaica
B54: Tipo de Instalación (autoconsumo) | D54: Sitema Eléctrico (sistema) | F54: nº CUPS (sólo colectivo)
B55: Autoconsumo Individual | D55: Trifásica | F55: 1
B56: Módulos Fotovoltaicos
B58: Modelo de modulo (mod_mod) | D58: Número de módulos (num_mod)
B59: AIKO N-TYPE ABC A-MAH72MW 605W | D59: 27
B61: Marca de Módulo Seleccionado | D61: nº módulos (Criterio Ecovivienda) | F61: Consumo Anual (kWh/año) (demanda2)
B62: =VLOOKUP(mod_mod,t.mod!A2:H28,2,) -> AIKO | D62: =H30 -> 0 | F62: =IF(tipo_calculo="Según Curvas Tipo",consumo1,consumo2) -> 18171
B63: Potencia pico del módulo seleccionado (Wp) | C63: =VLOOKUP(mod_mod,t.mod!A2:H28,7,) -> 605 | D63: nº módulos recomendados (por consumo)
B64: Potencia del generador FV (kWp) | C64: =num_mod*p_mod/1000 -> 16.335 | D64: =F62/(crecom*p_mod) -> 16.894525
B65: Potencia por usuario (kWp/usuario) | C65: =p_gen/F55 -> 16.335
B66: Inversores Tipo 1
B68: Modelo del Inversor (mod_inv1) | D68: nº de unidades (num_inv1) | F68: Potencia de Inversor Tipo 1 (kWp) | H68: Potencia total de Inversores (kWp)
B69: HUAWEI SUN2000 20KTL M3 | D69: 1 | F69: =VLOOKUP(mod_inv1,t.inv!A2:H36,7,) -> 20 | H69: =F72+F79 -> 20
B71: Marca de Inversor Seleccionado (fab_inv) | F71: Potencia total Inversores Tipo 1 (kWp)
B72: =VLOOKUP(mod_inv1,t.inv!A2:H36,3,) -> HUAWEI | F72: =pot_inv1*num_inv1 -> 20
B73: Inversores Tipo 2
B75: Modelo del Inversor (mod_inv2) | D75: nº de unidades (num_inv2) | F75: Potencia de Inversor Tipo 2
B76: HUAWEI SUN2000 6KTL L1 | D76: 0 | F76: =VLOOKUP(mod_inv2,t.inv!A2:H36,7,) -> 6
B78: Marca de Inversor Seleccionado | F78: Potencia total Inversores Tipo 2 (Wp) | H78: Potencia total de Inversores
B79: =VLOOKUP(mod_inv2,t.inv!A2:H27,3,) -> HUAWEI | F79: =pot_inv2*num_inv2 -> 0 | H79: =H69 -> 20
B80: Optimizadores
B82: Modelo del Optimizador (mod_opt) | D82: nº de unidades (num_opt)
B83: Sin Optimizador
B84: Meter
B86: Modelo de meter (mod_meter) | D86: nº de unidades (num_meter)
B87: Medidor Monofásico DDSU | D87: 1
B88: BMS
B90: Modelo de BMS (mod_bms) | D90: nº de unidades (num_bms)
B91: BMS LUNA 2000 | D91: 0
B92: Batería
B94: Modelo de Batería (mod_bat) | D94: nº de unidades (num_bat)
B95: DYNESS 3,6 kW 48V | D95: 0
B97: Capacidad Unitaria de cada módulo (kWh) | C97: =VLOOKUP(mod_bat,t.bat!A2:G12,5,) -> 3.6
B98: Total Capacidad de la Batería (kWh) | C98: =C97*num_bat -> 0 | D98: (cap_bat)
B99: Estructura
B101: Tipo de Estructura (estructura)
B102: Coplanaria aluminio
B103: =t.est!J3 -> 0
B104: Adicionales y Opcionales
B106: BackupBox Toscano
B107: Certificados Energéticos CEEs
B108: Otros Datos
B110: Adelanto a la firma (€) (adelanto) | D110: Puntos de dto. Sobre margen (%) (descuento) | F110: CsEE (Uds) (num_cee) | H110: Gastos Adicionales (€) (adicionales)
B111: 500 | D111: 0 | F111: 0 | H111: 4395.5
B112: Comisión de Comercial (comision) | D112: Ajuste de Producción (kWh/kWp) | F112: Tasas (licencia) | H112: IVA Aplicable (IVA)
B113: 0 | D113: 1550 | F113: Excluídas | H113: 0.21
B116: Punto de Recarga
B118: Cargador
B122: Precio Final y Descuentos Aplicados
B124: Opción iFV | D124: Opción iFVBAT | F124: Opción iBAT | I124: 77038.02
B125: Total con IVA (€) | D125: Total con IVA (€) | F125: Total con IVA (€) | I125: =B126-I124 -> -57043.099
B126: =ppto!G44 -> 19994.921 | D126: =ppto!H44 -> 19994.921 | F126: =ppto!I44 -> 5894.515
B127: Incentivo (€) | D127: Incentivo (€) | F127: Incentivo (€)
B128: =incentivo!C36 -> 0 | D128: =incentivo!D36 -> 0 | F128: =incentivo!E36 -> 0
B129: Total después de ayudas (€) | D129: Total después de ayudas (€) | F129: Total después de ayudas (€)
B130: =B126-B128 -> 19994.921 | D130: =D126-D128 -> 19994.921 | F130: =F126-F128 -> 5894.515
B131: Ratio (€/Wp) | D131: Ratio (€/Wp) | F131: Ratio (€/Wp)
B132: =B126/(1000*p_gen) -> 1.2240539 | D132: =D126/(1000*p_gen) -> 1.2240539 | F132: N/A
B133: Potencia (kWp) | D133: Potencia (kWp) | F133: Potencia (kWp)
B134: =p_gen -> 16.335 | D134: =p_gen -> 16.335 | F134: N/A
B135: Margen Neto (€) | D135: Margen Neto (€) | F135: Margen Neto (€)
B136: =ppto!G26 -> 3210.678 | D136: =ppto!H26 -> 3210.678 | F136: =ppto!I26 -> 126

Sheet ppto
B1: Elemento | C1: Descripción | D1: Unidad de Medida | E1: Medición | F1: Coste Unitario (€) | G1: iFV Coste Total (€) | H1: iFVBAT Coste Total (€) | I1: iBAT Coste Total (€)
B2: ="Instalación de Autoconsumo Fotovoltaico de "&p_gen&" kWp" -> Instalación de Autoconsumo Fotovoltaico de 16,335 kWp
B3: Módulo Fotovoltaico | C3: =mod_mod -> AIKO N-TYPE ABC A-MAH72MW 605W | D3: Ud de módulo | E3: =num_mod -> 27 | F3: =VLOOKUP(mod_mod,t.mod!A2:H28,8,) -> 78.65 | G3: =E3*F3 -> 2123.55 | H3: =E3*F3 -> 2123.55 | K3: =G3*($G$32/$G$16) -> 4667.2678 | L3: =IF(E3=0,0,K3/E3) -> 172.86177
B4: Grupo Inversores Tipo nº1 | C4: =mod_inv1 -> HUAWEI SUN2000 20KTL M3 | D4: Ud de inversor | E4: =num_inv1 -> 1 | F4: =VLOOKUP(mod_inv1,t.inv!A2:H261,8,) -> 1784 | G4: =E4*F4 -> 1784 | H4: =E4*F4 -> 1784 | K4: =G4*($G$32/$G$16) -> 3920.9841 | L4: =IF(E4=0,0,K4/E4) -> 3920.9841
B5: Grupo Inversores Tipo nº2 | C5: =mod_inv2 -> HUAWEI SUN2000 6KTL L1 | D5: Ud de inversor | E5: =num_inv2 -> 0 | F5: =VLOOKUP(mod_inv2,t.inv!A2:H261,8,) -> 780 | G5: =E5*F5 -> 0 | H5: =E5*F5 -> 0 | K5: =G5*($G$32/$G$16) -> 0 | L5: =IF(E5=0,0,K5/E5) -> 0
B6: Equipos de medida | C6: =mod_meter -> Medidor Monofásico DDSU | D6: Ud de medidores | E6: =num_meter -> 1 | F6: =VLOOKUP(C6,t.met!A2:F13,6,) -> 95 | G6: =E6*F6 -> 95 | H6: =E6*F6 -> 95 | K6: =G6*($G$32/$G$16) -> 208.7968 | L6: =IF(E6=0,0,K6/E6) -> 208.7968
B7: Estructura | C7: =estructura -> Coplanaria aluminio | D7: Ud de módulo | E7: =num_mod -> 27 | F7: =VLOOKUP(estructura,t.est!A3:F11,6,) -> 32 | G7: =E7*F7 -> 864 | H7: =E7*F7 -> 864 | K7: =G7*($G$32/$G$16) -> 1898.9519 | L7: =IF(E7=0,0,K7/E7) -> 70.331553
B8: Optimizadores | C8: =mod_opt -> Sin Optimizador | D8: Ud de optimizador | E8: =num_opt -> 0 | F8: =VLOOKUP(C8,t.opt!A3:H21,8,) -> 0 | G8: =E8*F8 -> 0 | H8: =E8*F8 -> 0 | K8: =G8*($G$32/$G$16) -> 0 | L8: =IF(E8=0,0,K8/E8) -> 0
B9: Cableado y Pequeño Material | C9: Cableado, Aparamenta y Pequeño Material | D9: Ud de instalación | E9: 1 | F9: =c_pmat -> 552 | G9: =E9*F9 -> 552 | H9: =E9*F9 -> 552 | K9: =G9*($G$32/$G$16) -> 1213.2193 | L9: =IF(E9=0,0,K9/E9) -> 1213.2193
B10: Montaje FV | C10: Montaje de la Instalación Fotovoltaica | D10: Ud de módulo | E10: =num_mod -> 27 | F10: =IF(num_mod=0,0,VLOOKUP(num_mod,t.mon!A3:F263,6,)/E3) -> 77.777778 | G10: =E10*F10 -> 2100 | H10: =E10*F10 -> 2100 | K10: =G10*($G$32/$G$16) -> 4615.5081 | L10: =IF(E10=0,0,K10/E10) -> 170.94475
B11: ="Instalación de Baterías de "&cap_bat&" kWh" -> Instalación de Baterías de 0 kWh
B12: BMS | C12: =mod_bms -> BMS LUNA 2000 | D12: Ud de BMS | E12: =num_bms -> 0 | F12: =VLOOKUP(C12,t.bms!A3:G22,7,) -> 735 | H12: =E12*F12 -> 0 | I12: =E12*F12 -> 0
B13: Módulos de Batería | C13: =mod_bat -> DYNESS 3,6 kW 48V | D13: Ud de módulos de Batería | E13: =num_bat -> 0 | F13: =VLOOKUP(mod_bat,t.bat!A3:G23,7,) -> 745.83 | H13: =E13*F13 -> 0 | I13: =E13*F13 -> 0
B14: Montaje Batería | C14: Montaje de la Instalación de Batería | D14: Ud de kWh | E14: =num_bms -> 0 | F14: =SUM(F12:F13)*0.15 -> 222.1245 | H14: =E14*F14*0.5 -> 0 | I14: =E14*F14 -> 0
E16: Coste Directo | G16: =SUM(G3:G14) -> 7518.55 | H16: =SUM(H3:H14) -> 7518.55 | I16: =SUM(I3:I14) -> 0
E17: Coste Indirecto | G17: =VLOOKUP(num_mod,t.coi!A2:E263,5) -> 1400 | H17: =VLOOKUP(num_mod,t.coi!A2:E263,5) -> 1400 | I17: 350
E18: Coste Total | G18: =G16+G17 -> 8918.55 | H18: =H16+H17 -> 8918.55 | I18: =I16+I17 -> 350
E20: Margen
E21: Margen bruto de Venta (%) | G21: =margen_venta -> 0.36 | H21: =margen_venta -> 0.36 | I21: =margen_venta -> 0.36
E22: Margen bruto de Venta (€) | G22: =G18*G21 -> 3210.678 | H22: =H18*H21 -> 3210.678 | I22: =I18*I21 -> 126
E23: Descuento (%) | G23: =-descuento -> 0 | H23: =-descuento -> 0 | I23: =-descuento -> 0
E24: Descuento (€) | G24: =G18*G23 -> 0 | H24: =H18*H23 -> 0 | I24: =I18*I23 -> 0
E25: Margen neto de Venta (%) | G25: =G21+G23 -> 0.36 | H25: =H21+H23 -> 0.36 | I25: =I21+I23 -> 0.36
D26: =G26/2 -> 1605.339 | E26: Margen neto de Venta (€) | G26: =G18*G25 -> 3210.678 | H26: =H18*H25 -> 3210.678 | I26: =I18*I25 -> 126
E27: Subtotal Venta (sin IVA)
E28: Subtotal Venta (sin IVA) | G28: =G18+G26 -> 12129.228 | H28: =H18+H26 -> 12129.228 | I28: =I18+I26 -> 476
E29: Otros Conceptos
E30: Certificados Energéticos | G30: =p_cee*num_cee -> 0 | H30: =p_cee*num_cee -> 0 | I30: =p_cee*num_cee -> 0
E31: Adicionales | G31: =adicionales -> 4395.5 | H31: =adicionales -> 4395.5 | I31: =adicionales -> 4395.5
E32: Total (sin IVA) | G32: =G28+G30+G31 -> 16524.728 | H32: =H28+H30+H31 -> 16524.728 | I32: =I28+I30+I31 -> 4871.5
E33: IVA (21%) | G33: =G32*0.21 -> 3470.1929 | H33: =H32*0.21 -> 3470.1929 | I33: =I32*0.21 -> 1023.015
E34: Total (con IVA) | G34: =G32+G33 -> 19994.921 | H34: =H32+H33 -> 19994.921 | I34: =I32+I33 -> 5894.515 | J34: =G34/(p_gen*1000) -> 1.2240539 | K34: €/Wp
E36: Cálculo Estimado de Tasas e ICIO
E37: Presupuesto neto | G37: =G32 -> 16524.728 | H37: =H32 -> 16524.728 | I37: =I32 -> 4871.5
E38: Gastos Generales (13%) | G38: =G40*0.13 -> 1805.2224 | H38: =H40*0.13 -> 1805.2224 | I38: =I40*0.13 -> 532.18067
E39: Beneficio Industrial (6%) | G39: =G40*0.06 -> 833.17956 | H39: =H40*0.06 -> 833.17956 | I39: =I40*0.06 -> 245.62185
E40: PEM | G40: =G37/1.19 -> 13886.326 | H40: =H37/1.19 -> 13886.326 | I40: =I37/1.19 -> 4093.6975
E41: Porcentaje Licencia, tasas + ICIO (%) | G41: 0.05 | H41: 0.05 | I41: 0.05
E42: Coste Licencia, tasas + ICIO (€) | G42: =G40*G41 -> 694.3163 | H42: =H40*H41 -> 694.3163 | I42: =I40*I41 -> 204.68487
E44: Total (con IVA y Tasas) | G44: =IF(licencia="Incluídas",G34+G42,G34) -> 19994.921 | H44: =IF(licencia="Incluídas",H34+H42,H34) -> 19994.921 | I44: =IF(licencia="Incluídas",I34+I42,I34) -> 5894.515 | J44: =G44/(p_gen*1000) -> 1.2240539 | K44: €/Wp

Sheet incentivo
B2: Cálculo del Incentivo
B3: Programa de Ayudas / Incentivo | C3: =programa -> Sinayuda
B4: Perfil de Cliente | C4: =perfil -> 0
B5: Tamaño de Empresa | C5: =IF(perfil="Particular","No Aplica (particular)",tamaño) -> Pequeña
B6: Autoconsumo | C6: =autoconsumo -> Autoconsumo Individual
B7: Potencia Instalación (Wp) | C7: =p_gen*1000 -> 16335
B8: Ecovivienda
B15: Incentivo por Paneles
B16: % de ayuda | C16: =IF(AND(programa="AAE",perfil="Empresa Pequeña",p_gen*1000<=10000),0.45, IF(AND(programa="AAE",perfil="Empresa Mediana",p_gen*1000<=10000),0.25, IF(AND(programa="AAE",perfil="Empresa Grande",p_gen*1000<=10000),0.15, IF(AND(programa="AAE",perfil="Empresa Pequeña",p_gen*1000>10000),0.35, IF(AND(programa="AAE",perfil="Empresa Mediana",p_gen*1000>10000),0.25, IF(AND(programa="AAE",perfil="Empresa Grande",p_gen*1000>10000),0.15, IF(AND(programa="Ecovivienda",datos!H29="CUMPLE"),0.8, IF(AND(programa="Ecovivienda",datos!H29="NO CUMPLE"),0.65, IF(programa="Sinayuda",0,) )))))))) -> 0 | F16: =perfil -> 0
B17: € de ayuda | C17: =IF(AND(programa="AAE",perfil="Particular",autoconsumo="Autoconsumo Individual",p_gen<=10),p_gen*600, IF(AND(programa="AAE",perfil="Particular",autoconsumo="Autoconsumo Individual",p_gen<=100),p_gen*450, IF(AND(programa="AAE",perfil="Particular",autoconsumo="Autoconsumo Individual",p_gen<=1000),p_gen*350, IF(AND(programa="AAE",perfil="Particular",autoconsumo="Autoconsumo Colectivo",p_gen<=10),p_gen*710, IF(AND(programa="AAE",perfil="Particular",autoconsumo="Autoconsumo Colectivo",p_gen<=100),p_gen*535, IF(AND(programa="AAE",perfil="Particular",autoconsumo="Autoconsumo Colectivo",p_gen<=1000),p_gen*420, )))))) -> 0
B18: Incentivo por Batería
B19: % de ayuda | C19: =IF(AND(programa="AAE",perfil="Empresa",tamaño="Pequeña"),0.65, IF(AND(programa="AAE",perfil="Empresa",tamaño="Mediana"),0.55, IF(AND(programa="AAE",perfil="Empresa",tamaño="Grande"),0.45, IF(AND(programa="Ecovivienda",datos!H29="CUMPLE"),0.8, IF(AND(programa="Ecovivienda",datos!H29="NO CUMPLE"),0.65, ))))) -> 0
B20: € de ayuda | C20: =IF(AND(programa="AAE",perfil="Particular",p_gen<=10,cap_bat<10),cap_bat*490, IF(AND(programa="AAE",perfil="Particular",p_gen<=100,cap_bat<10),cap_bat*490, IF(AND(programa="AAE",perfil="Particular",p_gen<=10,cap_bat>=10),cap_bat*350, IF(AND(programa="AAE",perfil="Particular",p_gen<=100,cap_bat>=10),cap_bat*350, )))) -> 0
B21: Incentivo por Pérgola
B22: Pérgola | C22: 0
B23: Incentivo y Presupuesto Final | C23: FV | D23: FVBAT | E23: BAT
B24: Particulares
B25: Presupuesto con IVA (€) | C25: =ppto!G44 -> 19994.921 | D25: =ppto!H44 -> 19994.921 | E25: =ppto!I44 -> 5894.515
B26: Incentivo Total (€) | C26: =C25*C16+C17+C22 -> 0 | D26: =D25*C16+C20+C17+C22 -> 0 | E26: =C19*E25+C20 -> 0
B27: Incentivo Total (%) | C27: =C26/C25 -> 0 | D27: =D26/D25 -> 0 | E27: =E26/E25 -> 0
B28: Presupuesto con IVA después de Incentivo (€) | C28: =C25-C26 -> 19994.921 | D28: =D25-D26 -> 19994.921 | E28: =E25-E26 -> 5894.515
B29: Empresas
B30: Presupuesto sin IVA (€) | C30: =ppto!G32 -> 16524.728 | D30: =ppto!H32 -> 16524.728 | E30: =ppto!I32 -> 4871.5
B31: Incentivo Total (€) | C31: =C30*C16+C17+C22 -> 0 | D31: =C30*C16+(D30-C30)*C19+C20+C17+C22 -> 0 | E31: =E25*C19+C20+C17+C22 -> 0
B32: Incentivo Total (%) | C32: =C36/C30 -> 0 | D32: =D31/D30 -> 0 | E32: =E31/E30 -> 0 | F32: revisar
B33: Presupuesto con IVA después de Incentivo (€) | C33: =C25-C31 -> 19994.921 | D33: =D30-D31 -> 16524.728 | E33: =E30-E31 -> 4871.5
B34: Cálculo
B35: Perfil | C35: =perfil -> 0 | D35: =perfil -> 0 | E35: =perfil -> 0
B36: Incentivo Total (€) | C36: =IF(perfil="Particular",incentivo!C26,incentivo!C31) -> 0 | D36: =IF(perfil="Particular",incentivo!D26,incentivo!D31) -> 0 | E36: =IF(perfil="Particular",incentivo!E26,incentivo!E31) -> 0
B37: Incentivo Total (%) | C37: =IF(perfil="Particular",incentivo!C27,incentivo!C32) -> 0 | D37: =IF(perfil="Particular",incentivo!D27,incentivo!D32) -> 0 | E37: =IF(perfil="Particular",incentivo!E27,incentivo!E32) -> 0
B38: Autoconsumo y Autosuficiencia
B39: Ratio demanda / Potencia Generador (kwh/año)/(kWp) | C39: =cálculos!P7/(p_gen*1000) -> 1.1123967
B40: Tamaño de batería (kWh) | C40: - | D40: =cap_bat -> 0
B41: Ratio (kWp/kWh) Con Bat | C41: - | D41: =(p_gen)/D40 -> #DIV/0!
B42: Coeficiente | C42: - | D42: =0.6529*D41^(-1.164) -> #DIV/0!
B43: Reducción de Demanda (%) | C43: =-0.0471*C39+0.5573 -> 0.50490612 | D43: =D41*D42+(C43-0.474) -> #DIV/0!

Sheet ppto_desglose
E2: SOLAY INGENIEROS, S.L. | H2: info@solay.es
E3: Paseo de Bollullos de la Mitación 18 | H3: www.solay.es
E4: 4110, Bollullos de la Mitación, Sevilla | H4: 954 664 252
E5: B09848912
A7: PRESUPUESTO DE VENTA
A8: =ppto!B2 -> Instalación de Autoconsumo Fotovoltaico de 16,335 kWp
C13: Datos del Presupuesto de Venta | E13: Datos del Cliente
C15: Ref:
E16: =CONCATENATE(nombre," ",apellidos,)
C17: Fecha: | E17: =telefono
C18: =fecha -> 45568 | E18: =direccion | J18: 0
E19: =CONCATENATE(cp," - ",localidad," - ",provincia) -> - -
C21: Elemento | D21: Descripción | F21: Uds. | G21: Precio Ud. | H21: Importe (€)
C22: =ppto!B2 -> Instalación de Autoconsumo Fotovoltaico de 16,335 kWp
C23: =ppto!B3 -> Módulo Fotovoltaico | D23: =ppto!C3 -> AIKO N-TYPE ABC A-MAH72MW 605W | F23: =ppto!E3 -> 27 | G23: =ppto!L3 -> 172.86177 | H23: =F23*(G23*(1-$J$18)) -> 4667.2678
C24: =ppto!B4 -> Grupo Inversores Tipo nº1 | D24: =ppto!C4 -> HUAWEI SUN2000 20KTL M3 | F24: =ppto!E4 -> 1 | G24: =ppto!L4 -> 3920.9841 | H24: =F24*(G24*(1-$J$18)) -> 3920.9841
C25: =ppto!B5 -> Grupo Inversores Tipo nº2 | D25: =ppto!C5 -> HUAWEI SUN2000 6KTL L1 | G25: =$J$18 -> 0 | H25: =F25*(G25*(1-$J$18)) -> 0
C26: =ppto!B6 -> Equipos de medida | D26: =ppto!C6 -> Medidor Monofásico DDSU | F26: =ppto!E6 -> 1 | G26: =ppto!L6 -> 208.7968 | H26: =F26*(G26*(1-$J$18)) -> 208.7968
C27: =ppto!B7 -> Estructura | D27: =ppto!C7 -> Coplanaria aluminio | F27: =ppto!E7 -> 27 | G27: =ppto!L7 -> 70.331553 | H27: =F27*(G27*(1-$J$18)) -> 1898.9519
C28: =ppto!B8 -> Optimizadores | D28: =ppto!C8 -> Sin Optimizador | G28: =$J$18 -> 0 | H28: =F28*(G28*(1-$J$18)) -> 0
C29: =ppto!B9 -> Cableado y Pequeño Material | D29: =ppto!C9 -> Cableado, Aparamenta y Pequeño Material | F29: =ppto!E9 -> 1 | G29: =ppto!L9 -> 1213.2193 | H29: =F29*(G29*(1-$J$18)) -> 1213.2193
C30: =ppto!B10 -> Montaje FV | D30: =ppto!C10 -> Montaje de la Instalación Fotovoltaica | F30: =ppto!E10 -> 27 | G30: =ppto!L10 -> 170.94475 | H30: =F30*(G30*(1-$J$18)) -> 4615.5081
C32: Servicios Adicionales Incluídos
C34: Gestión completa para el cobro de las ayudas e incentivos públicos
C35: Gestión completa para la bonificación del IBI y el cobro del mismo
C36: Legalización de la Instalación en Industria
C37: Servicio de postventa
C38: Asesoramiento Energético realizado por nuestros ingenieros, sobre tarifas eléctricsa, precios, etc
F42: Base Imponible: | H42: =SUM(H23:H38) -> 16524.728
F43: IVA (21,00 %): | H43: =H42*0.21 -> 3470.1929
F44: Total con IVA: | H44: =H42+H43 -> 19994.921
A48: SOLAY es marca registrada de SOLAY INGENIEROS, S,L. Inscrita en el Registro Mercantil de Sevilla CIF: B09.848.912

Sheet variables
A1: Parámetro | B1: Valor | C1: Nombre de Variable | F1: Valor Referencia
A2: Producción kWh/año por kWp en Sevilla | B2: =datos!D113 -> 1550 | C2: kwhkwp | F2: =1668.888 -> 1668.888
A3: Consumo Recomendado kWh/Wp | B3: =800/450 -> 1.7777778 | C3: crecom
A4: Precio de la Energía (€/kWh) | B4: 0.33 | C4: preciokwh
A5: Tasa de Interés | B5: 0.035 | C5: ti
A6: Retribución de Excedentes (€/kWh) | B6: 0.105 | C6: precioexc
A7: Emisiones de CO2 (kg/kWh) | B7: 0.256 | C7: dioxido
A8: Coeficiente Financiación 12 meses | B8: 0.088972 | C8: fin12m
A9: Coeficiente Financiación 24 meses | B9: 0.046236 | C9: fin24m
A10: Coeficiente Financiación 120 meses | B10: 0.012362 | C10: fin120m
A11: Coeficiente de pérdida de producción | B11: 0.99243 | C11: coefper
A12: Coste Pequeño Material (€) | B12: =120+16*num_mod -> 552 | C12: c_pmat
A13: Coste Tasas y Licencias (€) | B13: =0.025*(ppto!G18+ppto!G26)*1.21 -> 366.90915 | C13: c_tasas
A14: Precio de Venta de CEE (€) | B14: 65 | C14: p_cee
A15: Coste Mano de Obra Batería | B15: 150 | C15: mobateria
A16: Margen de Venta | B16: =VLOOKUP(num_mod,t.mar!A1:C263,3) -> 0.36 | C16: margen_venta
A19: tabla_financiación
A20: Entidad Financiera
A21: BANCO SANTANDER

Sheet Comercial
B1: Comercial:
B2: Margen del Comercial: | C2: 0.02
C5: iFV Coste Total (€) | D5: iFVBAT Coste Total (€) | E5: iBAT Coste Total (€)
B6: Precio sin IVA | C6: =ppto!G32 -> 16524.728 | D6: =ppto!H32 -> 16524.728 | E6: =ppto!I32 -> 4871.5
B10: Margen Neto de Venta | C10: =ppto!G26 -> 3210.678
B11: Margen del Comercial | C11: =C6*C2 -> 330.49456
B12: Margen Final Solay | C12: =C10-C11 -> 2880.1834

Sheet TABLA HUAWEI
A1: Módulo | C1: LONGI LR5-72HPH 550 (HiMO5 New) 550 Wp | E1: HUAWEI - ECOVIVIENDA
A2: Potencia (Wp) | C2: =VLOOKUP(C1,t.mod!A2:H28,7,) -> 550 | E2: Tarifa 2023.10
A5: UD | B5: Potencia Paneles (kW) | C5: Modelo Inversor | D5: Modelo Panel | E5: Medidor | F5: Estructura | G5: Coste Paneles (€) | H5: Coste Inversor (€) | I5: Coste Medida (€) | J5: Coste Estructura (€) | K5: Coste Cableado (€) | L5: Coste de Montaje (€) | M5: Coste directo (€) | N5: Coste indirecto (€) | O5: Coste total (€) | P5: Margen (€) | Q5: CEEs | R5: IVA (€) | S5: Precio con IVA (€)
A7: 3 | B7: =A7*$C$2/1000 -> 1.65 | C7: HUAWEI SUN2000 2KTL L1 | D7: =$C$1 -> LONGI LR5-72HPH 550 (HiMO5 New) 550 Wp | E7: Medidor Monofásico DDSU | F7: Coplanaria aluminio | G7: =VLOOKUP($C$1,t.mod!$A$2:$H$28,8,)*A7 -> 280.5 | H7: =VLOOKUP(C7,t.inv!$A$2:$H$261,8,) -> 462 | I7: =VLOOKUP(E7,t.met!$A$2:$F$13,6,) -> 95 | J7: =VLOOKUP(F7,t.est!$A$3:$F$11,6,)*A7 -> 96 | K7: =120+16*A7 -> 168 | L7: =VLOOKUP(A7,t.mon!$A$3:$F$263,6,) -> 850 | M7: =SUM(G7:L7) -> 1951.5 | N7: =VLOOKUP(A7,t.coi!$A$2:$E$263,5) -> 700 | O7: =M7+N7 -> 2651.5 | P7: =VLOOKUP(A7,t.mar!$A$1:$C$263,3)*O7 -> 1060.6 | Q7: =p_cee*2 -> 130 | R7: =(O7+P7+Q7)*0.21 -> 806.841 | S7: =O7+P7+Q7+R7 -> 4648.941
A8: 4 | B8: =A8*$C$2/1000 -> 2.2 | C8: HUAWEI SUN2000 2KTL L1 | D8: =$C$1 -> LONGI LR5-72HPH 550 (HiMO5 New) 550 Wp | E8: Medidor Monofásico DDSU | F8: Coplanaria aluminio | G8: =VLOOKUP($C$1,t.mod!$A$2:$H$28,8,)*A8 -> 374 | H8: =VLOOKUP(C8,t.inv!$A$2:$H$261,8,) -> 462 | I8: =VLOOKUP(E8,t.met!$A$2:$F$13,6,) -> 95 | J8: =VLOOKUP(F8,t.est!$A$3:$F$11,6,)*A8 -> 128 | K8: =120+16*A8 -> 184 | L8: =VLOOKUP(A8,t.mon!$A$3:$F$263,6,) -> 850 | M8: =SUM(G8:L8) -> 2093 | N8: =VLOOKUP(A8,t.coi!$A$2:$E$263,5) -> 700 | O8: =M8+N8 -> 2793 | P8: =VLOOKUP(A8,t.mar!$A$1:$C$263,3)*O8 -> 1117.2 | Q8: =p_cee*2 -> 130 | R8: =(O8+P8+Q8)*0.21 -> 848.442 | S8: =O8+P8+Q8+R8 -> 4888.642
A9: 5 | B9: =A9*$C$2/1000 -> 2.75 | C9: HUAWEI SUN2000 3KTL L1 | D9: =$C$1 -> LONGI LR5-72HPH 550 (HiMO5 New) 550 Wp | E9: Medidor Monofásico DDSU | F9: Coplanaria aluminio | G9: =VLOOKUP($C$1,t.mod!$A$2:$H$28,8,)*A9 -> 467.5 | H9: =VLOOKUP(C9,t.inv!$A$2:$H$261,8,) -> 545.05 | I9: =VLOOKUP(E9,t.met!$A$2:$F$13,6,) -> 95 | J9: =VLOOKUP(F9,t.est!$A$3:$F$11,6,)*A9 -> 160 | K9: =120+16*A9 -> 200 | L9: =VLOOKUP(A9,t.mon!$A$3:$F$263,6,) -> 900 | M9: =SUM(G9:L9) -> 2367.55 | N9: =VLOOKUP(A9,t.coi!$A$2:$E$263,5) -> 800 | O9: =M9+N9 -> 3167.55 | P9: =VLOOKUP(A9,t.mar!$A$1:$C$263,3)*O9 -> 1235.3445 | Q9: =p_cee*2 -> 130 | R9: =(O9+P9+Q9)*0.21 -> 951.90785 | S9: =O9+P9+Q9+R9 -> 5484.8023
A10: 6 | B10: =A10*$C$2/1000 -> 3.3 | C10: HUAWEI SUN2000 3KTL L1 | D10: =$C$1 -> LONGI LR5-72HPH 550 (HiMO5 New) 550 Wp | E10: Medidor Monofásico DDSU | F10: Coplanaria aluminio | G10: =VLOOKUP($C$1,t.mod!$A$2:$H$28,8,)*A10 -> 561 | H10: =VLOOKUP(C10,t.inv!$A$2:$H$261,8,) -> 545.05 | I10: =VLOOKUP(E10,t.met!$A$2:$F$13,6,) -> 95 | J10: =VLOOKUP(F10,t.est!$A$3:$F$11,6,)*A10 -> 192 | K10: =120+16*A10 -> 216 | L10: =VLOOKUP(A10,t.mon!$A$3:$F$263,6,) -> 1050 | M10: =SUM(G10:L10) -> 2659.05 | N10: =VLOOKUP(A10,t.coi!$A$2:$E$263,5) -> 800 | O10: =M10+N10 -> 3459.05 | P10: =VLOOKUP(A10,t.mar!$A$1:$C$263,3)*O10 -> 1349.0295 | Q10: =p_cee*2 -> 130 | R10: =(O10+P10+Q10)*0.21 -> 1036.9967 | S10: =O10+P10+Q10+R10 -> 5975.0762
A11: 7 | B11: =A11*$C$2/1000 -> 3.85 | C11: HUAWEI SUN2000 4KTL L1 | D11: =$C$1 -> LONGI LR5-72HPH 550 (HiMO5 New) 550 Wp | E11: Medidor Monofásico DDSU | F11: Coplanaria aluminio | G11: =VLOOKUP($C$1,t.mod!$A$2:$H$28,8,)*A11 -> 654.5 | H11: =VLOOKUP(C11,t.inv!$A$2:$H$261,8,) -> 664.95 | I11: =VLOOKUP(E11,t.met!$A$2:$F$13,6,) -> 95 | J11: =VLOOKUP(F11,t.est!$A$3:$F$11,6,)*A11 -> 224 | K11: =120+16*A11 -> 232 | L11: =VLOOKUP(A11,t.mon!$A$3:$F$263,6,) -> 1250 | M11: =SUM(G11:L11) -> 3120.45 | N11: =VLOOKUP(A11,t.coi!$A$2:$E$263,5) -> 850 | O11: =M11+N11 -> 3970.45 | P11: =VLOOKUP(A11,t.mar!$A$1:$C$263,3)*O11 -> 1508.771 | Q11: =p_cee*2 -> 130 | R11: =(O11+P11+Q11)*0.21 -> 1177.9364 | S11: =O11+P11+Q11+R11 -> 6787.1574
A12: 8 | B12: =A12*$C$2/1000 -> 4.4 | C12: HUAWEI SUN2000 4KTL L1 | D12: =$C$1 -> LONGI LR5-72HPH 550 (HiMO5 New) 550 Wp | E12: Medidor Monofásico DDSU | F12: Coplanaria aluminio | G12: =VLOOKUP($C$1,t.mod!$A$2:$H$28,8,)*A12 -> 748 | H12: =VLOOKUP(C12,t.inv!$A$2:$H$261,8,) -> 664.95 | I12: =VLOOKUP(E12,t.met!$A$2:$F$13,6,) -> 95 | J12: =VLOOKUP(F12,t.est!$A$3:$F$11,6,)*A12 -> 256 | K12: =120+16*A12 -> 248 | L12: =VLOOKUP(A12,t.mon!$A$3:$F$263,6,) -> 1250 | M12: =SUM(G12:L12) -> 3261.95 | N12: =VLOOKUP(A12,t.coi!$A$2:$E$263,5) -> 850 | O12: =M12+N12 -> 4111.95 | P12: =VLOOKUP(A12,t.mar!$A$1:$C$263,3)*O12 -> 1562.541 | Q12: =p_cee*2 -> 130 | R12: =(O12+P12+Q12)*0.21 -> 1218.9431 | S12: =O12+P12+Q12+R12 -> 7023.4341
A13: 9 | B13: =A13*$C$2/1000 -> 4.95 | C13: HUAWEI SUN2000 5KTL L1 | D13: =$C$1 -> LONGI LR5-72HPH 550 (HiMO5 New) 550 Wp | E13: Medidor Monofásico DDSU | F13: Coplanaria aluminio | G13: =VLOOKUP($C$1,t.mod!$A$2:$H$28,8,)*A13 -> 841.5 | H13: =VLOOKUP(C13,t.inv!$A$2:$H$261,8,) -> 722.7 | I13: =VLOOKUP(E13,t.met!$A$2:$F$13,6,) -> 95 | J13: =VLOOKUP(F13,t.est!$A$3:$F$11,6,)*A13 -> 288 | K13: =120+16*A13 -> 264 | L13: =VLOOKUP(A13,t.mon!$A$3:$F$263,6,) -> 1350 | M13: =SUM(G13:L13) -> 3561.2 | N13: =VLOOKUP(A13,t.coi!$A$2:$E$263,5) -> 900 | O13: =M13+N13 -> 4461.2 | P13: =VLOOKUP(A13,t.mar!$A$1:$C$263,3)*O13 -> 1650.644 | Q13: =p_cee*2 -> 130 | R13: =(O13+P13+Q13)*0.21 -> 1310.7872 | S13: =O13+P13+Q13+R13 -> 7552.6312
A14: 10 | B14: =A14*$C$2/1000 -> 5.5 | C14: HUAWEI SUN2000 5KTL L1 | D14: =$C$1 -> LONGI LR5-72HPH 550 (HiMO5 New) 550 Wp | E14: Medidor Monofásico DDSU | F14: Coplanaria aluminio | G14: =VLOOKUP($C$1,t.mod!$A$2:$H$28,8,)*A14 -> 935 | H14: =VLOOKUP(C14,t.inv!$A$2:$H$261,8,) -> 722.7 | I14: =VLOOKUP(E14,t.met!$A$2:$F$13,6,) -> 95 | J14: =VLOOKUP(F14,t.est!$A$3:$F$11,6,)*A14 -> 320 | K14: =120+16*A14 -> 280 | L14: =VLOOKUP(A14,t.mon!$A$3:$F$263,6,) -> 1400 | M14: =SUM(G14:L14) -> 3752.7 | N14: =VLOOKUP(A14,t.coi!$A$2:$E$263,5) -> 950 | O14: =M14+N14 -> 4702.7 | P14: =VLOOKUP(A14,t.mar!$A$1:$C$263,3)*O14 -> 1739.999 | Q14: =p_cee*2 -> 130 | R14: =(O14+P14+Q14)*0.21 -> 1380.2668 | S14: =O14+P14+Q14+R14 -> 7952.9658
A15: 11 | B15: =A15*$C$2/1000 -> 6.05 | C15: HUAWEI SUN2000 6KTL L1 | D15: =$C$1 -> LONGI LR5-72HPH 550 (HiMO5 New) 550 Wp | E15: Medidor Monofásico DDSU | F15: Coplanaria aluminio | G15: =VLOOKUP($C$1,t.mod!$A$2:$H$28,8,)*A15 -> 1028.5 | H15: =VLOOKUP(C15,t.inv!$A$2:$H$261,8,) -> 780 | I15: =VLOOKUP(E15,t.met!$A$2:$F$13,6,) -> 95 | J15: =VLOOKUP(F15,t.est!$A$3:$F$11,6,)*A15 -> 352 | K15: =120+16*A15 -> 296 | L15: =VLOOKUP(A15,t.mon!$A$3:$F$263,6,) -> 1400 | M15: =SUM(G15:L15) -> 3951.5 | N15: =VLOOKUP(A15,t.coi!$A$2:$E$263,5) -> 950 | O15: =M15+N15 -> 4901.5 | P15: =VLOOKUP(A15,t.mar!$A$1:$C$263,3)*O15 -> 1813.555 | Q15: =p_cee*2 -> 130 | R15: =(O15+P15+Q15)*0.21 -> 1437.4615 | S15: =O15+P15+Q15+R15 -> 8282.5166
A16: 12 | B16: =A16*$C$2/1000 -> 6.6 | C16: HUAWEI SUN2000 6KTL L1 | D16: =$C$1 -> LONGI LR5-72HPH 550 (HiMO5 New) 550 Wp | E16: Medidor Monofásico DDSU | F16: Coplanaria aluminio | G16: =VLOOKUP($C$1,t.mod!$A$2:$H$28,8,)*A16 -> 1122 | H16: =VLOOKUP(C16,t.inv!$A$2:$H$261,8,) -> 780 | I16: =VLOOKUP(E16,t.met!$A$2:$F$13,6,) -> 95 | J16: =VLOOKUP(F16,t.est!$A$3:$F$11,6,)*A16 -> 384 | K16: =120+16*A16 -> 312 | L16: =VLOOKUP(A16,t.mon!$A$3:$F$263,6,) -> 1450 | M16: =SUM(G16:L16) -> 4143 | N16: =VLOOKUP(A16,t.coi!$A$2:$E$263,5) -> 1000 | O16: =M16+N16 -> 5143 | P16: =VLOOKUP(A16,t.mar!$A$1:$C$263,3)*O16 -> 1902.91 | Q16: =p_cee*2 -> 130 | R16: =(O16+P16+Q16)*0.21 -> 1506.9411 | S16: =O16+P16+Q16+R16 -> 8682.8511
A17: 13 | B17: =A17*$C$2/1000 -> 7.15 | C17: HUAWEI SUN2000 6KTL L1 | D17: =$C$1 -> LONGI LR5-72HPH 550 (HiMO5 New) 550 Wp | E17: Medidor Monofásico DDSU | F17: Coplanaria aluminio | G17: =VLOOKUP($C$1,t.mod!$A$2:$H$28,8,)*A17 -> 1215.5 | H17: =VLOOKUP(C17,t.inv!$A$2:$H$261,8,) -> 780 | I17: =VLOOKUP(E17,t.met!$A$2:$F$13,6,) -> 95 | J17: =VLOOKUP(F17,t.est!$A$3:$F$11,6,)*A17 -> 416 | K17: =120+16*A17 -> 328 | L17: =VLOOKUP(A17,t.mon!$A$3:$F$263,6,) -> 1450 | M17: =SUM(G17:L17) -> 4284.5 | N17: =VLOOKUP(A17,t.coi!$A$2:$E$263,5) -> 1000 | O17: =M17+N17 -> 5284.5 | P17: =VLOOKUP(A17,t.mar!$A$1:$C$263,3)*O17 -> 1955.265 | Q17: =p_cee*2 -> 130 | R17: =(O17+P17+Q17)*0.21 -> 1547.6506 | S17: =O17+P17+Q17+R17 -> 8917.4156
A18: 14 | B18: =A18*$C$2/1000 -> 7.7 | C18: HUAWEI SUN2000 6KTL L1 | D18: =$C$1 -> LONGI LR5-72HPH 550 (HiMO5 New) 550 Wp | E18: Medidor Monofásico DDSU | F18: Coplanaria aluminio | G18: =VLOOKUP($C$1,t.mod!$A$2:$H$28,8,)*A18 -> 1309 | H18: =VLOOKUP(C18,t.inv!$A$2:$H$261,8,) -> 780 | I18: =VLOOKUP(E18,t.met!$A$2:$F$13,6,) -> 95 | J18: =VLOOKUP(F18,t.est!$A$3:$F$11,6,)*A18 -> 448 | K18: =120+16*A18 -> 344 | L18: =VLOOKUP(A18,t.mon!$A$3:$F$263,6,) -> 1500 | M18: =SUM(G18:L18) -> 4476 | N18: =VLOOKUP(A18,t.coi!$A$2:$E$263,5) -> 1100 | O18: =M18+N18 -> 5576 | P18: =VLOOKUP(A18,t.mar!$A$1:$C$263,3)*O18 -> 2063.12 | Q18: =p_cee*2 -> 130 | R18: =(O18+P18+Q18)*0.21 -> 1631.5152 | S18: =O18+P18+Q18+R18 -> 9400.6352
... A42: 26 | B42: =A42*$C$2/1000 -> 14.3 | C42: HUAWEI SUN2000 15KTL M2 | D42: =$C$1 -> LONGI LR5-72HPH 550 (HiMO5 New) 550 Wp | E42: Medidor Trifásico DTSU | F42: Coplanaria aluminio | G42: =VLOOKUP($C$1,t.mod!$A$2:$H$28,8,)*A42 -> 2431 | H42: =VLOOKUP(C42,t.inv!$A$2:$H$261,8,) -> 1669 | I42: =VLOOKUP(E42,t.met!$A$2:$F$13,6,) -> 135 | J42: =VLOOKUP(F42,t.est!$A$3:$F$11,6,)*A42 -> 832 | K42: =120+16*A42 -> 536 | L42: =VLOOKUP(A42,t.mon!$A$3:$F$263,6,) -> 2000 | M42: =SUM(G42:L42) -> 7603 | N42: =VLOOKUP(A42,t.coi!$A$2:$E$263,5) -> 1400 | O42: =M42+N42 -> 9003 | P42: =VLOOKUP(A42,t.mar!$A$1:$C$263,3)*O42 -> 3241.08 | Q42: =p_cee*2 -> 130 | R42: =(O42+P42+Q42)*0.21 -> 2598.5568 | S42: =O42+P42+Q42+R42 -> 14972.637
A44: Precios con todo incluído, salvo coste de Tasas/ICIO de Licencia de Obra.

Sheet TABLA ENPHASE
A1: Módulo | C1: LONGI LR5-72HPH 550 (HiMO5 New) 550 Wp | E1: MICROINVERSORES - ECOVIVIENDA
A2: Potencia (Wp) | C2: =VLOOKUP(C1,t.mod!A2:H28,7,) -> 550 | E2: Tarifa 2023.11
A5: UD | B5: Potencia Paneles (kW) | C5: Modelo Inversor | D5: Modelo Panel | E5: Medidor | F5: Estructura | G5: Coste Paneles (€) | H5: Coste Inversor (€) | I5: Coste Medida (€) | J5: Coste Estructura (€) | K5: Coste Cableado (€) | L5: Coste de Montaje (€) | M5: Coste directo (€) | N5: Coste indirecto (€) | O5: Coste total (€) | P5: Margen (€) | Q5: CEEs | R5: IVA (€) | S5: Precio con IVA (€)
A7: 3 | B7: =A7*$C$2/1000 -> 1.65 | C7: IQ8HC-72-M-INT | D7: =$C$1 -> LONGI LR5-72HPH 550 (HiMO5 New) 550 Wp | E7: Enphase Envoy-S Mono/Tri - Metered | F7: Coplanaria aluminio | G7: =VLOOKUP($C$1,t.mod!$A$2:$H$28,8,)*A7 -> 280.5 | H7: =VLOOKUP(C7,t.inv!$A$2:$H$261,8,)*A7 -> 395.55 | I7: =VLOOKUP(E7,t.met!$A$2:$F$13,6,) -> 301.63 | J7: =VLOOKUP(F7,t.est!$A$3:$F$11,6,)*A7 -> 96 | K7: =120+16*A7 -> 168 | L7: =VLOOKUP(A7,t.mon!$A$3:$F$263,6,) -> 850 | M7: =SUM(G7:L7) -> 2091.68 | N7: =VLOOKUP(A7,t.coi!$A$2:$E$263,5) -> 700 | O7: =M7+N7 -> 2791.68 | P7: =VLOOKUP(A7,t.mar!$A$1:$C$263,3)*O7 -> 1116.672 | Q7: =p_cee*2 -> 130 | R7: =(O7+P7+Q7)*0.21 -> 848.05392 | S7: =O7+P7+Q7+R7 -> 4886.4059
A8: 4 | B8: =A8*$C$2/1000 -> 2.2 | C8: IQ8HC-72-M-INT | D8: =$C$1 -> LONGI LR5-72HPH 550 (HiMO5 New) 550 Wp | E8: Enphase Envoy-S Mono/Tri - Metered | F8: Coplanaria aluminio | G8: =VLOOKUP($C$1,t.mod!$A$2:$H$28,8,)*A8 -> 374 | H8: =VLOOKUP(C8,t.inv!$A$2:$H$261,8,)*A8 -> 527.4 | I8: =VLOOKUP(E8,t.met!$A$2:$F$13,6,) -> 301.63 | J8: =VLOOKUP(F8,t.est!$A$3:$F$11,6,)*A8 -> 128 | K8: =120+16*A8 -> 184 | L8: =VLOOKUP(A8,t.mon!$A$3:$F$263,6,) -> 850 | M8: =SUM(G8:L8) -> 2365.03 | N8: =VLOOKUP(A8,t.coi!$A$2:$E$263,5) -> 700 | O8: =M8+N8 -> 3065.03 | P8: =VLOOKUP(A8,t.mar!$A$1:$C$263,3)*O8 -> 1226.012 | Q8: =p_cee*2 -> 130 | R8: =(O8+P8+Q8)*0.21 -> 928.41882 | S8: =O8+P8+Q8+R8 -> 5349.4608
A9: 5 | B9: =A9*$C$2/1000 -> 2.75 | C9: IQ8HC-72-M-INT | D9: =$C$1 -> LONGI LR5-72HPH 550 (HiMO5 New) 550 Wp | E9: Enphase Envoy-S Mono/Tri - Metered | F9: Coplanaria aluminio | G9: =VLOOKUP($C$1,t.mod!$A$2:$H$28,8,)*A9 -> 467.5 | H9: =VLOOKUP(C9,t.inv!$A$2:$H$261,8,)*A9 -> 659.25 | I9: =VLOOKUP(E9,t.met!$A$2:$F$13,6,) -> 301.63 | J9: =VLOOKUP(F9,t.est!$A$3:$F$11,6,)*A9 -> 160 | K9: =120+16*A9 -> 200 | L9: =VLOOKUP(A9,t.mon!$A$3:$F$263,6,) -> 900 | M9: =SUM(G9:L9) -> 2688.38 | N9: =VLOOKUP(A9,t.coi!$A$2:$E$263,5) -> 800 | O9: =M9+N9 -> 3488.38 | P9: =VLOOKUP(A9,t.mar!$A$1:$C$263,3)*O9 -> 1360.4682 | Q9: =p_cee*2 -> 130 | R9: =(O9+P9+Q9)*0.21 -> 1045.5581 | S9: =O9+P9+Q9+R9 -> 6024.4063
A10: 6 | B10: =A10*$C$2/1000 -> 3.3 | C10: IQ8HC-72-M-INT | D10: =$C$1 -> LONGI LR5-72HPH 550 (HiMO5 New) 550 Wp | E10: Enphase Envoy-S Mono/Tri - Metered | F10: Coplanaria aluminio | G10: =VLOOKUP($C$1,t.mod!$A$2:$H$28,8,)*A10 -> 561 | H10: =VLOOKUP(C10,t.inv!$A$2:$H$261,8,)*A10 -> 791.1 | I10: =VLOOKUP(E10,t.met!$A$2:$F$13,6,) -> 301.63 | J10: =VLOOKUP(F10,t.est!$A$3:$F$11,6,)*A10 -> 192 | K10: =120+16*A10 -> 216 | L10: =VLOOKUP(A10,t.mon!$A$3:$F$263,6,) -> 1050 | M10: =SUM(G10:L10) -> 3111.73 | N10: =VLOOKUP(A10,t.coi!$A$2:$E$263,5) -> 800 | O10: =M10+N10 -> 3911.73 | P10: =VLOOKUP(A10,t.mar!$A$1:$C$263,3)*O10 -> 1525.5747 | Q10: =p_cee*2 -> 130 | R10: =(O10+P10+Q10)*0.21 -> 1169.134 | S10: =O10+P10+Q10+R10 -> 6736.4387
A11: 7 | B11: =A11*$C$2/1000 -> 3.85 | C11: IQ8HC-72-M-INT | D11: =$C$1 -> LONGI LR5-72HPH 550 (HiMO5 New) 550 Wp | E11: Enphase Envoy-S Mono/Tri - Metered | F11: Coplanaria aluminio | G11: =VLOOKUP($C$1,t.mod!$A$2:$H$28,8,)*A11 -> 654.5 | H11: =VLOOKUP(C11,t.inv!$A$2:$H$261,8,)*A11 -> 922.95 | I11: =VLOOKUP(E11,t.met!$A$2:$F$13,6,) -> 301.63 | J11: =VLOOKUP(F11,t.est!$A$3:$F$11,6,)*A11 -> 224 | K11: =120+16*A11 -> 232 | L11: =VLOOKUP(A11,t.mon!$A$3:$F$263,6,) -> 1250 | M11: =SUM(G11:L11) -> 3585.08 | N11: =VLOOKUP(A11,t.coi!$A$2:$E$263,5) -> 850 | O11: =M11+N11 -> 4435.08 | P11: =VLOOKUP(A11,t.mar!$A$1:$C$263,3)*O11 -> 1685.3304 | Q11: =p_cee*2 -> 130 | R11: =(O11+P11+Q11)*0.21 -> 1312.5862 | S11: =O11+P11+Q11+R11 -> 7562.9966
A12: 8 | B12: =A12*$C$2/1000 -> 4.4 | C12: IQ8HC-72-M-INT | D12: =$C$1 -> LONGI LR5-72HPH 550 (HiMO5 New) 550 Wp | E12: Enphase Envoy-S Mono/Tri - Metered | F12: Coplanaria aluminio | G12: =VLOOKUP($C$1,t.mod!$A$2:$H$28,8,)*A12 -> 748 | H12: =VLOOKUP(C12,t.inv!$A$2:$H$261,8,)*A12 -> 1054.8 | I12: =VLOOKUP(E12,t.met!$A$2:$F$13,6,) -> 301.63 | J12: =VLOOKUP(F12,t.est!$A$3:$F$11,6,)*A12 -> 256 | K12: =120+16*A12 -> 248 | L12: =VLOOKUP(A12,t.mon!$A$3:$F$263,6,) -> 1250 | M12: =SUM(G12:L12) -> 3858.43 | N12: =VLOOKUP(A12,t.coi!$A$2:$E$263,5) -> 850 | O12: =M12+N12 -> 4708.43 | P12: =VLOOKUP(A12,t.mar!$A$1:$C$263,3)*O12 -> 1789.2034 | Q12: =p_cee*2 -> 130 | R12: =(O12+P12+Q12)*0.21 -> 1391.803 | S12: =O12+P12+Q12+R12 -> 8019.4364
A13: 9 | B13: =A13*$C$2/1000 -> 4.95 | C13: IQ8HC-72-M-INT | D13: =$C$1 -> LONGI LR5-72HPH 550 (HiMO5 New) 550 Wp | E13: Enphase Envoy-S Mono/Tri - Metered | F13: Coplanaria aluminio | G13: =VLOOKUP($C$1,t.mod!$A$2:$H$28,8,)*A13 -> 841.5 | H13: =VLOOKUP(C13,t.inv!$A$2:$H$261,8,)*A13 -> 1186.65 | I13: =VLOOKUP(E13,t.met!$A$2:$F$13,6,) -> 301.63 | J13: =VLOOKUP(F13,t.est!$A$3:$F$11,6,)*A13 -> 288 | K13: =120+16*A13 -> 264 | L13: =VLOOKUP(A13,t.mon!$A$3:$F$263,6,) -> 1350 | M13: =SUM(G13:L13) -> 4231.78 | N13: =VLOOKUP(A13,t.coi!$A$2:$E$263,5) -> 900 | O13: =M13+N13 -> 5131.78 | P13: =VLOOKUP(A13,t.mar!$A$1:$C$263,3)*O13 -> 1898.7586 | Q13: =p_cee*2 -> 130 | R13: =(O13+P13+Q13)*0.21 -> 1503.7131 | S13: =O13+P13+Q13+R13 -> 8664.2517
A14: 10 | B14: =A14*$C$2/1000 -> 5.5 | C14: IQ8HC-72-M-INT | D14: =$C$1 -> LONGI LR5-72HPH 550 (HiMO5 New) 550 Wp | E14: Enphase Envoy-S Mono/Tri - Metered | F14: Coplanaria aluminio | G14: =VLOOKUP($C$1,t.mod!$A$2:$H$28,8,)*A14 -> 935 | H14: =VLOOKUP(C14,t.inv!$A$2:$H$261,8,)*A14 -> 1318.5 | I14: =VLOOKUP(E14,t.met!$A$2:$F$13,6,) -> 301.63 | J14: =VLOOKUP(F14,t.est!$A$3:$F$11,6,)*A14 -> 320 | K14: =120+16*A14 -> 280 | L14: =VLOOKUP(A14,t.mon!$A$3:$F$263,6,) -> 1400 | M14: =SUM(G14:L14) -> 4555.13 | N14: =VLOOKUP(A14,t.coi!$A$2:$E$263,5) -> 950 | O14: =M14+N14 -> 5505.13 | P14: =VLOOKUP(A14,t.mar!$A$1:$C$263,3)*O14 -> 2036.8981 | Q14: =p_cee*2 -> 130 | R14: =(O14+P14+Q14)*0.21 -> 1611.1259 | S14: =O14+P14+Q14+R14 -> 9283.154
A15: 11 | B15: =A15*$C$2/1000 -> 6.05 | C15: IQ8HC-72-M-INT | D15: =$C$1 -> LONGI LR5-72HPH 550 (HiMO5 New) 550 Wp | E15: Enphase Envoy-S Mono/Tri - Metered | F15: Coplanaria aluminio | G15: =VLOOKUP($C$1,t.mod!$A$2:$H$28,8,)*A15 -> 1028.5 | H15: =VLOOKUP(C15,t.inv!$A$2:$H$261,8,)*A15 -> 1450.35 | I15: =VLOOKUP(E15,t.met!$A$2:$F$13,6,) -> 301.63 | J15: =VLOOKUP(F15,t.est!$A$3:$F$11,6,)*A15 -> 352 | K15: =120+16*A15 -> 296 | L15: =VLOOKUP(A15,t.mon!$A$3:$F$263,6,) -> 1400 | M15: =SUM(G15:L15) -> 4828.48 | N15: =VLOOKUP(A15,t.coi!$A$2:$E$263,5) -> 950 | O15: =M15+N15 -> 5778.48 | P15: =VLOOKUP(A15,t.mar!$A$1:$C$263,3)*O15 -> 2138.0376 | Q15: =p_cee*2 -> 130 | R15: =(O15+P15+Q15)*0.21 -> 1689.7687 | S15: =O15+P15+Q15+R15 -> 9736.2863
A16: 12 | B16: =A16*$C$2/1000 -> 6.6 | C16: IQ8HC-72-M-INT | D16: =$C$1 -> LONGI LR5-72HPH 550 (HiMO5 New) 550 Wp | E16: Enphase Envoy-S Mono/Tri - Metered | F16: Coplanaria aluminio | G16: =VLOOKUP($C$1,t.mod!$A$2:$H$28,8,)*A16 -> 1122 | H16: =VLOOKUP(C16,t.inv!$A$2:$H$261,8,)*A16 -> 1582.2 | I16: =VLOOKUP(E16,t.met!$A$2:$F$13,6,) -> 301.63 | J16: =VLOOKUP(F16,t.est!$A$3:$F$11,6,)*A16 -> 384 | K16: =120+16*A16 -> 312 | L16: =VLOOKUP(A16,t.mon!$A$3:$F$263,6,) -> 1450 | M16: =SUM(G16:L16) -> 5151.83 | N16: =VLOOKUP(A16,t.coi!$A$2:$E$263,5) -> 1000 | O16: =M16+N16 -> 6151.83 | P16: =VLOOKUP(A16,t.mar!$A$1:$C$263,3)*O16 -> 2276.1771 | Q16: =p_cee*2 -> 130 | R16: =(O16+P16+Q16)*0.21 -> 1797.1815 | S16: =O16+P16+Q16+R16 -> 10355.189
A17: 13 | B17: =A17*$C$2/1000 -> 7.15 | C17: IQ8HC-72-M-INT | D17: =$C$1 -> LONGI LR5-72HPH 550 (HiMO5 New) 550 Wp | E17: Enphase Envoy-S Mono/Tri - Metered | F17: Coplanaria aluminio | G17: =VLOOKUP($C$1,t.mod!$A$2:$H$28,8,)*A17 -> 1215.5 | H17: =VLOOKUP(C17,t.inv!$A$2:$H$261,8,)*A17 -> 1714.05 | I17: =VLOOKUP(E17,t.met!$A$2:$F$13,6,) -> 301.63 | J17: =VLOOKUP(F17,t.est!$A$3:$F$11,6,)*A17 -> 416 | K17: =120+16*A17 -> 328 | L17: =VLOOKUP(A17,t.mon!$A$3:$F$263,6,) -> 1450 | M17: =SUM(G17:L17) -> 5425.18 | N17: =VLOOKUP(A17,t.coi!$A$2:$E$263,5) -> 1000 | O17: =M17+N17 -> 6425.18 | P17: =VLOOKUP(A17,t.mar!$A$1:$C$263,3)*O17 -> 2377.3166 | Q17: =p_cee*2 -> 130 | R17: =(O17+P17+Q17)*0.21 -> 1875.8243 | S17: =O17+P17+Q17+R17 -> 10808.321
A18: 14 | B18: =A18*$C$2/1000 -> 7.7 | C18: IQ8HC-72-M-INT | D18: =$C$1 -> LONGI LR5-72HPH 550 (HiMO5 New) 550 Wp | E18: Enphase Envoy-S Mono/Tri - Metered | F18: Coplanaria aluminio | G18: =VLOOKUP($C$1,t.mod!$A$2:$H$28,8,)*A18 -> 1309 | H18: =VLOOKUP(C18,t.inv!$A$2:$H$261,8,)*A18 -> 1845.9 | I18: =VLOOKUP(E18,t.met!$A$2:$F$13,6,) -> 301.63 | J18: =VLOOKUP(F18,t.est!$A$3:$F$11,6,)*A18 -> 448 | K18: =120+16*A18 -> 344 | L18: =VLOOKUP(A18,t.mon!$A$3:$F$263,6,) -> 1500 | M18: =SUM(G18:L18) -> 5748.53 | N18: =VLOOKUP(A18,t.coi!$A$2:$E$263,5) -> 1100 | O18: =M18+N18 -> 6848.53 | P18: =VLOOKUP(A18,t.mar!$A$1:$C$263,3)*O18 -> 2533.9561 | Q18: =p_cee*2 -> 130 | R18: =(O18+P18+Q18)*0.21 -> 1997.6221 | S18: =O18+P18+Q18+R18 -> 11510.108
... A42: 26 | B42: =A42*$C$2/1000 -> 14.3 | C42: IQ8HC-72-M-INT | D42: =$C$1 -> LONGI LR5-72HPH 550 (HiMO5 New) 550 Wp | E42: Enphase Envoy-S Mono/Tri - Metered | F42: Coplanaria aluminio | G42: =VLOOKUP($C$1,t.mod!$A$2:$H$28,8,)*A42 -> 2431 | H42: =VLOOKUP(C42,t.inv!$A$2:$H$261,8,)*A42 -> 3428.1 | I42: =VLOOKUP(E42,t.met!$A$2:$F$13,6,) -> 301.63 | J42: =VLOOKUP(F42,t.est!$A$3:$F$11,6,)*A42 -> 832 | K42: =120+16*A42 -> 536 | L42: =VLOOKUP(A42,t.mon!$A$3:$F$263,6,) -> 2000 | M42: =SUM(G42:L42) -> 9528.73 | N42: =VLOOKUP(A42,t.coi!$A$2:$E$263,5) -> 1400 | O42: =M42+N42 -> 10928.73 | P42: =VLOOKUP(A42,t.mar!$A$1:$C$263,3)*O42 -> 3934.3428 | Q42: =p_cee*2 -> 130 | R42: =(O42+P42+Q42)*0.21 -> 3148.5453 | S42: =O42+P42+Q42+R42 -> 18141.618
A44: Precios con todo incluído, salvo coste de Tasas/ICIO de Licencia de Obra.

Sheet cálculos
B5: Situación Actual
B6: Mes | C6: Enero | D6: Febrero | E6: Marzo | F6: Abril | G6: Mayo | H6: Junio | I6: Julio | J6: Agosto | K6: Septiembre | L6: Octubre | M6: Noviembre | N6: Diciembre | P6: Total
B7: Demanda Mensual (kWh/mes) | C7: =t.con!C3 -> 2180.52 | D7: =t.con!D3 -> 1998.81 | E7: =t.con!E3 -> 1090.26 | F7: =t.con!F3 -> 1090.26 | G7: =t.con!G3 -> 1271.97 | H7: =t.con!H3 -> 1271.97 | I7: =t.con!I3 -> 1635.39 | J7: =t.con!J3 -> 1817.1 | ... N7: =t.con!N3 -> 2180.52 | P7: =SUM(C7:N7) -> 18171
B8: Gasto Mensual (€/mes) | C8: =C7*preciokwh -> 719.5716 | D8: =D7*preciokwh -> 659.6073 | E8: =E7*preciokwh -> 359.7858 | F8: =F7*preciokwh -> 359.7858 | G8: =G7*preciokwh -> 419.7501 | H8: =H7*preciokwh -> 419.7501 | I8: =I7*preciokwh -> 539.6787 | J8: =J7*preciokwh -> 599.643 | ... N8: =N7*preciokwh -> 719.5716 | P8: =SUM(C8:N8) -> 5996.43
B9: Emisiones de CO2 (kg/mes) | C9: =C7*dioxido -> 558.21312 | D9: =D7*dioxido -> 511.69536 | E9: =E7*dioxido -> 279.10656 | F9: =F7*dioxido -> 279.10656 | G9: =G7*dioxido -> 325.62432 | H9: =H7*dioxido -> 325.62432 | I9: =I7*dioxido -> 418.65984 | J9: =J7*dioxido -> 465.1776 | ... N9: =N7*dioxido -> 558.21312 | P9: =SUM(C9:N9) -> 4651.776
B10: Producción FV
B11: Mes | C11: Enero | D11: Febrero | E11: Marzo | F11: Abril | G11: Mayo | H11: Junio | I11: Julio | J11: Agosto | K11: Septiembre | L11: Octubre | M11: Noviembre | N11: Diciembre | P11: Total
B12: Referencia PVGIS 0º Azoimut y 35º Inclinación | C12: 118.59 | D12: 118.19 | E12: 140.32 | F12: 142.16 | G12: 155.06 | H12: 153.95 | I12: 163.58 | J12: 161.53 | K12: 144.55 | L12: 132.32 | M12: 112.65 | N12: 113.4 | P12: =SUM(C12:N12) -> 1656.3
B13: Coeficiente Mensual | C13: =C12/$P$12 -> 0.071599348 | D13: =D12/$P$12 -> 0.071357846 | E13: =E12/$P$12 -> 0.084718952 | F13: =F12/$P$12 -> 0.085829862 | G13: =G12/$P$12 -> 0.093618306 | H13: =H12/$P$12 -> 0.092948137 | I13: =I12/$P$12 -> 0.098762302 | J13: =J12/$P$12 -> 0.097524603 | ... N13: =N12/$P$12 -> 0.068465858 | P13: =SUM(C13:N13) -> 1
B14: Producción FV (kWh/mes) | C14: =$P$14*C13 -> 1812.8418 | D14: =$P$14*D13 -> 1806.7271 | E14: =$P$14*E13 -> 2145.0203 | F14: =$P$14*F13 -> 2173.1477 | G14: =$P$14*G13 -> 2370.3453 | H14: =$P$14*H13 -> 2353.3771 | I14: =$P$14*I13 -> 2500.5874 | J14: =$P$14*J13 -> 2469.2498 | ... N14: =$P$14*N13 -> 1733.5042 | P14: =p_gen*kwhkwp -> 25319.25
B16: Cálculo de Reducción media de la demanda | C16: Sin Baterías
B17: Mes | C17: Enero | D17: Febrero | E17: Marzo | F17: Abril | G17: Mayo | H17: Junio | I17: Julio | J17: Agosto | K17: Septiembre | L17: Octubre | M17: Noviembre | N17: Diciembre | P17: Total
B18: Cálculo de Reducción media de demanda (%) | C18: =incentivo!C43 -> 0.50490612 | D18: =incentivo!C43 -> 0.50490612 | E18: =incentivo!C43 -> 0.50490612 | F18: =incentivo!C43 -> 0.50490612 | G18: =incentivo!C43 -> 0.50490612 | H18: =incentivo!C43 -> 0.50490612 | I18: =incentivo!C43 -> 0.50490612 | J18: =incentivo!C43 -> 0.50490612 | K18: =incentivo!C43 -> 0.50490612 | L18: =incentivo!C43 -> 0.50490612 | M18: =incentivo!C43 -> 0.50490612 | N18: =incentivo!C43 -> 0.50490612
B19: Incremento de Producción respecto a producción media (kWh) | C19: =C14-$P$14/12 -> -297.09571 | D19: =D14-$P$14/12 -> -303.21036 | E19: =E14-$P$14/12 -> 35.082822 | F19: =F14-$P$14/12 -> 63.210227 | G19: =G14-$P$14/12 -> 260.40779 | H19: =H14-$P$14/12 -> 243.43963 | I19: =I14-$P$14/12 -> 390.6499 | J19: =J14-$P$14/12 -> 359.31231 | ... N19: =N14-$P$14/12 -> -376.43333 | P19: =SUM(C19:N19) -> -2.5011104e-12
B20: Incremento de Demanda respecto a demanda media (kWh) | C20: =C7-$P$7/12 -> 666.27 | D20: =D7-$P$7/12 -> 484.56 | E20: =E7-$P$7/12 -> -423.99 | F20: =F7-$P$7/12 -> -423.99 | G20: =G7-$P$7/12 -> -242.28 | H20: =H7-$P$7/12 -> -242.28 | I20: =I7-$P$7/12 -> 121.14 | J20: =J7-$P$7/12 -> 302.85 | ... N20: =N7-$P$7/12 -> 666.27 | P20: =SUM(C20:N20) -> 0
B21: Incremento Porcentual de Producción respecto media (%) | C21: =C19/$P$14 -> -0.011733985 | D21: =D19/$P$14 -> -0.011975488 | E21: =E19/$P$14 -> 0.0013856185 | F21: =F19/$P$14 -> 0.0024965284 | G21: =G19/$P$14 -> 0.010284973 | H21: =H19/$P$14 -> 0.0096148041 | I21: =I19/$P$14 -> 0.015428968 | J21: =J19/$P$14 -> 0.01419127 | ... N21: =N19/$P$14 -> -0.014867476 | P21: =SUM(C21:N21) -> -9.7144515e-17
B22: Incremento Porcentual de Demanda respecto media (%) | C22: =C20/$P$7 -> 0.036666667 | D22: =D20/$P$7 -> 0.026666667 | E22: =E20/$P$7 -> -0.023333333 | F22: =F20/$P$7 -> -0.023333333 | G22: =G20/$P$7 -> -0.013333333 | H22: =H20/$P$7 -> -0.013333333 | I22: =I20/$P$7 -> 0.0066666667 | J22: =J20/$P$7 -> 0.016666667 | ... N22: =N20/$P$7 -> 0.036666667 | P22: =SUM(C22:N22) -> 0
B23: Autoconsumo, Reducción de la Demanda Corregida (%) | C23: =C18+C21-C22 -> 0.45650546 | D23: =D18+D21-D22 -> 0.46626396 | E23: =E18+E21-E22 -> 0.52962507 | F23: =F18+F21-F22 -> 0.53073598 | G23: =G18+G21-G22 -> 0.52852442 | H23: =H18+H21-H22 -> 0.52785425 | I23: =I18+I21-I22 -> 0.51366842 | J23: =J18+J21-J22 -> 0.50243072 | ... N23: =N18+N21-N22 -> 0.45337197 | P23: =SUM(C23:N23)/12 -> 0.50490612
B25: Autoconsumo y Autosuficiencia | C25: Sin Baterías
B26: Mes | C26: Enero | D26: Febrero | E26: Marzo | F26: Abril | G26: Mayo | H26: Junio | I26: Julio | J26: Agosto | K26: Septiembre | L26: Octubre | M26: Noviembre | N26: Diciembre | P26: Total
B27: Autoconsumo, Reducción de la Demanda (kWh/mes) | C27: =C7*C23 -> 995.41929 | D27: =D7*D23 -> 931.97307 | E27: =E7*E23 -> 577.42903 | F27: =F7*F23 -> 578.64021 | G27: =G7*G23 -> 672.26721 | H27: =H7*H23 -> 671.41477 | I27: =I7*I23 -> 840.04819 | J27: =J7*J23 -> 912.96686 | ... N27: =N7*N23 -> 988.58666 | P27: =SUM(C27:N27) -> 9037.6685
B28: Demanda mensual (kWh/mes) | C28: =C7-C27 -> 1185.1007 | D28: =D7-D27 -> 1066.8369 | E28: =E7-E27 -> 512.83097 | F28: =F7-F27 -> 511.61979 | G28: =G7-G27 -> 599.70279 | H28: =H7-H27 -> 600.55523 | I28: =I7-I27 -> 795.34181 | J28: =J7-J27 -> 904.13314 | ... N28: =N7-N27 -> 1191.9333 | P28: =SUM(C28:N28) -> 9133.3315
B29: Excedentes (kWh/mes) | C29: =C14-(C7-C28) -> 817.4225 | D29: =D14-(D7-D28) -> 874.75407 | E29: =E14-E27 -> 1567.5913 | F29: =F14-F27 -> 1594.5075 | G29: =G14-G27 -> 1698.0781 | H29: =H14-H27 -> 1681.9624 | I29: =I14-I27 -> 1660.5392 | J29: =J14-J27 -> 1556.2829 | K29: =K14-K27 -> 1629.4694 | L29: =L14-L27 -> 1450.5642 | ... N29: =N14-N27 -> 744.91751 | P29: =SUM(C29:N29) -> 16281.582 | R29: =C7-C28 -> 995.41929
B30: Gasto | C30: Sin Baterías
B31: Mes | C31: Enero | D31: Febrero | E31: Marzo | F31: Abril | G31: Mayo | H31: Junio | I31: Julio | J31: Agosto | K31: Septiembre | L31: Octubre | M31: Noviembre | N31: Diciembre | P31: Total
B32: Gasto mensual (€/mes) | C32: =C28*preciokwh -> 391.08323 | D32: =D28*preciokwh -> 352.05619 | E32: =E28*preciokwh -> 169.23422 | F32: =F28*preciokwh -> 168.83453 | G32: =G28*preciokwh -> 197.90192 | H32: =H28*preciokwh -> 198.18322 | I32: =I28*preciokwh -> 262.4628 | J32: =J28*preciokwh -> 298.36394 | ... N32: =N28*preciokwh -> 393.338 | P32: =SUM(C32:N32) -> 3013.9994
B33: Ahorro mensual (€/mes) | C33: =C27*preciokwh+C29*precioexc -> 414.31773 | D33: =D27*preciokwh+D29*precioexc -> 399.40029 | E33: =E27*preciokwh+E29*precioexc -> 355.14866 | F33: =F27*preciokwh+F29*precioexc -> 358.37456 | G33: =G27*preciokwh+G29*precioexc -> 400.14638 | H33: =H27*preciokwh+H29*precioexc -> 398.17292 | I33: =I27*preciokwh+I29*precioexc -> 451.57252 | J33: =J27*preciokwh+J29*precioexc -> 464.68877 | ... N33: =N27*preciokwh+N29*precioexc -> 404.44993 | P33: =SUM(C33:N33) -> 4691.9967
B34: Emisiones | C34: Sin Baterías
B35: Mes | C35: Enero | D35: Febrero | E35: Marzo | F35: Abril | G35: Mayo | H35: Junio | I35: Julio | J35: Agosto | K35: Septiembre | L35: Octubre | M35: Noviembre | N35: Diciembre | P35: Total
B36: Emisiones de CO2 (kg/mes) | C36: =C28*dioxido -> 303.38578 | D36: =D28*dioxido -> 273.11025 | E36: =E28*dioxido -> 131.28473 | F36: =F28*dioxido -> 130.97467 | G36: =G28*dioxido -> 153.52391 | H36: =H28*dioxido -> 153.74214 | I36: =I28*dioxido -> 203.6075 | J36: =J28*dioxido -> 231.45808 | ... N36: =N28*dioxido -> 305.13494 | P36: =SUM(C36:N36) -> 2338.1329
B38: Cálculo de Reducción media de la demanda | C38: Con Baterías
B39: Mes | C39: Enero | D39: Febrero | E39: Marzo | F39: Abril | G39: Mayo | H39: Junio | I39: Julio | J39: Agosto | K39: Septiembre | L39: Octubre | M39: Noviembre | N39: Diciembre | P39: Total
B40: Cálculo de Reducción media de demanda (%) | C40: =incentivo!D43 -> #DIV/0! | D40: =incentivo!D43 -> #DIV/0! | E40: =incentivo!D43 -> #DIV/0! | F40: =incentivo!D43 -> #DIV/0! | G40: =incentivo!D43 -> #DIV/0! | H40: =incentivo!D43 -> #DIV/0! | I40: =incentivo!D43 -> #DIV/0! | J40: =incentivo!D43 -> #DIV/0! | K40: =incentivo!D43 -> #DIV/0! | L40: =incentivo!D43 -> #DIV/0! | M40: =incentivo!D43 -> #DIV/0! | N40: =incentivo!D43 -> #DIV/0!
B41: Incremento de Producción respecto a producción media (kWh) | C41: =C19 -> -297.09571 | D41: =D19 -> -303.21036 | E41: =E19 -> 35.082822 | F41: =F19 -> 63.210227 | G41: =G19 -> 260.40779 | H41: =H19 -> 243.43963 | I41: =I19 -> 390.6499 | J41: =J19 -> 359.31231 | ... N41: =N19 -> -376.43333 | P41: =SUM(C41:N41) -> -2.5011104e-12
B42: Incremento de Demanda respecto a demanda media (kWh) | C42: =C20 -> 666.27 | D42: =D20 -> 484.56 | E42: =E20 -> -423.99 | F42: =F20 -> -423.99 | G42: =G20 -> -242.28 | H42: =H20 -> -242.28 | I42: =I20 -> 121.14 | J42: =J20 -> 302.85 | ... N42: =N20 -> 666.27 | P42: =SUM(C42:N42) -> 0
B43: Incremento Porcentual de Producción respecto media (%) | C43: =C21 -> -0.011733985 | D43: =D21 -> -0.011975488 | E43: =E21 -> 0.0013856185 | F43: =F21 -> 0.0024965284 | G43: =G21 -> 0.010284973 | H43: =H21 -> 0.0096148041 | I43: =I21 -> 0.015428968 | J43: =J21 -> 0.01419127 | ... N43: =N21 -> -0.014867476 | P43: =SUM(C43:N43) -> -9.7144515e-17
B44: Incremento Porcentual de Demanda respecto media (%) | C44: =C22 -> 0.036666667 | D44: =D22 -> 0.026666667 | E44: =E22 -> -0.023333333 | F44: =F22 -> -0.023333333 | G44: =G22 -> -0.013333333 | H44: =H22 -> -0.013333333 | I44: =I22 -> 0.0066666667 | J44: =J22 -> 0.016666667 | ... N44: =N22 -> 0.036666667 | P44: =SUM(C44:N44) -> 0
B45: Autoconsumo, Reducción de la Demanda Corregida (%) | C45: =C40+C43-C44 -> #DIV/0! | D45: =D40+D43-D44 -> #DIV/0! | E45: =E40+E43-E44 -> #DIV/0! | F45: =F40+F43-F44 -> #DIV/0! | G45: =G40+G43-G44 -> #DIV/0! | H45: =H40+H43-H44 -> #DIV/0! | I45: =I40+I43-I44 -> #DIV/0! | J45: =J40+J43-J44 -> #DIV/0! | ... N45: =N40+N43-N44 -> #DIV/0! | P45: =SUM(C45:N45)/12 -> #DIV/0!
B47: Autoconsumo y Autosuficiencia | C47: Con Baterías
B48: Mes | C48: Enero | D48: Febrero | E48: Marzo | F48: Abril | G48: Mayo | H48: Junio | I48: Julio | J48: Agosto | K48: Septiembre | L48: Octubre | M48: Noviembre | N48: Diciembre | P48: Total
B49: Autoconsumo, Reducción de la Demanda (kWh/mes) | C49: =C7*C45 -> #DIV/0! | D49: =D7*D45 -> #DIV/0! | E49: =E7*E45 -> #DIV/0! | F49: =F7*F45 -> #DIV/0! | G49: =G7*G45 -> #DIV/0! | H49: =H7*H45 -> #DIV/0! | I49: =I7*I45 -> #DIV/0! | J49: =J7*J45 -> #DIV/0! | ... N49: =N7*N45 -> #DIV/0! | P49: =SUM(C49:N49) -> #DIV/0!
B50: Demanda mensual (kWh/mes) | C50: =C7-C49 -> #DIV/0! | D50: =D7-D49 -> #DIV/0! | E50: =E7-E49 -> #DIV/0! | F50: =F7-F49 -> #DIV/0! | G50: =G7-G49 -> #DIV/0! | H50: =H7-H49 -> #DIV/0! | I50: =I7-I49 -> #DIV/0! | J50: =J7-J49 -> #DIV/0! | ... N50: =N7-N49 -> #DIV/0! | P50: =SUM(C50:N50) -> #DIV/0!
B51: Excedentes (kWh/mes) | C51: =C14-C49 -> #DIV/0! | D51: =D14-D49 -> #DIV/0! | E51: =E14-E49 -> #DIV/0! | F51: =F14-F49 -> #DIV/0! | G51: =G14-G49 -> #DIV/0! | H51: =H14-H49 -> #DIV/0! | I51: =I14-I49 -> #DIV/0! | J51: =J14-J49 -> #DIV/0! | ... N51: =N14-N49 -> #DIV/0! | P51: =SUM(C51:N51) -> #DIV/0!
B52: Gasto | C52: Con Baterías
B53: Mes | C53: Enero | D53: Febrero | E53: Marzo | F53: Abril | G53: Mayo | H53: Junio | I53: Julio | J53: Agosto | K53: Septiembre | L53: Octubre | M53: Noviembre | N53: Diciembre | P53: Total
B54: Gasto mensual (€/mes) | C54: =C50*preciokwh -> #DIV/0! | D54: =D50*preciokwh -> #DIV/0! | E54: =E50*preciokwh -> #DIV/0! | F54: =F50*preciokwh -> #DIV/0! | G54: =G50*preciokwh -> #DIV/0! | H54: =H50*preciokwh -> #DIV/0! | I54: =I50*preciokwh -> #DIV/0! | J54: =J50*preciokwh -> #DIV/0! | ... N54: =N50*preciokwh -> #DIV/0! | P54: =SUM(C54:N54) -> #DIV/0!
B55: Ahorro mensual (€/mes) | C55: =C49*preciokwh+C51*precioexc -> #DIV/0! | D55: =D49*preciokwh+D51*precioexc -> #DIV/0! | E55: =E49*preciokwh+E51*precioexc -> #DIV/0! | F55: =F49*preciokwh+F51*precioexc -> #DIV/0! | G55: =G49*preciokwh+G51*precioexc -> #DIV/0! | H55: =H49*preciokwh+H51*precioexc -> #DIV/0! | I55: =I49*preciokwh+I51*precioexc -> #DIV/0! | J55: =J49*preciokwh+J51*precioexc -> #DIV/0! | ... N55: =N49*preciokwh+N51*precioexc -> #DIV/0! | P55: =SUM(C55:N55) -> #DIV/0!
B56: Emisiones | C56: Con Baterías
B57: Mes | C57: Enero | D57: Febrero | E57: Marzo | F57: Abril | G57: Mayo | H57: Junio | I57: Julio | J57: Agosto | K57: Septiembre | L57: Octubre | M57: Noviembre | N57: Diciembre | P57: Total
B58: Emisiones de CO2 (kg/mes) | C58: =C50*dioxido -> #DIV/0! | D58: =D50*dioxido -> #DIV/0! | E58: =E50*dioxido -> #DIV/0! | F58: =F50*dioxido -> #DIV/0! | G58: =G50*dioxido -> #DIV/0! | H58: =H50*dioxido -> #DIV/0! | I58: =I50*dioxido -> #DIV/0! | J58: =J50*dioxido -> #DIV/0! | ... N58: =N50*dioxido -> #DIV/0! | P58: =SUM(C58:N58) -> #DIV/0!

Sheet finan
C2: Financiación | D2: Sin Bateria | E2: Con Batería | F2: Sólo Batería
C3: Presupuesto total, con IVA (€) | D3: =ppto!G44 -> 19994.921 | E3: =ppto!H44 -> 19994.921 | F3: =ppto!I44 -> 5894.515
C4: Financiación a 12 meses | D4: =D3*fin12m -> 1778.9881 | E4: =E3*fin12m -> 1778.9881 | F4: =F3*fin12m -> 524.44679
C5: Financiación a 24 meses | D5: =D3*fin24m -> 924.48516 | E5: =E3*fin24m -> 924.48516 | F5: =F3*fin24m -> 272.5388
C6: Financiación a 120 meses | D6: =D3*fin120m -> 247.17721 | E6: =E3*fin120m -> 247.17721 | F6: =F3*fin120m -> 72.867994

Sheet exp0
B2: =empresa -> 0
B3: =nombre&" "&apellidos | C3: =fecha -> 45568
B4: =nif
B5: =telefono
B6: =direccion
B7: =cp&" "&localidad&" - "&provincia -> -
B8: =email
C13: ="r."&descuento*100 -> r.0 | E13: =num_mod -> 27 | G13: =p_gen -> 16.335 | H13: =cap_bat -> 0 | I13: =cálculos!P14 -> 25319.25 | J13: =cálculos!P33 -> 4691.9967 | K13: =cálculos!P55 -> #DIV/0!
E14: SIN BATERÍA | G14: CON BATERÍA | I14: SOLO BATERÍA | J14: SIN BATERÍA | K14: CON BATERÍA | L14: SOLO BATERÍA
D15: Sin IVA | E15: =ppto!G32 -> 16524.728 | G15: =ppto!H32 -> 16524.728 | I15: =ppto!I32 -> 4871.5
D16: Con IVA | E16: =ppto!G44 -> 19994.921 | G16: =ppto!H44 -> 19994.921 | I16: =ppto!I44 -> 5894.515 | J16: =E16 -> 19994.921 | K16: =G16 -> 19994.921 | L16: =I16 -> 5894.515
D17: Ayudas | E17: =-incentivo!C36 -> 0 | G17: =-incentivo!D36 -> 0 | I17: =-incentivo!E36 -> 0 | J17: =-E17 -> 0 | K17: =-G17 -> 0 | L17: =-I17 -> 0
D18: Total con Ayudas | E18: =E16+E17 -> 19994.921 | G18: =G16+G17 -> 19994.921 | I18: =I16+I17 -> 5894.515 | J18: =E18 -> 19994.921 | K18: =G18 -> 19994.921 | L18: =I18 -> 5894.515
C20: 10 años | E20: =finan!D6 -> 247.17721 | G20: =finan!E6 -> 247.17721 | I20: =finan!F6 -> 72.867994
C21: 2 años | E21: =finan!D5 -> 924.48516 | G21: =finan!E5 -> 924.48516 | I21: =finan!F5 -> 272.5388
C22: 1 año | E22: =finan!D4 -> 1778.9881 | G22: =finan!E4 -> 1778.9881 | I22: =finan!F4 -> 524.44679
E25: =incentivo!C37 -> 0 | G25: =incentivo!D37 -> 0 | I25: =incentivo!E37 -> 0 | J25: =E25 -> 0 | K25: =G25 -> 0 | L25: =I25 -> 0
E27: =programa -> Sinayuda | J27: =E27 -> Sinayuda | K27: =J27 -> Sinayuda | L27: =K27 -> Sinayuda
C29: =datos!F113 -> Excluídas | H29: Aceptación | J29: =adelanto -> 500 | K29: =adelanto -> 500 | L29: =adelanto -> 500
H30: Antes de Instalar | J30: =(ppto!G44/2)-adelanto -> 9497.4604 | K30: =(ppto!H44/2)-adelanto -> 9497.4604 | L30: =(ppto!I44/2)-adelanto -> 2447.2575
H31: Después de Instalar | J31: =ppto!G44-exp0!J29-exp0!J30 -> 9997.4604 | K31: =ppto!H44-exp0!K29-exp0!K30 -> 9997.4604 | L31: =ppto!I44-exp0!L29-exp0!L30 -> 2947.2575

Sheet exp2
B3: Producción Fovotolvaica | D3: =cálculos!P14 -> 25319.25 | K3: Producción Fovotolvaica | M3: =cálculos!P14 -> 25319.25
B5: Demanda Actual de la Red | D5: =cálculos!P7 -> 18171 | K5: Demanda Actual de la Red | M5: =cálculos!P7 -> 18171
B7: Demanda Futura de la Red | D7: =cálculos!P28 -> 9133.3315 | K7: Demanda Futura de la Red | M7: =cálculos!P50 -> #DIV/0!
B9: Autoconsumo | D9: =cálculos!P27 -> 9037.6685 | K9: Autoconsumo | M9: =cálculos!P49 -> #DIV/0!
B11: Excedente | D11: =cálculos!P29 -> 16281.582 | K11: Excedente | M11: =cálculos!P51 -> #DIV/0!
B13: Reducción de la Demanda de la Red: | D13: =cálculos!P23 -> 0.50490612
B70: Producción | C70: #FFD100
B71: Demanda Actual de la Red | C71: #FF3B3B
B72: Demanda Futura de la Red | C72: #FF33CC
B73: Autoconsumo | C73: #30F030
B74: Excedente | C74: #00B0F0

Sheet exp3
A1: Razón Social: | B1: =empresa -> 0 | C1: Dirección: | D1: =direccion
A2: NIF: | B2: =nif | C2: Código postal: | D2: =cp
A3: Nombre: | B3: =nombre | C3: Localidad: | D3: =localidad
A4: Apellidos: | B4: =apellidos | C4: Provincia: | D4: =provincia
A5: Email: | B5: =email | C5: CUPS: | D5: =cups
A6: Teléfono: | B6: =telefono | C6: Fecha: | D6: =fecha -> 45568

Sheet exp4
B1: ="Autoconsumo (Sin Baterías) de "&p_gen&" kW" -> Autoconsumo (Sin Baterías) de 16,335 kW | L1: Instalación Con baterías
B3: AÑO | C3: DEMANDA ACTUAL | D3: DEMANDA FUTURA | F3: PRODUCCIÓN FOTOVOLTAICA | G3: AUTOCONSUMO | J3: EXCEDENTE | L3: AÑO | M3: DEMANDA ACTUAL | N3: DEMANDA FUTURA | P3: PRODUCCIÓN FOTOVOLTAICA | Q3: AUTOCONSUMO | T3: EXCEDENTE
C4: (kWh/año) | D4: (kWh/año) | E4: Reducción de demanda (%) | F4: (kWh/año) | G4: Directo (kWh/año) | H4: Indirecto (kWh/año) | I4: Total (kWh/año) | J4: (kWh/año) | M4: (kWh/año) | N4: (kWh/año) | O4: (%) | P4: (kWh/año) | Q4: Directo (kWh/año) | R4: Indirecto (kWh/año) | S4: Total (kWh/año) | T4: (kWh/año)
B5: 0 | L5: 0
B6: 1 | C6: =t.con!O3 -> 18171 | D6: =cálculos!P28 -> 9133.3315 | E6: =cálculos!P23 -> 0.50490612 | F6: =cálculos!P14 -> 25319.25 | G6: =cálculos!P27 -> 9037.6685 | H6: 0 | I6: =G6+H6 -> 9037.6685 | J6: =cálculos!P29 -> 16281.582 | L6: 1 | M6: =cálculos!P7 -> 18171 | N6: =cálculos!P50 -> #DIV/0! | O6: =cálculos!P45 -> #DIV/0! | P6: =cálculos!P14 -> 25319.25 | Q6: =cálculos!P27 -> 9037.6685 | R6: =cálculos!P49-Q6 -> #DIV/0! | S6: =Q6+R6 -> #DIV/0! | T6: =P6-S6 -> #DIV/0!
B7: 2 | C7: =$C$6 -> 18171 | D7: =C7-I7 -> 9201.7467 | E7: =1-D7/C7 -> 0.49360263 | F7: =F6*coefper -> 25127.583 | G7: =G6*coefper -> 8969.2533 | H7: 0 | I7: =G7+H7 -> 8969.2533 | J7: =F7-I7 -> 16158.33 | L7: 2 | M7: =$M$6 -> 18171 | N7: =M7-S7 -> #DIV/0! | O7: =1-N7/M7 -> #DIV/0! | P7: =P6*coefper -> 25127.583 | Q7: =Q6*coefper -> 8969.2533 | R7: =R6-(1-coefper)*(R6/S6)*R6 -> #DIV/0! | S7: =Q7+R7 -> #DIV/0! | T7: =P7-S7 -> #DIV/0!
B8: 3 | C8: =$C$6 -> 18171 | D8: =C8-I8 -> 9269.6439 | E8: =1-D8/C8 -> 0.48986605 | F8: =F7*coefper -> 24937.367 | G8: =G7*coefper -> 8901.3561 | H8: 0 | I8: =G8+H8 -> 8901.3561 | J8: =F8-I8 -> 16036.011 | L8: 3 | M8: =$M$6 -> 18171 | N8: =M8-S8 -> #DIV/0! | O8: =1-N8/M8 -> #DIV/0! | P8: =P7*coefper -> 24937.367 | Q8: =Q7*coefper -> 8901.3561 | R8: =R7-(1-coefper)*(R7/S7)*R7 -> #DIV/0! | S8: =Q8+R8 -> #DIV/0! | T8: =P8-S8 -> #DIV/0!
B9: 4 | C9: =$C$6 -> 18171 | D9: =C9-I9 -> 9337.0272 | E9: =1-D9/C9 -> 0.48615777 | F9: =F8*coefper -> 24748.592 | G9: =G8*coefper -> 8833.9728 | H9: 0 | I9: =G9+H9 -> 8833.9728 | J9: =F9-I9 -> 15914.619 | L9: 4 | M9: =$M$6 -> 18171 | N9: =M9-S9 -> #DIV/0! | O9: =1-N9/M9 -> #DIV/0! | P9: =P8*coefper -> 24748.592 | Q9: =Q8*coefper -> 8833.9728 | R9: =R8-(1-coefper)*(R8/S8)*R8 -> #DIV/0! | S9: =Q9+R9 -> #DIV/0! | T9: =P9-S9 -> #DIV/0!
B10: 5 | C10: =$C$6 -> 18171 | D10: =C10-I10 -> 9403.9004 | E10: =1-D10/C10 -> 0.48247755 | F10: =F9*coefper -> 24561.245 | G10: =G9*coefper -> 8767.0996 | H10: 0 | I10: =G10+H10 -> 8767.0996 | J10: =F10-I10 -> 15794.145 | L10: 5 | M10: =$M$6 -> 18171 | N10: =M10-S10 -> #DIV/0! | O10: =1-N10/M10 -> #DIV/0! | P10: =P9*coefper -> 24561.245 | Q10: =Q9*coefper -> 8767.0996 | R10: =R9-(1-coefper)*(R9/S9)*R9 -> #DIV/0! | S10: =Q10+R10 -> #DIV/0! | T10: =P10-S10 -> #DIV/0!
B11: 6 | C11: =$C$6 -> 18171 | D11: =C11-I11 -> 9470.2673 | E11: =1-D11/C11 -> 0.4788252 | F11: =F10*coefper -> 24375.316 | G11: =G10*coefper -> 8700.7327 | H11: 0 | I11: =G11+H11 -> 8700.7327 | J11: =F11-I11 -> 15674.583 | L11: 6 | M11: =$M$6 -> 18171 | N11: =M11-S11 -> #DIV/0! | O11: =1-N11/M11 -> #DIV/0! | P11: =P10*coefper -> 24375.316 | Q11: =Q10*coefper -> 8700.7327 | R11: =R10-(1-coefper)*(R10/S10)*R10 -> #DIV/0! | S11: =Q11+R11 -> #DIV/0! | T11: =P11-S11 -> #DIV/0!
B12: 7 | C12: =$C$6 -> 18171 | D12: =C12-I12 -> 9536.1319 | E12: =1-D12/C12 -> 0.47520049 | F12: =F11*coefper -> 24190.795 | G12: =G11*coefper -> 8634.8681 | H12: 0 | I12: =G12+H12 -> 8634.8681 | J12: =F12-I12 -> 15555.927 | L12: 7 | M12: =$M$6 -> 18171 | N12: =M12-S12 -> #DIV/0! | O12: =1-N12/M12 -> #DIV/0! | P12: =P11*coefper -> 24190.795 | Q12: =Q11*coefper -> 8634.8681 | R12: =R11-(1-coefper)*(R11/S11)*R11 -> #DIV/0! | S12: =Q12+R12 -> #DIV/0! | T12: =P12-S12 -> #DIV/0!
B13: 8 | C13: =$C$6 -> 18171 | D13: =C13-I13 -> 9601.4978 | E13: =1-D13/C13 -> 0.47160322 | F13: =F12*coefper -> 24007.671 | G13: =G12*coefper -> 8569.5022 | H13: 0 | I13: =G13+H13 -> 8569.5022 | J13: =F13-I13 -> 15438.169 | L13: 8 | M13: =$M$6 -> 18171 | N13: =M13-S13 -> #DIV/0! | O13: =1-N13/M13 -> #DIV/0! | P13: =P12*coefper -> 24007.671 | Q13: =Q12*coefper -> 8569.5022 | R13: =R12-(1-coefper)*(R12/S12)*R12 -> #DIV/0! | S13: =Q13+R13 -> #DIV/0! | T13: =P13-S13 -> #DIV/0!
B14: 9 | C14: =$C$6 -> 18171 | D14: =C14-I14 -> 9666.369 | E14: =1-D14/C14 -> 0.46803319 | F14: =F13*coefper -> 23825.933 | G14: =G13*coefper -> 8504.631 | H14: 0 | I14: =G14+H14 -> 8504.631 | J14: =F14-I14 -> 15321.302 | L14: 9 | M14: =$M$6 -> 18171 | N14: =M14-S14 -> #DIV/0! | O14: =1-N14/M14 -> #DIV/0! | P14: =P13*coefper -> 23825.933 | Q14: =Q13*coefper -> 8504.631 | R14: =R13-(1-coefper)*(R13/S13)*R13 -> #DIV/0! | S14: =Q14+R14 -> #DIV/0! | T14: =P14-S14 -> #DIV/0!
B15: 10 | C15: =$C$6 -> 18171 | D15: =C15-I15 -> 9730.749 | E15: =1-D15/C15 -> 0.46449018 | F15: =F14*coefper -> 23645.57 | G15: =G14*coefper -> 8440.251 | H15: 0 | I15: =G15+H15 -> 8440.251 | J15: =F15-I15 -> 15205.319 | L15: 10 | M15: =$M$6 -> 18171 | N15: =M15-S15 -> #DIV/0! | O15: =1-N15/M15 -> #DIV/0! | P15: =P14*coefper -> 23645.57 | Q15: =Q14*coefper -> 8440.251 | R15: =R14-(1-coefper)*(R14/S14)*R14 -> #DIV/0! | S15: =Q15+R15 -> #DIV/0! | T15: =P15-S15 -> #DIV/0!
B16: 11 | C16: =$C$6 -> 18171 | D16: =C16-I16 -> 9794.6417 | E16: =1-D16/C16 -> 0.46097399 | F16: =F15*coefper -> 23466.573 | G16: =G15*coefper -> 8376.3583 | H16: 0 | I16: =G16+H16 -> 8376.3583 | J16: =F16-I16 -> 15090.215 | L16: 11 | M16: =$M$6 -> 18171 | N16: =M16-S16 -> #DIV/0! | O16: =1-N16/M16 -> #DIV/0! | P16: =P15*coefper -> 23466.573 | Q16: =Q15*coefper -> 8376.3583 | R16: =R15-(1-coefper)*(R15/S15)*R15 -> #DIV/0! | S16: =Q16+R16 -> #DIV/0! | T16: =P16-S16 -> #DIV/0!
B17: 12 | C17: =$C$6 -> 18171 | D17: =C17-I17 -> 9858.0507 | E17: =1-D17/C17 -> 0.45748441 | F17: =F16*coefper -> 23288.931 | G17: =G16*coefper -> 8312.9493 | H17: 0 | I17: =G17+H17 -> 8312.9493 | J17: =F17-I17 -> 14975.982 | L17: 12 | M17: =$M$6 -> 18171 | N17: =M17-S17 -> #DIV/0! | O17: =1-N17/M17 -> #DIV/0! | P17: =P16*coefper -> 23288.931 | Q17: =Q16*coefper -> 8312.9493 | R17: =R16-(1-coefper)*(R16/S16)*R16 -> #DIV/0! | S17: =Q17+R17 -> #DIV/0! | T17: =P17-S17 -> #DIV/0!
B18: 13 | C18: =$C$6 -> 18171 | D18: =C18-I18 -> 9920.9798 | E18: =1-D18/C18 -> 0.45402126 | F18: =F17*coefper -> 23112.634 | G18: =G17*coefper -> 8250.0202 | H18: 0 | I18: =G18+H18 -> 8250.0202 | J18: =F18-I18 -> 14862.614 | L18: 13 | M18: =$M$6 -> 18171 | N18: =M18-S18 -> #DIV/0! | O18: =1-N18/M18 -> #DIV/0! | P18: =P17*coefper -> 23112.634 | Q18: =Q17*coefper -> 8250.0202 | R18: =R17-(1-coefper)*(R17/S17)*R17 -> #DIV/0! | S18: =Q18+R18 -> #DIV/0! | T18: =P18-S18 -> #DIV/0!
... B30: 25 | C30: =$C$6 -> 18171 | D30: =C30-I30 -> 10639.983 | E30: =1-D30/C30 -> 0.41445253 | F30: =F29*coefper -> 21098.329 | G30: =G29*coefper -> 7531.0169 | H30: 0 | I30: =G30+H30 -> 7531.0169 | J30: =F30-I30 -> 13567.312 | L30: 25 | M30: =$M$6 -> 18171 | N30: =M30-S30 -> #DIV/0! | O30: =1-N30/M30 -> #DIV/0! | P30: =P29*coefper -> 21098.329 | Q30: =Q29*coefper -> 7531.0169 | R30: =R29-(1-coefper)*(R29/S29)*R29 -> #DIV/0! | S30: =Q30+R30 -> #DIV/0! | T30: =P30-S30 -> #DIV/0!

Sheet exp5
B1: ="Autoconsumo (Sin Baterías) de "&p_gen&" kW" -> Autoconsumo (Sin Baterías) de 16,335 kW | L1: Instalación Con baterías | V1: Instalación Con baterías
B3: AÑO | C3: AHORRO POR ENERGÍA AUTOCONSUMIDA | F3: AHORRO POR EXCEDENTE | G3: AHORRO TOTAL AL AÑO | I3: AHORRO ACUMULADO | J3: RENTABILIDAD | L3: AÑO | M3: AHORRO POR ENERGÍA AUTOCONSUMIDA | P3: AHORRO POR EXCEDENTE | Q3: AHORRO TOTAL AL AÑO | S3: AHORRO ACUMULADO | T3: RENTABILIDAD | V3: AÑO | W3: AHORRO POR ENERGÍA AUTOCONSUMIDA | Z3: AHORRO POR EXCEDENTE | AA3: AHORRO TOTAL AL AÑO | AC3: AHORRO ACUMULADO | AD3: RENTABILIDAD
C4: Autoconsumo Directo Ahorro ( €/año) | D4: Autoconsumo Indirecto Ahorro (€/año) | E4: Autoconsumo Total Ahorro (€/año) | F4: Excedentes Ahorro (€/año) | G4: Total Ahorro (€/año) | I4: Ahorro acumulado (€) | J4: Rentabilidad de la Inversión (€) | M4: Autoconsumo Directo Ahorro ( €/año) | N4: Autoconsumo Indirecto Ahorro (€/año) | O4: Autoconsumo Total Ahorro (€/año) | P4: Excedentes Ahorro (€/año) | Q4: Total Ahorro (€/año) | S4: Ahorro acumulado (€) | T4: Rentabilidad de la Inversión (€) | W4: Autoconsumo Directo Ahorro ( €/año) | X4: Autoconsumo Indirecto Ahorro (€/año) | Y4: Autoconsumo Total Ahorro (€/año) | Z4: Excedentes Ahorro (€/año) | AA4: Total Ahorro (€/año) | AC4: Ahorro acumulado (€) | AD4: Rentabilidad de la Inversión (€)
B5: 0 | J5: =-incentivo!C33 -> -19994.921 | L5: 0 | T5: =-incentivo!D28 -> -19994.921 | V5: 0 | AD5: =-incentivo!N28 -> 0
B6: 1 | C6: =cálculos!P27*preciokwh -> 2982.4306 | D6: ='exp4'!H6*preciokwh*(1+ti) -> 0 | E6: =C6+D6 -> 2982.4306 | F6: ='exp4'!J6*precioexc -> 1709.5661 | G6: =E6+F6 -> 4691.9967 | I6: =I5+G6 -> 4691.9967 | J6: =J5+G6 -> -15302.924 | L6: 1 | M6: =C6 -> 2982.4306 | N6: ='exp4'!R6*preciokwh -> #DIV/0! | O6: =M6+N6 -> #DIV/0! | P6: ='exp4'!T6*precioexc -> #DIV/0! | Q6: =O6+P6 -> #DIV/0! | S6: =Q6+S5 -> #DIV/0! | T6: =T5+Q6 -> #DIV/0! | V6: 1 | W6: =M6 -> 2982.4306 | X6: ='exp4'!AB6*preciokwh -> 0 | Y6: =W6+X6 -> 2982.4306 | Z6: ='exp4'!AD6*precioexc -> 0 | AA6: =Y6+Z6 -> 2982.4306 | AC6: =AA6+AC5 -> 2982.4306 | AD6: =AD5+AA6 -> 2982.4306
B7: 2 | C7: ='exp4'!G7*preciokwh*(1+ti) -> 3063.4485 | D7: ='exp4'!H7*preciokwh*(1+ti) -> 0 | E7: =C7+D7 -> 3063.4485 | F7: ='exp4'!J7*precioexc -> 1696.6246 | G7: =E7+F7 -> 4760.0731 | I7: =I6+G7 -> 9452.0698 | J7: =J6+G7 -> -10542.851 | L7: 2 | M7: =C7 -> 3063.4485 | N7: ='exp4'!R7*preciokwh -> #DIV/0! | O7: =M7+N7 -> #DIV/0! | P7: ='exp4'!T7*precioexc -> #DIV/0! | Q7: =O7+P7 -> #DIV/0! | S7: =Q7+S6 -> #DIV/0! | T7: =T6+Q7 -> #DIV/0! | V7: 2 | W7: =M7 -> 3063.4485 | X7: ='exp4'!AB7*preciokwh -> 0 | Y7: =W7+X7 -> 3063.4485 | Z7: ='exp4'!AD7*precioexc -> 0 | AA7: =Y7+Z7 -> 3063.4485 | AC7: =AA7+AC6 -> 6045.8791 | AD7: =AD6+AA7 -> 6045.8791
B8: 3 | C8: ='exp4'!G8*preciokwh*(1+ti) -> 3040.2582 | D8: ='exp4'!H8*preciokwh*(1+ti) -> 0 | E8: =C8+D8 -> 3040.2582 | F8: ='exp4'!J8*precioexc -> 1683.7812 | G8: =E8+F8 -> 4724.0394 | I8: =I7+G8 -> 14176.109 | J8: =J7+G8 -> -5818.8118 | L8: 3 | M8: =C8 -> 3040.2582 | N8: ='exp4'!R8*preciokwh -> #DIV/0! | O8: =M8+N8 -> #DIV/0! | P8: ='exp4'!T8*precioexc -> #DIV/0! | Q8: =O8+P8 -> #DIV/0! | S8: =Q8+S7 -> #DIV/0! | T8: =T7+Q8 -> #DIV/0! | V8: 3 | W8: =M8 -> 3040.2582 | X8: ='exp4'!AB8*preciokwh -> 0 | Y8: =W8+X8 -> 3040.2582 | Z8: ='exp4'!AD8*precioexc -> 0 | AA8: =Y8+Z8 -> 3040.2582 | AC8: =AA8+AC7 -> 9086.1372 | AD8: =AD7+AA8 -> 9086.1372
B9: 4 | C9: ='exp4'!G9*preciokwh*(1+ti) -> 3017.2434 | D9: ='exp4'!H9*preciokwh*(1+ti) -> 0 | E9: =C9+D9 -> 3017.2434 | F9: ='exp4'!J9*precioexc -> 1671.035 | G9: =E9+F9 -> 4688.2784 | I9: =I8+G9 -> 18864.388 | J9: =J8+G9 -> -1130.5334 | L9: 4 | M9: =C9 -> 3017.2434 | N9: ='exp4'!R9*preciokwh -> #DIV/0! | O9: =M9+N9 -> #DIV/0! | P9: ='exp4'!T9*precioexc -> #DIV/0! | Q9: =O9+P9 -> #DIV/0! | S9: =Q9+S8 -> #DIV/0! | T9: =T8+Q9 -> #DIV/0! | V9: 4 | W9: =M9 -> 3017.2434 | X9: ='exp4'!AB9*preciokwh -> 0 | Y9: =W9+X9 -> 3017.2434 | Z9: ='exp4'!AD9*precioexc -> 0 | AA9: =Y9+Z9 -> 3017.2434 | AC9: =AA9+AC8 -> 12103.381 | AD9: =AD8+AA9 -> 12103.381
B10: 5 | C10: ='exp4'!G10*preciokwh*(1+ti) -> 2994.4029 | D10: ='exp4'!H10*preciokwh*(1+ti) -> 0 | E10: =C10+D10 -> 2994.4029 | F10: ='exp4'!J10*precioexc -> 1658.3852 | G10: =E10+F10 -> 4652.7881 | I10: =I9+G10 -> 23517.176 | J10: =J9+G10 -> 3522.2547 | L10: 5 | M10: =C10 -> 2994.4029 | N10: ='exp4'!R10*preciokwh -> #DIV/0! | O10: =M10+N10 -> #DIV/0! | P10: ='exp4'!T10*precioexc -> #DIV/0! | Q10: =O10+P10 -> #DIV/0! | S10: =Q10+S9 -> #DIV/0! | T10: =T9+Q10 -> #DIV/0! | V10: 5 | W10: =M10 -> 2994.4029 | X10: ='exp4'!AB10*preciokwh -> 0 | Y10: =W10+X10 -> 2994.4029 | Z10: ='exp4'!AD10*precioexc -> 0 | AA10: =Y10+Z10 -> 2994.4029 | AC10: =AA10+AC9 -> 15097.783 | AD10: =AD9+AA10 -> 15097.783
B11: 6 | C11: ='exp4'!G11*preciokwh*(1+ti) -> 2971.7352 | D11: ='exp4'!H11*preciokwh*(1+ti) -> 0 | E11: =C11+D11 -> 2971.7352 | F11: ='exp4'!J11*precioexc -> 1645.8313 | G11: =E11+F11 -> 4617.5665 | I11: =I10+G11 -> 28134.742 | J11: =J10+G11 -> 8139.8212 | L11: 6 | M11: =C11 -> 2971.7352 | N11: ='exp4'!R11*preciokwh -> #DIV/0! | O11: =M11+N11 -> #DIV/0! | P11: ='exp4'!T11*precioexc -> #DIV/0! | Q11: =O11+P11 -> #DIV/0! | S11: =Q11+S10 -> #DIV/0! | T11: =T10+Q11 -> #DIV/0! | V11: 6 | W11: =M11 -> 2971.7352 | X11: ='exp4'!AB11*preciokwh -> 0 | Y11: =W11+X11 -> 2971.7352 | Z11: ='exp4'!AD11*precioexc -> 0 | AA11: =Y11+Z11 -> 2971.7352 | AC11: =AA11+AC10 -> 18069.519 | AD11: =AD10+AA11 -> 18069.519
B12: 7 | C12: ='exp4'!G12*preciokwh*(1+ti) -> 2949.2392 | D12: ='exp4'!H12*preciokwh*(1+ti) -> 0 | E12: =C12+D12 -> 2949.2392 | F12: ='exp4'!J12*precioexc -> 1633.3723 | G12: =E12+F12 -> 4582.6115 | I12: =I11+G12 -> 32717.354 | J12: =J11+G12 -> 12722.433 | L12: 7 | M12: =C12 -> 2949.2392 | N12: ='exp4'!R12*preciokwh -> #DIV/0! | O12: =M12+N12 -> #DIV/0! | P12: ='exp4'!T12*precioexc -> #DIV/0! | Q12: =O12+P12 -> #DIV/0! | S12: =Q12+S11 -> #DIV/0! | T12: =T11+Q12 -> #DIV/0! | V12: 7 | W12: =M12 -> 2949.2392 | X12: ='exp4'!AB12*preciokwh -> 0 | Y12: =W12+X12 -> 2949.2392 | Z12: ='exp4'!AD12*precioexc -> 0 | AA12: =Y12+Z12 -> 2949.2392 | AC12: =AA12+AC11 -> 21018.758 | AD12: =AD11+AA12 -> 21018.758
B13: 8 | C13: ='exp4'!G13*preciokwh*(1+ti) -> 2926.9135 | D13: ='exp4'!H13*preciokwh*(1+ti) -> 0 | E13: =C13+D13 -> 2926.9135 | F13: ='exp4'!J13*precioexc -> 1621.0077 | G13: =E13+F13 -> 4547.9212 | I13: =I12+G13 -> 37265.275 | J13: =J12+G13 -> 17270.354 | L13: 8 | M13: =C13 -> 2926.9135 | N13: ='exp4'!R13*preciokwh -> #DIV/0! | O13: =M13+N13 -> #DIV/0! | P13: ='exp4'!T13*precioexc -> #DIV/0! | Q13: =O13+P13 -> #DIV/0! | S13: =Q13+S12 -> #DIV/0! | T13: =T12+Q13 -> #DIV/0! | V13: 8 | W13: =M13 -> 2926.9135 | X13: ='exp4'!AB13*preciokwh -> 0 | Y13: =W13+X13 -> 2926.9135 | Z13: ='exp4'!AD13*precioexc -> 0 | AA13: =Y13+Z13 -> 2926.9135 | AC13: =AA13+AC12 -> 23945.671 | AD13: =AD12+AA13 -> 23945.671
B14: 9 | C14: ='exp4'!G14*preciokwh*(1+ti) -> 2904.7567 | D14: ='exp4'!H14*preciokwh*(1+ti) -> 0 | E14: =C14+D14 -> 2904.7567 | F14: ='exp4'!J14*precioexc -> 1608.7367 | G14: =E14+F14 -> 4513.4934 | I14: =I13+G14 -> 41778.768 | J14: =J13+G14 -> 21783.847 | L14: 9 | M14: =C14 -> 2904.7567 | N14: ='exp4'!R14*preciokwh -> #DIV/0! | O14: =M14+N14 -> #DIV/0! | P14: ='exp4'!T14*precioexc -> #DIV/0! | Q14: =O14+P14 -> #DIV/0! | S14: =Q14+S13 -> #DIV/0! | T14: =T13+Q14 -> #DIV/0! | V14: 9 | W14: =M14 -> 2904.7567 | X14: ='exp4'!AB14*preciokwh -> 0 | Y14: =W14+X14 -> 2904.7567 | Z14: ='exp4'!AD14*precioexc -> 0 | AA14: =Y14+Z14 -> 2904.7567 | AC14: =AA14+AC13 -> 26850.428 | AD14: =AD13+AA14 -> 26850.428
B15: 10 | C15: ='exp4'!G15*preciokwh*(1+ti) -> 2882.7677 | D15: ='exp4'!H15*preciokwh*(1+ti) -> 0 | E15: =C15+D15 -> 2882.7677 | F15: ='exp4'!J15*precioexc -> 1596.5585 | G15: =E15+F15 -> 4479.3263 | I15: =I14+G15 -> 46258.094 | J15: =J14+G15 -> 26263.174 | L15: 10 | M15: =C15 -> 2882.7677 | N15: ='exp4'!R15*preciokwh -> #DIV/0! | O15: =M15+N15 -> #DIV/0! | P15: ='exp4'!T15*precioexc -> #DIV/0! | Q15: =O15+P15 -> #DIV/0! | S15: =Q15+S14 -> #DIV/0! | T15: =T14+Q15 -> #DIV/0! | V15: 10 | W15: =M15 -> 2882.7677 | X15: ='exp4'!AB15*preciokwh -> 0 | Y15: =W15+X15 -> 2882.7677 | Z15: ='exp4'!AD15*precioexc -> 0 | AA15: =Y15+Z15 -> 2882.7677 | AC15: =AA15+AC14 -> 29733.196 | AD15: =AD14+AA15 -> 29733.196
B16: 11 | C16: ='exp4'!G16*preciokwh*(1+ti) -> 2860.9452 | D16: ='exp4'!H16*preciokwh*(1+ti) -> 0 | E16: =C16+D16 -> 2860.9452 | F16: ='exp4'!J16*precioexc -> 1584.4726 | G16: =E16+F16 -> 4445.4178 | I16: =I15+G16 -> 50703.512 | J16: =J15+G16 -> 30708.591 | L16: 11 | M16: =C16 -> 2860.9452 | N16: ='exp4'!R16*preciokwh -> #DIV/0! | O16: =M16+N16 -> #DIV/0! | P16: ='exp4'!T16*precioexc -> #DIV/0! | Q16: =O16+P16 -> #DIV/0! | S16: =Q16+S15 -> #DIV/0! | T16: =T15+Q16 -> #DIV/0! | V16: 11 | W16: =M16 -> 2860.9452 | X16: ='exp4'!AB16*preciokwh -> 0 | Y16: =W16+X16 -> 2860.9452 | Z16: ='exp4'!AD16*precioexc -> 0 | AA16: =Y16+Z16 -> 2860.9452 | AC16: =AA16+AC15 -> 32594.141 | AD16: =AD15+AA16 -> 32594.141
B17: 12 | C17: ='exp4'!G17*preciokwh*(1+ti) -> 2839.2878 | D17: ='exp4'!H17*preciokwh*(1+ti) -> 0 | E17: =C17+D17 -> 2839.2878 | F17: ='exp4'!J17*precioexc -> 1572.4781 | G17: =E17+F17 -> 4411.7659 | I17: =I16+G17 -> 55115.278 | J17: =J16+G17 -> 35120.357 | L17: 12 | M17: =C17 -> 2839.2878 | N17: ='exp4'!R17*preciokwh -> #DIV/0! | O17: =M17+N17 -> #DIV/0! | P17: ='exp4'!T17*precioexc -> #DIV/0! | Q17: =O17+P17 -> #DIV/0! | S17: =Q17+S16 -> #DIV/0! | T17: =T16+Q17 -> #DIV/0! | V17: 12 | W17: =M17 -> 2839.2878 | X17: ='exp4'!AB17*preciokwh -> 0 | Y17: =W17+X17 -> 2839.2878 | Z17: ='exp4'!AD17*precioexc -> 0 | AA17: =Y17+Z17 -> 2839.2878 | AC17: =AA17+AC16 -> 35433.429 | AD17: =AD16+AA17 -> 35433.429
B18: 13 | C18: ='exp4'!G18*preciokwh*(1+ti) -> 2817.7944 | D18: ='exp4'!H18*preciokwh*(1+ti) -> 0 | E18: =C18+D18 -> 2817.7944 | F18: ='exp4'!J18*precioexc -> 1560.5745 | G18: =E18+F18 -> 4378.3689 | I18: =I17+G18 -> 59493.647 | J18: =J17+G18 -> 39498.726 | L18: 13 | M18: =C18 -> 2817.7944 | N18: ='exp4'!R18*preciokwh -> #DIV/0! | O18: =M18+N18 -> #DIV/0! | P18: ='exp4'!T18*precioexc -> #DIV/0! | Q18: =O18+P18 -> #DIV/0! | S18: =Q18+S17 -> #DIV/0! | T18: =T17+Q18 -> #DIV/0! | V18: 13 | W18: =M18 -> 2817.7944 | X18: ='exp4'!AB18*preciokwh -> 0 | Y18: =W18+X18 -> 2817.7944 | Z18: ='exp4'!AD18*precioexc -> 0 | AA18: =Y18+Z18 -> 2817.7944 | AC18: =AA18+AC17 -> 38251.223 | AD18: =AD17+AA18 -> 38251.223
... B30: 25 | C30: ='exp4'!G30*preciokwh*(1+ti) -> 2572.2188 | D30: ='exp4'!H30*preciokwh*(1+ti) -> 0 | E30: =C30+D30 -> 2572.2188 | F30: ='exp4'!J30*precioexc -> 1424.5677 | G30: =E30+F30 -> 3996.7866 | I30: =I29+G30 -> 109519.24 | J30: =J29+G30 -> 89524.319 | L30: 25 | M30: =C30 -> 2572.2188 | N30: ='exp4'!R30*preciokwh -> #DIV/0! | O30: =M30+N30 -> #DIV/0! | P30: ='exp4'!T30*precioexc -> #DIV/0! | Q30: =O30+P30 -> #DIV/0! | S30: =Q30+S29 -> #DIV/0! | T30: =T29+Q30 -> #DIV/0! | V30: 25 | W30: =M30 -> 2572.2188 | X30: ='exp4'!AB30*preciokwh -> 0 | Y30: =W30+X30 -> 2572.2188 | Z30: ='exp4'!AD30*precioexc -> 0 | AA30: =Y30+Z30 -> 2572.2188 | AC30: =AA30+AC29 -> 70446.281 | AD30: =AD29+AA30 -> 70446.281

Sheet exp6
B2: Fabricante | C2: =fab_mod -> AIKO
B3: Modelo | C3: =mod_mod -> AIKO N-TYPE ABC A-MAH72MW 605W
B4: Tecnología | C4: =VLOOKUP(mod_mod,t.mod!A2:H28,3,) -> Módulo solar N-Type
B5: Optimizador | C5: =mod_opt -> Sin Optimizador
B6: Potencia del módulo | C6: =p_mod&" W" -> 605 W
B7: Potencia Total | C7: =p_gen*1000&" W" -> 16335 W
B8: Garantía
B9: Producción | C9: =VLOOKUP(mod_mod,t.mod!A2:H28,6,) -> 30 años
B10: Producto | C10: =VLOOKUP(mod_mod,t.mod!A2:H28,5,) -> 15 años
B12: Fabricante | C12: =fab_inv -> HUAWEI
B13: Modelo | C13: =mod_inv1 -> HUAWEI SUN2000 20KTL M3
B14: Tecnología | C14: =VLOOKUP(mod_inv1,t.inv!A3:H36,2,FALSE) -> Inversor Trifásico de conexión a red con conexión a internet WLAN o Ethernet integrada.
B15: Potencia total | C15: =pot_inv&" kW, en "&(num_inv1+num_inv2)&" equipo/s" -> 20 kW, en 1 equipo/s
B16: Smart Meter | C16: =VLOOKUP(mod_meter,t.met!A3:D13,3,0) -> Medidor Monofásico DDSU Huawei
B17: Garantía | C17: =VLOOKUP(mod_inv1,t.inv!A3:H36,5,FALSE) -> 10 años
B19: Fabricante | C19: =VLOOKUP(mod_bat,t.bat!A3:G12,2,) -> DYNESS
B20: Modelo | C20: =mod_bat -> DYNESS 3,6 kW 48V
C21: =VLOOKUP(mod_bat,t.bat!A3:G12,3,) -> Módulo de Batería Dyness de 48V
B22: nº de módulos | C22: =num_bat -> 0
B23: Capacidad | C23: =cap_bat&" kWh" -> 0 kWh
B24: Garantía | C24: =VLOOKUP(mod_bat,t.bat!A3:G12,6,) -> 10 años
B28: Tipo | C28: =t.est!H3 -> Coplanaria aluminio
B29: Descripción | C29: =VLOOKUP(estructura,t.est!A3:D11,4,0) -> Soporte coplanar contínuo atornillado para cubierta de teja, incluyendo juntas de estanqueidad, con perfilería de aluminio EN AW 6005A T6 y tornillería de acero inoxidable A2-70. Soporta cargas de viento de hasta 150 km/h. Certificado ISO:9001
B32: Fabricante | C32: =VLOOKUP(mod_bat,t.bat!A3:G12,2,) -> DYNESS
B33: Modelo | C33: =mod_bat -> DYNESS 3,6 kW 48V
C34: =VLOOKUP(mod_bat,t.bat!A3:G12,3,) -> Módulo de Batería Dyness de 48V
B35: nº de módulos | C35: =num_bat -> 0
B36: Capacidad | C36: =cap_bat&" kWh" -> 0 kWh
B37: Garantía | C37: =VLOOKUP(mod_bat,t.bat!A3:G12,6,) -> 10 años

Sheet ecov
B2: =N5 -> Unifamiliar de 4 Fachadas | E2: =N6 -> Pareados de 3 Fachadas | H2: =N7 -> Adosados de 2 Fachadas
C3: número de plantas | F3: número de plantas | I3: número de plantas
B4: Superficie construida (m2) | C4: 1 | D4: 2 | E4: Superficie construida (m2) | F4: 1 | G4: 2 | H4: Superficie construida (m2) | I4: 1 | J4: 2
B5: 50 | C5: 6 | D5: 6 | E5: 50 | F5: 5 | G5: 5 | H5: 50 | I5: 5 | J5: 4 | N5: Unifamiliar de 4 Fachadas
B6: 75 | C6: 7 | D6: 7 | E6: 75 | F6: 7 | G6: 6 | H6: 75 | I6: 6 | J6: 5 | N6: Pareados de 3 Fachadas
B7: 100 | C7: 9 | D7: 9 | E7: 100 | F7: 8 | G7: 8 | H7: 100 | I7: 7 | J7: 6 | N7: Adosados de 2 Fachadas
B8: 125 | C8: 10 | D8: 10 | E8: 125 | F8: 10 | G8: 9 | H8: 125 | I8: 9 | J8: 7
B9: 150 | C9: 12 | D9: 11 | E9: 150 | F9: 11 | G9: 10 | H9: 150 | I9: 10 | J9: 9
B10: 175 | C10: 13 | D10: 12 | E10: 175 | F10: 13 | G10: 11 | H10: 175 | I10: 12 | J10: 10
B11: 200 | C11: 15 | D11: 14 | E11: 200 | F11: 14 | G11: 12 | H11: 200 | I11: 13 | J11: 11
B12: 225 | C12: 16 | D12: 15 | E12: 225 | F12: 15 | G12: 13 | H12: 225 | I12: 14 | J12: 12
B13: 250 | C13: 18 | D13: 16 | E13: 250 | F13: 17 | G13: 14 | H13: 250 | I13: 16 | J13: 13
B15: =N5 -> Unifamiliar de 4 Fachadas | E15: =N6 -> Pareados de 3 Fachadas | H15: =N7 -> Adosados de 2 Fachadas
C16: número de plantas | F16: número de plantas | I16: número de plantas
B17: Superficie construida (m2) | C17: 1 | D17: 2 | E17: Superficie construida (m2) | F17: 1 | G17: 2 | H17: Superficie construida (m2) | I17: 1 | J17: 2
B18: 50 | C18: 2.7 | D18: 2.7 | E18: 50 | F18: 2.25 | G18: 2.25 | H18: 50 | I18: 2.25 | J18: 1.8
B19: 75 | C19: 3.15 | D19: 3.15 | E19: 75 | F19: 3.15 | G19: 2.7 | H19: 75 | I19: 2.7 | J19: 2.25
B20: 100 | C20: 4.05 | D20: 4.05 | E20: 100 | F20: 3.6 | G20: 3.6 | H20: 100 | I20: 3.15 | J20: 2.7
B21: 125 | C21: 4.5 | D21: 4.5 | E21: 125 | F21: 4.5 | G21: 4.05 | H21: 125 | I21: 4.05 | J21: 3.15
B22: 150 | C22: 5.4 | D22: 4.95 | E22: 150 | F22: 4.95 | G22: 4.5 | H22: 150 | I22: 4.5 | J22: 4.05
B23: 175 | C23: 5.85 | D23: 5.4 | E23: 175 | F23: 5.85 | G23: 4.95 | H23: 175 | I23: 5.4 | J23: 4.5
B24: 200 | C24: 6.75 | D24: 6.3 | E24: 200 | F24: 6.3 | G24: 5.4 | H24: 200 | I24: 5.85 | J24: 4.95
B25: 225 | C25: 7.2 | D25: 6.75 | E25: 225 | F25: 6.75 | G25: 5.85 | H25: 225 | I25: 6.3 | J25: 5.4
B26: 250 | C26: 8.1 | D26: 7.2 | E26: 250 | F26: 7.65 | G26: 6.3 | H26: 250 | I26: 7.2 | J26: 5.85

Sheet t.con
C2: Enero (kWh/mes) | D2: Febrero (kWh/mes) | E2: Marzo (kWh/mes) | F2: Abril (kWh/mes) | G2: Mayo (kWh/mes) | H2: Junio (kWh/mes) | I2: Julio (kWh/mes) | J2: Agosto (kWh/mes) | K2: Septiembre (kWh/mes) | L2: Octubre (kWh/mes) | M2: Noviembre (kWh/mes) | N2: Diciembre (kWh/mes) | O2: Total (kWh/año)
B3: Demanda Mensual (kWh/mes) | C3: =IF(tipo_calculo="Consumo Mensual Real",datos!B41, VLOOKUP(curva,t.con!B5:N8,2,)*consumo1) -> 2180.52 | D3: =IF(tipo_calculo="Consumo Mensual Real",datos!B43, VLOOKUP(curva,t.con!B5:N8,3,)*consumo1) -> 1998.81 | E3: =IF(tipo_calculo="Consumo Mensual Real",datos!B45, VLOOKUP(curva,t.con!B5:N8,4,)*consumo1) -> 1090.26 | F3: =IF(tipo_calculo="Consumo Mensual Real",datos!B47, VLOOKUP(curva,t.con!B5:N8,5,)*consumo1) -> 1090.26 | G3: =IF(tipo_calculo="Consumo Mensual Real",datos!D41, VLOOKUP(curva,t.con!B5:N8,6,)*consumo1) -> 1271.97 | H3: =IF(tipo_calculo="Consumo Mensual Real",datos!D43, VLOOKUP(curva,t.con!B5:N8,7,)*consumo1) -> 1271.97 | I3: =IF(tipo_calculo="Consumo Mensual Real",datos!D45, VLOOKUP(curva,t.con!B5:N8,8,)*consumo1) -> 1635.39 | J3: =IF(tipo_calculo="Consumo Mensual Real",datos!D47, VLOOKUP(curva,t.con!B5:N8,9,)*consumo1) -> 1817.1 | K3: =IF(tipo_calculo="Consumo Mensual Real",datos!F41, VLOOKUP(curva,t.con!B5:N8,10,)*consumo1) -> 1090.26 | L3: =IF(tipo_calculo="Consumo Mensual Real",datos!F43, VLOOKUP(curva,t.con!B5:N8,11,)*consumo1) -> 1090.26 | M3: =IF(tipo_calculo="Consumo Mensual Real",datos!F45, VLOOKUP(curva,t.con!B5:N8,12,)*consumo1) -> 1453.68 | N3: =IF(tipo_calculo="Consumo Mensual Real",datos!F47, VLOOKUP(curva,t.con!B5:N8,13,)*consumo1) -> 2180.52 | O3: =SUM(C3:N3) -> 18171
B5: Vivienda habitada todo el año | C5: 0.12 | D5: 0.11 | E5: 0.06 | F5: 0.06 | G5: 0.07 | H5: 0.07 | I5: 0.09 | J5: 0.1 | K5: 0.06 | L5: 0.06 | M5: 0.08 | N5: 0.12 | O5: =SUM(C5:N5) -> 1
B6: Vivienda de verano | C6: 0.08 | D6: 0.07 | E6: 0.07 | F6: 0.07 | G6: 0.08 | H6: 0.09 | I6: 0.1 | J6: 0.1 | K6: 0.1 | L6: 0.09 | M6: 0.07 | N6: 0.08 | O6: =SUM(C6:N6) -> 1
B7: Comercio | C7: 0.08 | D7: 0.08 | E7: 0.08 | F7: 0.08 | G7: 0.1 | H7: 0.1 | I7: 0.1 | J7: 0.08 | K7: 0.08 | L7: 0.08 | M7: 0.06 | N7: 0.08 | O7: =SUM(C7:N7) -> 1
B8: Curva de Consumo Mensual 4 | C8: 0.1 | D8: 0.1 | E8: 0.08 | F8: 0.08 | G8: 0.08 | H8: 0.1 | I8: 0.08 | J8: 0.02 | K8: 0.08 | L8: 0.08 | M8: 0.1 | N8: 0.1 | O8: =SUM(C8:N8) -> 1

Sheet t.mod
A1: tabla_modulos
A2: Modelo de Módulo | B2: Fabricante | C2: Descripción | D2: Proveedor | E2: Garantía producto | F2: Garantía producción | G2: Potencia (Wp) | H2: Coste Neto (€/Ud de módulo) | I2: Ratio (€/Wp)
A3: CANADIAN SOLAR CS6W-550MS HiKu6 | B3: CANADIAN SOLAR | C3: Módulo solar monocristalino PERC | D3: SOLARTODAY | E3: 12 años | F3: 25 años | G3: 550 | H3: =0.21*G3 -> 115.5 | I3: =H3/G3 -> 0.21
A4: AIKO N-TYPE ABC A-MAH72MW 600W | B4: AIKO | C4: Módulo solar N-Type | D4: BETSOLAR | E4: 15 años | F4: 30 años | G4: 600 | H4: =G4*0.13 -> 78 | I4: =H4/G4 -> 0.13
A5: AIKO N-TYPE ABC A-MAH72MW 605W | B5: AIKO | C5: Módulo solar N-Type | D5: BETSOLAR | E5: 15 años | F5: 30 años | G5: 605 | H5: =G5*0.13 -> 78.65 | I5: =H5/G5 -> 0.13
A6: AIKO N-TYPE ABC A-MAH72MW 610W | B6: AIKO | C6: Módulo solar N-Type | D6: BETSOLAR | E6: 15 años | F6: 30 años | G6: 610 | H6: =G6*0.13 -> 79.3 | I6: =H6/G6 -> 0.13
A7: HIKU6 CS6W 540W-MS | B7: CANADIAN SOLAR | C7: Módulo solar monocristalino PERC | D7: AMARA | E7: 12 años | F7: 25 años | G7: 540 | H7: =0.21*G7 -> 113.4 | I7: =H7/G7 -> 0.21
A8: JA SOLAR JAM66S30 500 Wp | B8: JA SOLAR | C8: Módulo solar monocristalino PERC | D8: AMARA | E8: 25 años | F8: 25 años | G8: 500 | H8: =0.14*G8 -> 70 | I8: =H8/G8 -> 0.14
A9: JA SOLAR JAM72 460 Wp | B9: JA SOLAR | C9: Módulo solar monocristalino PERC | D9: AMARA | E9: 25 años | F9: 25 años | G9: 460 | H9: =0.15*G9 -> 69 | I9: =H9/G9 -> 0.15
A10: JA SOLAR JAM72S30 545 Wp | B10: JA SOLAR | C10: Módulo solar monocristalino PERC | D10: AMARA | E10: 25 años | F10: 25 años | G10: 545 | H10: =0.17*G10 -> 92.65 | I10: =H10/G10 -> 0.17
A11: JA SOLAR JAM72D40-575/GB 575 Wp | B11: JA SOLAR | C11: Módulo solar monocristalino PERC | D11: AMARA | E11: 25 años | F11: 25 años | G11: 575 | H11: =0.17*G11 -> 97.75 | I11: =H11/G11 -> 0.17
A12: JINKO SOLAR TIGER NEO N-TYPE 60HL4-V 470 | B12: JINKO | C12: Módulo solar monocristalino PERC | E12: 25 años | F12: 25 años | G12: 470 | H12: =0.19*G12 -> 89.3 | I12: =H12/G12 -> 0.19
A13: JINKO SOLAR TIGER PRO P-TYPE 550 | B13: JINKO | C13: Módulo solar monocristalino PERC | E13: 12 años | F13: 25 años | G13: 550 | H13: =0.13*G13 -> 71.5 | I13: =H13/G13 -> 0.13
A14: JINKO TIGER N-TYPE 410W ALL BLACK JKM410N-63L3-B | B14: JINKO | C14: Módulo solar monocristalino PERC | E14: 25 años | F14: 25 años | G14: 410 | H14: 92 | I14: =H14/G14 -> 0.22439024
A15: LONGI 450 Wp | B15: LONGI SOLAR | C15: Módulo solar monocristalino PERC | D15: AMARA | E15: 25 años | F15: 25 años | G15: 450 | H15: =0.21*G15 -> 94.5 | I15: =H15/G15 -> 0.21
A16: LONGI 4Hi-MO6 LR5-54HTB 440W (FullBlack) | B16: LONGI SOLAR | C16: Módulo solar monocristalino PERC | D16: BETSOLAR | E16: 25 años | F16: 25 años | G16: 445 | H16: =445*0.193 -> 85.885 | I16: =H16/G16 -> 0.193
A17: LONGI LR5-72HBD 550M G2 HiMO5 Bifacial Double Glass | B17: LONGI SOLAR | C17: Módulo solar monocristalino PERC Bifacial | D17: AMARA | E17: 12 años | F17: 25 años | G17: 550 | H17: 74.47 | I17: =H17/G17 -> 0.1354
A18: LONGI LR5-72HPH 550 (HiMO5 New) 550 Wp | B18: LONGI SOLAR | C18: Módulo solar monocristalino PERC | D18: AMARA | E18: 25 años | F18: 25 años | G18: 550 | H18: =0.17*G18 -> 93.5 | I18: =H18/G18 -> 0.17
A19: LONGI LR5-72HPH 550 (HiMO5 New) 550 Wp | B19: LONGI SOLAR | C19: Módulo solar monocristalino PERC | D19: AMARA | E19: 25 años | F19: 25 años | G19: 550 | H19: =0.17*G19 -> 93.5 | I19: =H19/G19 -> 0.17
A20: LONGI LR5-72HPH 550 (HiMO5 New) 570 Wp | B20: LONGI SOLAR | C20: Módulo solar monocristalino PERC | D20: AMARA | E20: 25 años | F20: 25 años | G20: 570 | H20: =0.17*G20 -> 96.9 | I20: 0.14
A21: LONGI LR5-72HTD 550-570 (HiMO6) 570 Wp | B21: LONGI SOLAR | C21: Módulo solar monocristalino PERC | D21: AMARA | E21: 15 años | F21: 25 años | G21: 570 | H21: =0.21*G21 -> 119.7 | I21: =H21/G21 -> 0.21
A22: QCELLS BLK M-G11S 405 Wp | B22: QCELLS | C22: Módulo solar monocristalino PERC | E22: 15 años | F22: 30 años | G22: 405 | H22: =0.2*405 -> 81 | I22: =H22/G22 -> 0.2
A23: SOLITEK 440 Wp | B23: SOLITEK - TUNGHSU | C23: Módulo solar bifacial vidrio-vidrio monocristalino PERC frameless de alto rendimiento | D23: SOLITEK - TUNGHSU | E23: 15 años | F23: 30 años | G23: 440 | H23: =0.26*G23 -> 114.4 | I23: =H23/G23 -> 0.26

Sheet t.bat
A1: tabla_bateria
A2: Modelo de Batería / BMS | B2: Fabricante | C2: Descripción | D2: Proveedor | E2: Capacidad (kWh) | F2: Garantía | G2: Coste Neto (€) | H2: Coste Neto (€)
A3: LUNA 2000 5 kWh | B3: HUAWEI | C3: Módulo de Batería de Litio-Ferrofosfato de 5 kWh | D3: WCCSOLAR | E3: 5 | F3: 10 años | G3: 1660 | H3: =G3/E3 -> 332
A4: MÓDULO GROWATT 5 KWh | B4: GROWATT | C4: Módulo de Batería de Litio-Ferrofostato 5 kWh | D4: COTO | E4: 5 | F4: 10 años | G4: 1695 | H4: =G4/E4 -> 339
A5: ENPHASE ENCHARGE BATTERY 10T | B5: ENPHASE | C5: Módulo de Batería de 10,5 kWh | D5: AMARA | E5: 10.5 | F5: 10 años | G5: 5530.63 | H5: =G5/E5 -> 526.72667
A6: PYLONTECH US5000 | B6: PYLONTECH | C6: Módulo de Batería Pylontech de 48V | D6: PYLONTECH | E6: 4.8 | F6: 7 años | G6: 1120 | H6: =G6/E6 -> 233.33333
A7: DYNESS 2,4 kW 48V | B7: DYNESS | C7: Módulo de Batería Dyness de 48V | D7: DYNESS | E7: 2.4 | F7: 10 años | G7: 495 | H7: =G7/E7 -> 206.25
A8: DYNESS 5,1 kW 48V | B8: DYNESS | C8: Módulo de Batería Dyness de 48V | D8: DYNESS | E8: 5.1 | F8: 10 años | G8: 1099 | H8: =G8/E8 -> 215.4902
A9: DYNESS 3,6 kW 48V | B9: DYNESS | C9: Módulo de Batería Dyness de 48V | D9: DYNESS | E9: 3.6 | F9: 10 años | G9: 745.83 | H9: =G9/E9 -> 207.175
A10: ENPHASE ENCHARGE BATTERY 3T | B10: ENPHASE | C10: Módulo de Batería de 3,5 kWh | D10: AMARA | E10: 3.5 | F10: 10 años | G10: 2027.03 | H10: =G10/E10 -> 579.15143

Sheet t.inv
A1: tabla_inversor
A2: Modelo | B2: Descripción Larga | C2: Fabricante | D2: Tipo | E2: Garantía | F2: Proveedor | G2: Potencia (kW) | H2: Precio Neto (€/Ud)
A3: Sin Inversor | C3: No aplica | D3: No aplica | E3: No aplica | F3: No aplica | G3: 0 | H3: 0
A4: HUAWEI SUN2000 2KTL L1 | B4: Inversor Híbrido Monofásico de conexión a red con conexión a internet WLAN o Ethernet integrada. | C4: HUAWEI | D4: Monofásico híbrido | E4: 10 años | F4: AMARA | G4: 2 | H4: 462
A5: HUAWEI SUN2000 3KTL L1 | B5: Inversor Híbrido Monofásico de conexión a red con conexión a internet WLAN o Ethernet integrada. | C5: HUAWEI | D5: Monofásico híbrido | E5: 10 años | F5: AMARA | G5: 3 | H5: 545.05
A6: HUAWEI SUN2000 4KTL L1 | B6: Inversor Híbrido Monofásico de conexión a red con conexión a internet WLAN o Ethernet integrada. | C6: HUAWEI | D6: Monofásico híbrido | E6: 10 años | F6: AMARA | G6: 4 | H6: 664.95
A7: HUAWEI SUN2000 5KTL L1 | B7: Inversor Híbrido Monofásico de conexión a red con conexión a internet WLAN o Ethernet integrada. | C7: HUAWEI | D7: Monofásico híbrido | E7: 10 años | F7: AMARA | G7: 5 | H7: 722.7
A8: HUAWEI SUN2000 6KTL L1 | B8: Inversor Híbrido Monofásico de conexión a red con conexión a internet WLAN o Ethernet integrada. | C8: HUAWEI | D8: Monofásico híbrido | E8: 10 años | F8: AMARA | G8: 6 | H8: 780
A9: HUAWEI SUN2000 8KTL LC0 | B9: Inversor Híbrido Monofásico de conexión a red con conexión a internet WLAN o Ethernet integrada. | C9: HUAWEI | D9: Monofásico híbrido | E9: 10 años | F9: AMARA | G9: 8 | H9: 1080
A10: HUAWEI SUN2000 10KTL LC0 | B10: Inversor Híbrido Monofásico de conexión a red con conexión a internet WLAN o Ethernet integrada. | C10: HUAWEI | D10: Monofásico híbrido | E10: 10 años | F10: AMARA | G10: 10 | H10: 1200
A11: HUAWEI SUN2000 3KTL M1 | B11: Inversor Híbrido Trifásico de conexión a red con conexión a internet WLAN o Ethernet integrada. | C11: HUAWEI | D11: Trifásico híbrido | E11: 10 años | F11: AMARA | G11: 3 | H11: 840
A12: HUAWEI SUN2000 4KTL M1 | B12: Inversor Híbrido Trifásico de conexión a red con conexión a internet WLAN o Ethernet integrada. | C12: HUAWEI | D12: Trifásico híbrido | E12: 10 años | F12: AMARA | G12: 4 | H12: 870
A13: HUAWEI SUN2000 5KTL M1 | B13: Inversor Híbrido Trifásico de conexión a red con conexión a internet WLAN o Ethernet integrada. | C13: HUAWEI | D13: Trifásico híbrido | E13: 10 años | F13: AMARA | G13: 5 | H13: 913
A14: HUAWEI SUN2000 6KTL M1 | B14: Inversor Híbrido Trifásico de conexión a red con conexión a internet WLAN o Ethernet integrada. | C14: HUAWEI | D14: Trifásico híbrido | E14: 10 años | F14: AMARA | G14: 6 | H14: 1023
A15: HUAWEI SUN2000 8KTL M1 | B15: Inversor Híbrido Trifásico de conexión a red con conexión a internet WLAN o Ethernet integrada. | C15: HUAWEI | D15: Trifásico híbrido | E15: 10 años | F15: AMARA | G15: 8 | H15: 1217
... A34: DEYE HYBRID SUN 6 KW | B34: Inversor Trifásico Híbrido de conexión a Red | C34: DEYE | D34: Trifásico | E34: 10 años | F34: WCCSOLAR | G34: 6 | H34: 999

Sheet t.est
A1: tabla_estructura
A2: TIPO | B2: FOTO | C2: Fabricante | D2: Descripción | E2: Proveedor | F2: Coste Neto (€/Ud de módulo) | H2: TIPO | J2: FOTO
A3: Coplanaria aluminio | C3: SUNFER | D3: Soporte coplanar contínuo atornillado para cubierta de teja, incluyendo juntas de estanqueidad, con perfilería de aluminio EN AW 6005A T6 y tornillería de acero inoxidable A2-70. Soporta cargas de viento de hasta 150 km/h. Certificado ISO:9001 | E3: AMARA | F3: 32 | H3: =estructura -> Coplanaria aluminio
A4: Inclinada aluminio con lastre sobre cubierta plana | C4: SUNFER | D4: Soporte inclinado de aluminio con lastre, incluyendo juntas de estanqueidad, con perfilería de aluminio EN AW 6005A T6 y tornillería de acero inoxidable A2-70. Soporta cargas de viento de hasta 150 km/h. Certificado ISO:9001 | E4: AMARA | F4: 48
A5: Inclinada Este-Oeste con Lastre sobre cubierta plana | C5: SUNFER | D5: Soporte inclinado Este-Oeste, con lastre, sobre cubierta plana. incluyendo juntas de estanqueidad, con perfilería de aluminio EN AW 6005A T6 y tornillería de acero inoxidable A2-70. Soporta cargas de viento de hasta 150 km/h. Certificado ISO:9001 | E5: AMARA | F5: 59
A6: Inclinada aluminio sobre cubierta plana | C6: SUNFER | D6: Soporte inclinado de aluminio sobre cubierta plana, incluyendo juntas de estanqueidad, con perfilería de aluminio EN AW 6005A T6 y tornillería de acero inoxidable A2-70. Soporta cargas de viento de hasta 150 km/h. Certificado ISO:9001 | E6: AMARA | F6: 37
A7: Coplanaria aluminio Microrraíles | C7: SUNFER | D7: Soporte coplanar microrail de fijación a chapa, apto para cubiertas metálicas de chapa o panel sandwich. Soporta cargas de viento de hasta 150 km/h. Certificado ISO:9001 | E7: AMARA | F7: 24
A8: Inclinada con monobloque prefabricado de hormigón sobre cubierta plana | C8: SOLARBLOC | D8: Estructura inclinada prefabricada con monobloque de hormigón lastrado sobre cubierta plana. Soporta cargas de viento de hasta 150 km/h. Certificado ISO:9001 | E8: AMARA | F8: 51
A9: Pérgola de Acero Galvanizado | C9: SUNFER | D9: Pérgola Especial de Acero Galvanizado | E9: AMARA | F9: 142
A10: Pérgola de Aluminio | C10: SUNFER | D10: Pérgola Especial de Aluminio Lacado | E10: AMARA | F10: 160
A11: Pérgola Bioclimática | C11: BIOCLIM | D11: Pérgola Bioclimática de Aluminio Estanca Pintada, con canalón y cableado oculto | E11: AMARA | F11: 280

Sheet t.opt
A1: tabla_optimizadores
A2: Modelo | B2: Fabricante | C2: Descripción | D2: Proveedor | E2: Garantía producto | F2: Garantía producción | G2: Potencia (Wp) | H2: Coste Neto (€/Ud de módulo)
A3: Sin Optimizador
A4: Smart PV Huawei SUN2000-600W-P | B4: HUAWEI | C4: Optimizador con tecnología de seguimiernto de máxima potencia (MPPT) para asegurar que cada panel esté produciendo la máxima candidad de energía en todo momento | D4: HUAWEI | E4: 15 | G4: 600 | H4: 44.75
A5: Smart PV Huawei SUN2000-600W-P | B5: HUAWEI | C5: Optimizador con tecnología de seguimiernto de máxima potencia (MPPT) para asegurar que cada panel esté produciendo la máxima candidad de energía en todo momento | D5: HUAWEI | E5: 15 | G5: 600 | H5: 46.75

Sheet t.met
A1: tabla_meter
A2: Modelo de Meter | B2: Fabricante | C2: Descripción | D2: Proveedor | E2: Tipo | F2: Coste Neto (€)
A3: Medidor Trifásico DTSU DEYE | B3: DEYE | C3: Medidor Trifásico DEYE | D3: WCCSOLAR | E3: Trifásico, medida indirecta | F3: 111.57
A4: Medidor Monofásico DTSU DEYE | B4: DEYE | C4: Medidor Monofásico DEYE | D4: WCCSOLAR | E4: Trifásico, medida indirecta | F4: 50
A5: Medidor Monofásico FOX-ESS | B5: FOX | C5: Medidor Monofásico FOX | D5: FOX | E5: Monofásico, medida indirecta | F5: 80
A6: Medidor Monofásico DDSU | B6: HUAWEI | C6: Medidor Monofásico DDSU Huawei | D6: AMARA | E6: Monofásico, medida indirecta | F6: 95
A7: Medidor Trifásico DTSU | B7: HUAWEI | C7: Medidor Trifásico DTSU Huawei | D7: AMARA | E7: Trifásico, medida indirecta | F7: 135
A8: SmartLogger 3000A | B8: HUAWEI | C8: SmartLogger 3000A Huawei | D8: AMARA | E8: SmartLogger | F8: 462
A9: Enphase Envoy-S Mono/Tri - Metered | B9: ENHPASE | C9: Medidor Enhpase Trifásico Monitorización | D9: ALASKA | E9: Trifásico, medida indirecta | F9: 301.63

Sheet t.bms
A1: tabla_bms
A2: Modelo de Batería / BMS | B2: Descripción Larga | C2: Fabricante | D2: Descripción | E2: Proveedor | F2: Capacidad (kWh) | G2: Coste Neto (€) | H2: Proveedor | I2: fecha Precio
A3: BMS LUNA 2000 | B3: HUAWEI BCU-PowerModule LUNA2000 | C3: HUAWEI | D3: BMS para Batería Luna2000 | E3: AMARA | F3: - | G3: 735 | H3: Amara | I3: 45049
A4: GROWATT | C4: GROWATT | D4: BMS para Batería Growatt | E4: AMARA | F4: - | G4: 2191.75 | H4: Amara | I4: 45049
A5: BMS Integrada en Inversor | B5: BMS Integrada en Inversor | C5: DEYE | D5: BMS Integrada | E5: WCC | F5: - | G5: 0

Sheet t.mon
A1: tabla_montaje
A2: Número de Módulos | B2: Descripción | C2: Potencia Pico Generador (Wp) | D2: Proveedor | E2: Precio Montaje (€/Wp) | F2: Precio de Montaje Total (€) | G2: herrera
A3: 0 | C3: =A3*datos!$C$63 -> 0 | D3: ENRIQUE HERRERA | E3: 0 | F3: 0 | G3: 800
A4: 1 | C4: =A4*datos!$C$63 -> 605 | D4: ENRIQUE HERRERA | E4: =F4/C4 -> 1.4049587 | F4: =IF(C4<=3000,850, IF(C4<=3500,900, IF(C4<=4000,1050, IF(C4<=5000,1250, IF(C4<=6000,1350, IF(C4<=7000,1400, IF(C4<=8000,1450, IF(C4<=9000,1500, IF(C4<=10000,1600, IF(C4<=11000,1700, IF(C4<=12000,1800, IF(C4<=13000,1850, IF(C4<=14000,1900, IF(C4<=15000,1950, IF(C4<=16000,2000, IF(C4<=17000,2100, IF(C4<=18000,2200, IF(C4<=19000,2300, IF(C4<=20000,C4*0.118, IF(C4<=30000,C4*0.116, IF(C4<=40000,C4*0.114, IF(C4<=50000,C4*0.112, IF(C4<=60000,C4*0.11, IF(C4<=70000,C4*0.108, IF(C4<=80000,C4*0.106, IF(C4<=90000,C4*0.104, IF(C4<=100000,C4*0.102, IF(C4<=110000,C4*0.1, IF(C4<=120000,C4*0.098, IF(C4<=130000,C4*0.098, IF(C4<=140000,C4*0.098, IF(C4<=150000,C4*0.098, IF(C4<=160000,C4*0.098, ))))))))))))))))))))))))))))))))) -> 850
A5: 2 | C5: =A5*datos!$C$63 -> 1210 | D5: ENRIQUE HERRERA | E5: =F5/C5 -> 0.70247934 | F5: =IF(C5<=3000,850, IF(C5<=3500,900, IF(C5<=4000,1050, IF(C5<=5000,1250, IF(C5<=6000,1350, IF(C5<=7000,1400, IF(C5<=8000,1450, IF(C5<=9000,1500, IF(C5<=10000,1600, IF(C5<=11000,1700, IF(C5<=12000,1800, IF(C5<=13000,1850, IF(C5<=14000,1900, IF(C5<=15000,1950, IF(C5<=16000,2000, IF(C5<=17000,2100, IF(C5<=18000,2200, IF(C5<=19000,2300, IF(C5<=20000,C5*0.118, IF(C5<=30000,C5*0.116, IF(C5<=40000,C5*0.114, IF(C5<=50000,C5*0.112, IF(C5<=60000,C5*0.11, IF(C5<=70000,C5*0.108, IF(C5<=80000,C5*0.106, IF(C5<=90000,C5*0.104, IF(C5<=100000,C5*0.102, IF(C5<=110000,C5*0.1, IF(C5<=120000,C5*0.098, IF(C5<=130000,C5*0.098, IF(C5<=140000,C5*0.098, IF(C5<=150000,C5*0.098, IF(C5<=160000,C5*0.098, ))))))))))))))))))))))))))))))))) -> 850
A6: 3 | C6: =A6*datos!$C$63 -> 1815 | D6: ENRIQUE HERRERA | E6: =F6/C6 -> 0.46831956 | F6: =IF(C6<=3000,850, IF(C6<=3500,900, IF(C6<=4000,1050, IF(C6<=5000,1250, IF(C6<=6000,1350, IF(C6<=7000,1400, IF(C6<=8000,1450, IF(C6<=9000,1500, IF(C6<=10000,1600, IF(C6<=11000,1700, IF(C6<=12000,1800, IF(C6<=13000,1850, IF(C6<=14000,1900, IF(C6<=15000,1950, IF(C6<=16000,2000, IF(C6<=17000,2100, IF(C6<=18000,2200, IF(C6<=19000,2300, IF(C6<=20000,C6*0.118, IF(C6<=30000,C6*0.116, IF(C6<=40000,C6*0.114, IF(C6<=50000,C6*0.112, IF(C6<=60000,C6*0.11, IF(C6<=70000,C6*0.108, IF(C6<=80000,C6*0.106, IF(C6<=90000,C6*0.104, IF(C6<=100000,C6*0.102, IF(C6<=110000,C6*0.1, IF(C6<=120000,C6*0.098, IF(C6<=130000,C6*0.098, IF(C6<=140000,C6*0.098, IF(C6<=150000,C6*0.098, IF(C6<=160000,C6*0.098, ))))))))))))))))))))))))))))))))) -> 850
A7: 4 | C7: =A7*datos!$C$63 -> 2420 | D7: ENRIQUE HERRERA | E7: =F7/C7 -> 0.35123967 | F7: =IF(C7<=3000,850, IF(C7<=3500,900, IF(C7<=4000,1050, IF(C7<=5000,1250, IF(C7<=6000,1350, IF(C7<=7000,1400, IF(C7<=8000,1450, IF(C7<=9000,1500, IF(C7<=10000,1600, IF(C7<=11000,1700, IF(C7<=12000,1800, IF(C7<=13000,1850, IF(C7<=14000,1900, IF(C7<=15000,1950, IF(C7<=16000,2000, IF(C7<=17000,2100, IF(C7<=18000,2200, IF(C7<=19000,2300, IF(C7<=20000,C7*0.118, IF(C7<=30000,C7*0.116, IF(C7<=40000,C7*0.114, IF(C7<=50000,C7*0.112, IF(C7<=60000,C7*0.11, IF(C7<=70000,C7*0.108, IF(C7<=80000,C7*0.106, IF(C7<=90000,C7*0.104, IF(C7<=100000,C7*0.102, IF(C7<=110000,C7*0.1, IF(C7<=120000,C7*0.098, IF(C7<=130000,C7*0.098, IF(C7<=140000,C7*0.098, IF(C7<=150000,C7*0.098, IF(C7<=160000,C7*0.098, ))))))))))))))))))))))))))))))))) -> 850
A8: 5 | C8: =A8*datos!$C$63 -> 3025 | D8: ENRIQUE HERRERA | E8: =F8/C8 -> 0.29752066 | F8: =IF(C8<=3000,850, IF(C8<=3500,900, IF(C8<=4000,1050, IF(C8<=5000,1250, IF(C8<=6000,1350, IF(C8<=7000,1400, IF(C8<=8000,1450, IF(C8<=9000,1500, IF(C8<=10000,1600, IF(C8<=11000,1700, IF(C8<=12000,1800, IF(C8<=13000,1850, IF(C8<=14000,1900, IF(C8<=15000,1950, IF(C8<=16000,2000, IF(C8<=17000,2100, IF(C8<=18000,2200, IF(C8<=19000,2300, IF(C8<=20000,C8*0.118, IF(C8<=30000,C8*0.116, IF(C8<=40000,C8*0.114, IF(C8<=50000,C8*0.112, IF(C8<=60000,C8*0.11, IF(C8<=70000,C8*0.108, IF(C8<=80000,C8*0.106, IF(C8<=90000,C8*0.104, IF(C8<=100000,C8*0.102, IF(C8<=110000,C8*0.1, IF(C8<=120000,C8*0.098, IF(C8<=130000,C8*0.098, IF(C8<=140000,C8*0.098, IF(C8<=150000,C8*0.098, IF(C8<=160000,C8*0.098, ))))))))))))))))))))))))))))))))) -> 900
A9: 6 | C9: =A9*datos!$C$63 -> 3630 | D9: ENRIQUE HERRERA | E9: =F9/C9 -> 0.2892562 | F9: =IF(C9<=3000,850, IF(C9<=3500,900, IF(C9<=4000,1050, IF(C9<=5000,1250, IF(C9<=6000,1350, IF(C9<=7000,1400, IF(C9<=8000,1450, IF(C9<=9000,1500, IF(C9<=10000,1600, IF(C9<=11000,1700, IF(C9<=12000,1800, IF(C9<=13000,1850, IF(C9<=14000,1900, IF(C9<=15000,1950, IF(C9<=16000,2000, IF(C9<=17000,2100, IF(C9<=18000,2200, IF(C9<=19000,2300, IF(C9<=20000,C9*0.118, IF(C9<=30000,C9*0.116, IF(C9<=40000,C9*0.114, IF(C9<=50000,C9*0.112, IF(C9<=60000,C9*0.11, IF(C9<=70000,C9*0.108, IF(C9<=80000,C9*0.106, IF(C9<=90000,C9*0.104, IF(C9<=100000,C9*0.102, IF(C9<=110000,C9*0.1, IF(C9<=120000,C9*0.098, IF(C9<=130000,C9*0.098, IF(C9<=140000,C9*0.098, IF(C9<=150000,C9*0.098, IF(C9<=160000,C9*0.098, ))))))))))))))))))))))))))))))))) -> 1050
A10: 7 | C10: =A10*datos!$C$63 -> 4235 | D10: ENRIQUE HERRERA | E10: =F10/C10 -> 0.29515939 | F10: =IF(C10<=3000,850, IF(C10<=3500,900, IF(C10<=4000,1050, IF(C10<=5000,1250, IF(C10<=6000,1350, IF(C10<=7000,1400, IF(C10<=8000,1450, IF(C10<=9000,1500, IF(C10<=10000,1600, IF(C10<=11000,1700, IF(C10<=12000,1800, IF(C10<=13000,1850, IF(C10<=14000,1900, IF(C10<=15000,1950, IF(C10<=16000,2000, IF(C10<=17000,2100, IF(C10<=18000,2200, IF(C10<=19000,2300, IF(C10<=20000,C10*0.118, IF(C10<=30000,C10*0.116, IF(C10<=40000,C10*0.114, IF(C10<=50000,C10*0.112, IF(C10<=60000,C10*0.11, IF(C10<=70000,C10*0.108, IF(C10<=80000,C10*0.106, IF(C10<=90000,C10*0.104, IF(C10<=100000,C10*0.102, IF(C10<=110000,C10*0.1, IF(C10<=120000,C10*0.098, IF(C10<=130000,C10*0.098, IF(C10<=140000,C10*0.098, IF(C10<=150000,C10*0.098, IF(C10<=160000,C10*0.098, ))))))))))))))))))))))))))))))))) -> 1250 | G10: 1000
A11: 8 | C11: =A11*datos!$C$63 -> 4840 | D11: ENRIQUE HERRERA | E11: =F11/C11 -> 0.25826446 | F11: =IF(C11<=3000,850, IF(C11<=3500,900, IF(C11<=4000,1050, IF(C11<=5000,1250, IF(C11<=6000,1350, IF(C11<=7000,1400, IF(C11<=8000,1450, IF(C11<=9000,1500, IF(C11<=10000,1600, IF(C11<=11000,1700, IF(C11<=12000,1800, IF(C11<=13000,1850, IF(C11<=14000,1900, IF(C11<=15000,1950, IF(C11<=16000,2000, IF(C11<=17000,2100, IF(C11<=18000,2200, IF(C11<=19000,2300, IF(C11<=20000,C11*0.118, IF(C11<=30000,C11*0.116, IF(C11<=40000,C11*0.114, IF(C11<=50000,C11*0.112, IF(C11<=60000,C11*0.11, IF(C11<=70000,C11*0.108, IF(C11<=80000,C11*0.106, IF(C11<=90000,C11*0.104, IF(C11<=100000,C11*0.102, IF(C11<=110000,C11*0.1, IF(C11<=120000,C11*0.098, IF(C11<=130000,C11*0.098, IF(C11<=140000,C11*0.098, IF(C11<=150000,C11*0.098, IF(C11<=160000,C11*0.098, ))))))))))))))))))))))))))))))))) -> 1250 | G11: 1200
A12: 9 | C12: =A12*datos!$C$63 -> 5445 | D12: ENRIQUE HERRERA | E12: =F12/C12 -> 0.24793388 | F12: =IF(C12<=3000,850, IF(C12<=3500,900, IF(C12<=4000,1050, IF(C12<=5000,1250, IF(C12<=6000,1350, IF(C12<=7000,1400, IF(C12<=8000,1450, IF(C12<=9000,1500, IF(C12<=10000,1600, IF(C12<=11000,1700, IF(C12<=12000,1800, IF(C12<=13000,1850, IF(C12<=14000,1900, IF(C12<=15000,1950, IF(C12<=16000,2000, IF(C12<=17000,2100, IF(C12<=18000,2200, IF(C12<=19000,2300, IF(C12<=20000,C12*0.118, IF(C12<=30000,C12*0.116, IF(C12<=40000,C12*0.114, IF(C12<=50000,C12*0.112, IF(C12<=60000,C12*0.11, IF(C12<=70000,C12*0.108, IF(C12<=80000,C12*0.106, IF(C12<=90000,C12*0.104, IF(C12<=100000,C12*0.102, IF(C12<=110000,C12*0.1, IF(C12<=120000,C12*0.098, IF(C12<=130000,C12*0.098, IF(C12<=140000,C12*0.098, IF(C12<=150000,C12*0.098, IF(C12<=160000,C12*0.098, ))))))))))))))))))))))))))))))))) -> 1350
A13: 10 | C13: =A13*datos!$C$63 -> 6050 | D13: ENRIQUE HERRERA | E13: =F13/C13 -> 0.23140496 | F13: =IF(C13<=3000,850, IF(C13<=3500,900, IF(C13<=4000,1050, IF(C13<=5000,1250, IF(C13<=6000,1350, IF(C13<=7000,1400, IF(C13<=8000,1450, IF(C13<=9000,1500, IF(C13<=10000,1600, IF(C13<=11000,1700, IF(C13<=12000,1800, IF(C13<=13000,1850, IF(C13<=14000,1900, IF(C13<=15000,1950, IF(C13<=16000,2000, IF(C13<=17000,2100, IF(C13<=18000,2200, IF(C13<=19000,2300, IF(C13<=20000,C13*0.118, IF(C13<=30000,C13*0.116, IF(C13<=40000,C13*0.114, IF(C13<=50000,C13*0.112, IF(C13<=60000,C13*0.11, IF(C13<=70000,C13*0.108, IF(C13<=80000,C13*0.106, IF(C13<=90000,C13*0.104, IF(C13<=100000,C13*0.102, IF(C13<=110000,C13*0.1, IF(C13<=120000,C13*0.098, IF(C13<=130000,C13*0.098, IF(C13<=140000,C13*0.098, IF(C13<=150000,C13*0.098, IF(C13<=160000,C13*0.098, ))))))))))))))))))))))))))))))))) -> 1400
A14: 11 | C14: =A14*datos!$C$63 -> 6655 | D14: ENRIQUE HERRERA | E14: =F14/C14 -> 0.21036814 | F14: =IF(C14<=3000,850, IF(C14<=3500,900, IF(C14<=4000,1050, IF(C14<=5000,1250, IF(C14<=6000,1350, IF(C14<=7000,1400, IF(C14<=8000,1450, IF(C14<=9000,1500, IF(C14<=10000,1600, IF(C14<=11000,1700, IF(C14<=12000,1800, IF(C14<=13000,1850, IF(C14<=14000,1900, IF(C14<=15000,1950, IF(C14<=16000,2000, IF(C14<=17000,2100, IF(C14<=18000,2200, IF(C14<=19000,2300, IF(C14<=20000,C14*0.118, IF(C14<=30000,C14*0.116, IF(C14<=40000,C14*0.114, IF(C14<=50000,C14*0.112, IF(C14<=60000,C14*0.11, IF(C14<=70000,C14*0.108, IF(C14<=80000,C14*0.106, IF(C14<=90000,C14*0.104, IF(C14<=100000,C14*0.102, IF(C14<=110000,C14*0.1, IF(C14<=120000,C14*0.098, IF(C14<=130000,C14*0.098, IF(C14<=140000,C14*0.098, IF(C14<=150000,C14*0.098, IF(C14<=160000,C14*0.098, ))))))))))))))))))))))))))))))))) -> 1400 | G14: 1300
A15: 12 | C15: =A15*datos!$C$63 -> 7260 | D15: ENRIQUE HERRERA | E15: =F15/C15 -> 0.19972452 | F15: =IF(C15<=3000,850, IF(C15<=3500,900, IF(C15<=4000,1050, IF(C15<=5000,1250, IF(C15<=6000,1350, IF(C15<=7000,1400, IF(C15<=8000,1450, IF(C15<=9000,1500, IF(C15<=10000,1600, IF(C15<=11000,1700, IF(C15<=12000,1800, IF(C15<=13000,1850, IF(C15<=14000,1900, IF(C15<=15000,1950, IF(C15<=16000,2000, IF(C15<=17000,2100, IF(C15<=18000,2200, IF(C15<=19000,2300, IF(C15<=20000,C15*0.118, IF(C15<=30000,C15*0.116, IF(C15<=40000,C15*0.114, IF(C15<=50000,C15*0.112, IF(C15<=60000,C15*0.11, IF(C15<=70000,C15*0.108, IF(C15<=80000,C15*0.106, IF(C15<=90000,C15*0.104, IF(C15<=100000,C15*0.102, IF(C15<=110000,C15*0.1, IF(C15<=120000,C15*0.098, IF(C15<=130000,C15*0.098, IF(C15<=140000,C15*0.098, IF(C15<=150000,C15*0.098, IF(C15<=160000,C15*0.098, ))))))))))))))))))))))))))))))))) -> 1450
A16: 13 | C16: =A16*datos!$C$63 -> 7865 | D16: ENRIQUE HERRERA | E16: =F16/C16 -> 0.18436109 | F16: =IF(C16<=3000,850, IF(C16<=3500,900, IF(C16<=4000,1050, IF(C16<=5000,1250, IF(C16<=6000,1350, IF(C16<=7000,1400, IF(C16<=8000,1450, IF(C16<=9000,1500, IF(C16<=10000,1600, IF(C16<=11000,1700, IF(C16<=12000,1800, IF(C16<=13000,1850, IF(C16<=14000,1900, IF(C16<=15000,1950, IF(C16<=16000,2000, IF(C16<=17000,2100, IF(C16<=18000,2200, IF(C16<=19000,2300, IF(C16<=20000,C16*0.118, IF(C16<=30000,C16*0.116, IF(C16<=40000,C16*0.114, IF(C16<=50000,C16*0.112, IF(C16<=60000,C16*0.11, IF(C16<=70000,C16*0.108, IF(C16<=80000,C16*0.106, IF(C16<=90000,C16*0.104, IF(C16<=100000,C16*0.102, IF(C16<=110000,C16*0.1, IF(C16<=120000,C16*0.098, IF(C16<=130000,C16*0.098, IF(C16<=140000,C16*0.098, IF(C16<=150000,C16*0.098, IF(C16<=160000,C16*0.098, ))))))))))))))))))))))))))))))))) -> 1450
A17: 14 | C17: =A17*datos!$C$63 -> 8470 | D17: ENRIQUE HERRERA | E17: =F17/C17 -> 0.17709563 | F17: =IF(C17<=3000,850, IF(C17<=3500,900, IF(C17<=4000,1050, IF(C17<=5000,1250, IF(C17<=6000,1350, IF(C17<=7000,1400, IF(C17<=8000,1450, IF(C17<=9000,1500, IF(C17<=10000,1600, IF(C17<=11000,1700, IF(C17<=12000,1800, IF(C17<=13000,1850, IF(C17<=14000,1900, IF(C17<=15000,1950, IF(C17<=16000,2000, IF(C17<=17000,2100, IF(C17<=18000,2200, IF(C17<=19000,2300, IF(C17<=20000,C17*0.118, IF(C17<=30000,C17*0.116, IF(C17<=40000,C17*0.114, IF(C17<=50000,C17*0.112, IF(C17<=60000,C17*0.11, IF(C17<=70000,C17*0.108, IF(C17<=80000,C17*0.106, IF(C17<=90000,C17*0.104, IF(C17<=100000,C17*0.102, IF(C17<=110000,C17*0.1, IF(C17<=120000,C17*0.098, IF(C17<=130000,C17*0.098, IF(C17<=140000,C17*0.098, IF(C17<=150000,C17*0.098, IF(C17<=160000,C17*0.098, ))))))))))))))))))))))))))))))))) -> 1500
A18: 15 | C18: =A18*datos!$C$63 -> 9075 | D18: ENRIQUE HERRERA | E18: =F18/C18 -> 0.17630854 | F18: =IF(C18<=3000,850, IF(C18<=3500,900, IF(C18<=4000,1050, IF(C18<=5000,1250, IF(C18<=6000,1350, IF(C18<=7000,1400, IF(C18<=8000,1450, IF(C18<=9000,1500, IF(C18<=10000,1600, IF(C18<=11000,1700, IF(C18<=12000,1800, IF(C18<=13000,1850, IF(C18<=14000,1900, IF(C18<=15000,1950, IF(C18<=16000,2000, IF(C18<=17000,2100, IF(C18<=18000,2200, IF(C18<=19000,2300, IF(C18<=20000,C18*0.118, IF(C18<=30000,C18*0.116, IF(C18<=40000,C18*0.114, IF(C18<=50000,C18*0.112, IF(C18<=60000,C18*0.11, IF(C18<=70000,C18*0.108, IF(C18<=80000,C18*0.106, IF(C18<=90000,C18*0.104, IF(C18<=100000,C18*0.102, IF(C18<=110000,C18*0.1, IF(C18<=120000,C18*0.098, IF(C18<=130000,C18*0.098, IF(C18<=140000,C18*0.098, IF(C18<=150000,C18*0.098, IF(C18<=160000,C18*0.098, ))))))))))))))))))))))))))))))))) -> 1600
A19: 16 | C19: =A19*datos!$C$63 -> 9680 | D19: ENRIQUE HERRERA | E19: =F19/C19 -> 0.16528926 | F19: =IF(C19<=3000,850, IF(C19<=3500,900, IF(C19<=4000,1050, IF(C19<=5000,1250, IF(C19<=6000,1350, IF(C19<=7000,1400, IF(C19<=8000,1450, IF(C19<=9000,1500, IF(C19<=10000,1600, IF(C19<=11000,1700, IF(C19<=12000,1800, IF(C19<=13000,1850, IF(C19<=14000,1900, IF(C19<=15000,1950, IF(C19<=16000,2000, IF(C19<=17000,2100, IF(C19<=18000,2200, IF(C19<=19000,2300, IF(C19<=20000,C19*0.118, IF(C19<=30000,C19*0.116, IF(C19<=40000,C19*0.114, IF(C19<=50000,C19*0.112, IF(C19<=60000,C19*0.11, IF(C19<=70000,C19*0.108, IF(C19<=80000,C19*0.106, IF(C19<=90000,C19*0.104, IF(C19<=100000,C19*0.102, IF(C19<=110000,C19*0.1, IF(C19<=120000,C19*0.098, IF(C19<=130000,C19*0.098, IF(C19<=140000,C19*0.098, IF(C19<=150000,C19*0.098, IF(C19<=160000,C19*0.098, ))))))))))))))))))))))))))))))))) -> 1600
A20: 17 | C20: =A20*datos!$C$63 -> 10285 | D20: ENRIQUE HERRERA | E20: =F20/C20 -> 0.16528926 | F20: =IF(C20<=3000,850, IF(C20<=3500,900, IF(C20<=4000,1050, IF(C20<=5000,1250, IF(C20<=6000,1350, IF(C20<=7000,1400, IF(C20<=8000,1450, IF(C20<=9000,1500, IF(C20<=10000,1600, IF(C20<=11000,1700, IF(C20<=12000,1800, IF(C20<=13000,1850, IF(C20<=14000,1900, IF(C20<=15000,1950, IF(C20<=16000,2000, IF(C20<=17000,2100, IF(C20<=18000,2200, IF(C20<=19000,2300, IF(C20<=20000,C20*0.118, IF(C20<=30000,C20*0.116, IF(C20<=40000,C20*0.114, IF(C20<=50000,C20*0.112, IF(C20<=60000,C20*0.11, IF(C20<=70000,C20*0.108, IF(C20<=80000,C20*0.106, IF(C20<=90000,C20*0.104, IF(C20<=100000,C20*0.102, IF(C20<=110000,C20*0.1, IF(C20<=120000,C20*0.098, IF(C20<=130000,C20*0.098, IF(C20<=140000,C20*0.098, IF(C20<=150000,C20*0.098, IF(C20<=160000,C20*0.098, ))))))))))))))))))))))))))))))))) -> 1700
A21: 18 | C21: =A21*datos!$C$63 -> 10890 | D21: ENRIQUE HERRERA | E21: =F21/C21 -> 0.15610652 | F21: =IF(C21<=3000,850, IF(C21<=3500,900, IF(C21<=4000,1050, IF(C21<=5000,1250, IF(C21<=6000,1350, IF(C21<=7000,1400, IF(C21<=8000,1450, IF(C21<=9000,1500, IF(C21<=10000,1600, IF(C21<=11000,1700, IF(C21<=12000,1800, IF(C21<=13000,1850, IF(C21<=14000,1900, IF(C21<=15000,1950, IF(C21<=16000,2000, IF(C21<=17000,2100, IF(C21<=18000,2200, IF(C21<=19000,2300, IF(C21<=20000,C21*0.118, IF(C21<=30000,C21*0.116, IF(C21<=40000,C21*0.114, IF(C21<=50000,C21*0.112, IF(C21<=60000,C21*0.11, IF(C21<=70000,C21*0.108, IF(C21<=80000,C21*0.106, IF(C21<=90000,C21*0.104, IF(C21<=100000,C21*0.102, IF(C21<=110000,C21*0.1, IF(C21<=120000,C21*0.098, IF(C21<=130000,C21*0.098, IF(C21<=140000,C21*0.098, IF(C21<=150000,C21*0.098, IF(C21<=160000,C21*0.098, ))))))))))))))))))))))))))))))))) -> 1700
A22: 19 | C22: =A22*datos!$C$63 -> 11495 | D22: ENRIQUE HERRERA | E22: =F22/C22 -> 0.15658982 | F22: =IF(C22<=3000,850, IF(C22<=3500,900, IF(C22<=4000,1050, IF(C22<=5000,1250, IF(C22<=6000,1350, IF(C22<=7000,1400, IF(C22<=8000,1450, IF(C22<=9000,1500, IF(C22<=10000,1600, IF(C22<=11000,1700, IF(C22<=12000,1800, IF(C22<=13000,1850, IF(C22<=14000,1900, IF(C22<=15000,1950, IF(C22<=16000,2000, IF(C22<=17000,2100, IF(C22<=18000,2200, IF(C22<=19000,2300, IF(C22<=20000,C22*0.118, IF(C22<=30000,C22*0.116, IF(C22<=40000,C22*0.114, IF(C22<=50000,C22*0.112, IF(C22<=60000,C22*0.11, IF(C22<=70000,C22*0.108, IF(C22<=80000,C22*0.106, IF(C22<=90000,C22*0.104, IF(C22<=100000,C22*0.102, IF(C22<=110000,C22*0.1, IF(C22<=120000,C22*0.098, IF(C22<=130000,C22*0.098, IF(C22<=140000,C22*0.098, IF(C22<=150000,C22*0.098, IF(C22<=160000,C22*0.098, ))))))))))))))))))))))))))))))))) -> 1800
A23: 20 | C23: =A23*datos!$C$63 -> 12100 | D23: ENRIQUE HERRERA | E23: =F23/C23 -> 0.15289256 | F23: =IF(C23<=3000,850, IF(C23<=3500,900, IF(C23<=4000,1050, IF(C23<=5000,1250, IF(C23<=6000,1350, IF(C23<=7000,1400, IF(C23<=8000,1450, IF(C23<=9000,1500, IF(C23<=10000,1600, IF(C23<=11000,1700, IF(C23<=12000,1800, IF(C23<=13000,1850, IF(C23<=14000,1900, IF(C23<=15000,1950, IF(C23<=16000,2000, IF(C23<=17000,2100, IF(C23<=18000,2200, IF(C23<=19000,2300, IF(C23<=20000,C23*0.118, IF(C23<=30000,C23*0.116, IF(C23<=40000,C23*0.114, IF(C23<=50000,C23*0.112, IF(C23<=60000,C23*0.11, IF(C23<=70000,C23*0.108, IF(C23<=80000,C23*0.106, IF(C23<=90000,C23*0.104, IF(C23<=100000,C23*0.102, IF(C23<=110000,C23*0.1, IF(C23<=120000,C23*0.098, IF(C23<=130000,C23*0.098, IF(C23<=140000,C23*0.098, IF(C23<=150000,C23*0.098, IF(C23<=160000,C23*0.098, ))))))))))))))))))))))))))))))))) -> 1850
A24: 21 | C24: =A24*datos!$C$63 -> 12705 | D24: ENRIQUE HERRERA | E24: =F24/C24 -> 0.14561196 | F24: =IF(C24<=3000,850, IF(C24<=3500,900, IF(C24<=4000,1050, IF(C24<=5000,1250, IF(C24<=6000,1350, IF(C24<=7000,1400, IF(C24<=8000,1450, IF(C24<=9000,1500, IF(C24<=10000,1600, IF(C24<=11000,1700, IF(C24<=12000,1800, IF(C24<=13000,1850, IF(C24<=14000,1900, IF(C24<=15000,1950, IF(C24<=16000,2000, IF(C24<=17000,2100, IF(C24<=18000,2200, IF(C24<=19000,2300, IF(C24<=20000,C24*0.118, IF(C24<=30000,C24*0.116, IF(C24<=40000,C24*0.114, IF(C24<=50000,C24*0.112, IF(C24<=60000,C24*0.11, IF(C24<=70000,C24*0.108, IF(C24<=80000,C24*0.106, IF(C24<=90000,C24*0.104, IF(C24<=100000,C24*0.102, IF(C24<=110000,C24*0.1, IF(C24<=120000,C24*0.098, IF(C24<=130000,C24*0.098, IF(C24<=140000,C24*0.098, IF(C24<=150000,C24*0.098, IF(C24<=160000,C24*0.098, ))))))))))))))))))))))))))))))))) -> 1850
A25: 22 | C25: =A25*datos!$C$63 -> 13310 | D25: ENRIQUE HERRERA | E25: =F25/C25 -> 0.14274981 | F25: =IF(C25<=3000,850, IF(C25<=3500,900, IF(C25<=4000,1050, IF(C25<=5000,1250, IF(C25<=6000,1350, IF(C25<=7000,1400, IF(C25<=8000,1450, IF(C25<=9000,1500, IF(C25<=10000,1600, IF(C25<=11000,1700, IF(C25<=12000,1800, IF(C25<=13000,1850, IF(C25<=14000,1900, IF(C25<=15000,1950, IF(C25<=16000,2000, IF(C25<=17000,2100, IF(C25<=18000,2200, IF(C25<=19000,2300, IF(C25<=20000,C25*0.118, IF(C25<=30000,C25*0.116, IF(C25<=40000,C25*0.114, IF(C25<=50000,C25*0.112, IF(C25<=60000,C25*0.11, IF(C25<=70000,C25*0.108, IF(C25<=80000,C25*0.106, IF(C25<=90000,C25*0.104, IF(C25<=100000,C25*0.102, IF(C25<=110000,C25*0.1, IF(C25<=120000,C25*0.098, IF(C25<=130000,C25*0.098, IF(C25<=140000,C25*0.098, IF(C25<=150000,C25*0.098, IF(C25<=160000,C25*0.098, ))))))))))))))))))))))))))))))))) -> 1900
A26: 23 | C26: =A26*datos!$C$63 -> 13915 | D26: ENRIQUE HERRERA | E26: =F26/C26 -> 0.1365433 | F26: =IF(C26<=3000,850, IF(C26<=3500,900, IF(C26<=4000,1050, IF(C26<=5000,1250, IF(C26<=6000,1350, IF(C26<=7000,1400, IF(C26<=8000,1450, IF(C26<=9000,1500, IF(C26<=10000,1600, IF(C26<=11000,1700, IF(C26<=12000,1800, IF(C26<=13000,1850, IF(C26<=14000,1900, IF(C26<=15000,1950, IF(C26<=16000,2000, IF(C26<=17000,2100, IF(C26<=18000,2200, IF(C26<=19000,2300, IF(C26<=20000,C26*0.118, IF(C26<=30000,C26*0.116, IF(C26<=40000,C26*0.114, IF(C26<=50000,C26*0.112, IF(C26<=60000,C26*0.11, IF(C26<=70000,C26*0.108, IF(C26<=80000,C26*0.106, IF(C26<=90000,C26*0.104, IF(C26<=100000,C26*0.102, IF(C26<=110000,C26*0.1, IF(C26<=120000,C26*0.098, IF(C26<=130000,C26*0.098, IF(C26<=140000,C26*0.098, IF(C26<=150000,C26*0.098, IF(C26<=160000,C26*0.098, ))))))))))))))))))))))))))))))))) -> 1900
... A263: 260 | C263: =A263*datos!$C$63 -> 157300 | D263: ENRIQUE HERRERA | E263: =F263/C263 -> 0.098 | F263: =IF(C263<=3000,850, IF(C263<=3500,900, IF(C263<=4000,1050, IF(C263<=5000,1250, IF(C263<=6000,1350, IF(C263<=7000,1400, IF(C263<=8000,1450, IF(C263<=9000,1500, IF(C263<=10000,1600, IF(C263<=11000,1700, IF(C263<=12000,1800, IF(C263<=13000,1850, IF(C263<=14000,1900, IF(C263<=15000,1950, IF(C263<=16000,2000, IF(C263<=17000,2100, IF(C263<=18000,2200, IF(C263<=19000,2300, IF(C263<=20000,C263*0.118, IF(C263<=30000,C263*0.116, IF(C263<=40000,C263*0.114, IF(C263<=50000,C263*0.112, IF(C263<=60000,C263*0.11, IF(C263<=70000,C263*0.108, IF(C263<=80000,C263*0.106, IF(C263<=90000,C263*0.104, IF(C263<=100000,C263*0.102, IF(C263<=110000,C263*0.1, IF(C263<=120000,C263*0.098, IF(C263<=130000,C263*0.098, IF(C263<=140000,C263*0.098, IF(C263<=150000,C263*0.098, IF(C263<=160000,C263*0.098, ))))))))))))))))))))))))))))))))) -> 15415.4

Sheet t.mar
A1: tabla_margen_de_venta
A2: Número de Módulos | B2: Potencia Pico Generador (Wp) | C2: Margen de Venta (%)
A3: 0 | B3: =A3*p_mod -> 0 | C3: =IF(B3<=3000,0.4, IF(B3<=3000,0.4, IF(B3<=4000,0.39, IF(B3<=5000,0.38, IF(B3<=10000,0.37, IF(B3<=20000,0.36, IF(B3<=30000,0.35, IF(B3<=40000,0.34, IF(B3<=50000,0.33, IF(B3<=60000,0.32, IF(B3<=70000,0.31, IF(B3<=80000,0.3, IF(B3<=90000,0.295, IF(B3<=100000,0.29, IF(B3<=110000,0.285, IF(B3<=120000,0.28, IF(B3<=130000,0.28, IF(B3<=140000,0.28, IF(B3<=150000,0.28, ))))))))))))))))))) -> 0.4
A4: 1 | B4: =A4*p_mod -> 605 | C4: =IF(B4<=3000,0.4, IF(B4<=3000,0.4, IF(B4<=4000,0.39, IF(B4<=5000,0.38, IF(B4<=10000,0.37, IF(B4<=20000,0.36, IF(B4<=30000,0.35, IF(B4<=40000,0.34, IF(B4<=50000,0.33, IF(B4<=60000,0.32, IF(B4<=70000,0.31, IF(B4<=80000,0.3, IF(B4<=90000,0.295, IF(B4<=100000,0.29, IF(B4<=110000,0.285, IF(B4<=120000,0.28, IF(B4<=130000,0.28, IF(B4<=140000,0.28, IF(B4<=150000,0.28, ))))))))))))))))))) -> 0.4
A5: 2 | B5: =A5*p_mod -> 1210 | C5: =IF(B5<=3000,0.4, IF(B5<=3000,0.4, IF(B5<=4000,0.39, IF(B5<=5000,0.38, IF(B5<=10000,0.37, IF(B5<=20000,0.36, IF(B5<=30000,0.35, IF(B5<=40000,0.34, IF(B5<=50000,0.33, IF(B5<=60000,0.32, IF(B5<=70000,0.31, IF(B5<=80000,0.3, IF(B5<=90000,0.295, IF(B5<=100000,0.29, IF(B5<=110000,0.285, IF(B5<=120000,0.28, IF(B5<=130000,0.28, IF(B5<=140000,0.28, IF(B5<=150000,0.28, ))))))))))))))))))) -> 0.4
A6: 3 | B6: =A6*p_mod -> 1815 | C6: =IF(B6<=3000,0.4, IF(B6<=3000,0.4, IF(B6<=4000,0.39, IF(B6<=5000,0.38, IF(B6<=10000,0.37, IF(B6<=20000,0.36, IF(B6<=30000,0.35, IF(B6<=40000,0.34, IF(B6<=50000,0.33, IF(B6<=60000,0.32, IF(B6<=70000,0.31, IF(B6<=80000,0.3, IF(B6<=90000,0.295, IF(B6<=100000,0.29, IF(B6<=110000,0.285, IF(B6<=120000,0.28, IF(B6<=130000,0.28, IF(B6<=140000,0.28, IF(B6<=150000,0.28, ))))))))))))))))))) -> 0.4
A7: 4 | B7: =A7*p_mod -> 2420 | C7: =IF(B7<=3000,0.4, IF(B7<=3000,0.4, IF(B7<=4000,0.39, IF(B7<=5000,0.38, IF(B7<=10000,0.37, IF(B7<=20000,0.36, IF(B7<=30000,0.35, IF(B7<=40000,0.34, IF(B7<=50000,0.33, IF(B7<=60000,0.32, IF(B7<=70000,0.31, IF(B7<=80000,0.3, IF(B7<=90000,0.295, IF(B7<=100000,0.29, IF(B7<=110000,0.285, IF(B7<=120000,0.28, IF(B7<=130000,0.28, IF(B7<=140000,0.28, IF(B7<=150000,0.28, ))))))))))))))))))) -> 0.4
A8: 5 | B8: =A8*p_mod -> 3025 | C8: =IF(B8<=3000,0.4, IF(B8<=3000,0.4, IF(B8<=4000,0.39, IF(B8<=5000,0.38, IF(B8<=10000,0.37, IF(B8<=20000,0.36, IF(B8<=30000,0.35, IF(B8<=40000,0.34, IF(B8<=50000,0.33, IF(B8<=60000,0.32, IF(B8<=70000,0.31, IF(B8<=80000,0.3, IF(B8<=90000,0.295, IF(B8<=100000,0.29, IF(B8<=110000,0.285, IF(B8<=120000,0.28, IF(B8<=130000,0.28, IF(B8<=140000,0.28, IF(B8<=150000,0.28, ))))))))))))))))))) -> 0.39
A9: 6 | B9: =A9*p_mod -> 3630 | C9: =IF(B9<=3000,0.4, IF(B9<=3000,0.4, IF(B9<=4000,0.39, IF(B9<=5000,0.38, IF(B9<=10000,0.37, IF(B9<=20000,0.36, IF(B9<=30000,0.35, IF(B9<=40000,0.34, IF(B9<=50000,0.33, IF(B9<=60000,0.32, IF(B9<=70000,0.31, IF(B9<=80000,0.3, IF(B9<=90000,0.295, IF(B9<=100000,0.29, IF(B9<=110000,0.285, IF(B9<=120000,0.28, IF(B9<=130000,0.28, IF(B9<=140000,0.28, IF(B9<=150000,0.28, ))))))))))))))))))) -> 0.39
A10: 7 | B10: =A10*p_mod -> 4235 | C10: =IF(B10<=3000,0.4, IF(B10<=3000,0.4, IF(B10<=4000,0.39, IF(B10<=5000,0.38, IF(B10<=10000,0.37, IF(B10<=20000,0.36, IF(B10<=30000,0.35, IF(B10<=40000,0.34, IF(B10<=50000,0.33, IF(B10<=60000,0.32, IF(B10<=70000,0.31, IF(B10<=80000,0.3, IF(B10<=90000,0.295, IF(B10<=100000,0.29, IF(B10<=110000,0.285, IF(B10<=120000,0.28, IF(B10<=130000,0.28, IF(B10<=140000,0.28, IF(B10<=150000,0.28, ))))))))))))))))))) -> 0.38
A11: 8 | B11: =A11*p_mod -> 4840 | C11: =IF(B11<=3000,0.4, IF(B11<=3000,0.4, IF(B11<=4000,0.39, IF(B11<=5000,0.38, IF(B11<=10000,0.37, IF(B11<=20000,0.36, IF(B11<=30000,0.35, IF(B11<=40000,0.34, IF(B11<=50000,0.33, IF(B11<=60000,0.32, IF(B11<=70000,0.31, IF(B11<=80000,0.3, IF(B11<=90000,0.295, IF(B11<=100000,0.29, IF(B11<=110000,0.285, IF(B11<=120000,0.28, IF(B11<=130000,0.28, IF(B11<=140000,0.28, IF(B11<=150000,0.28, ))))))))))))))))))) -> 0.38
A12: 9 | B12: =A12*p_mod -> 5445 | C12: =IF(B12<=3000,0.4, IF(B12<=3000,0.4, IF(B12<=4000,0.39, IF(B12<=5000,0.38, IF(B12<=10000,0.37, IF(B12<=20000,0.36, IF(B12<=30000,0.35, IF(B12<=40000,0.34, IF(B12<=50000,0.33, IF(B12<=60000,0.32, IF(B12<=70000,0.31, IF(B12<=80000,0.3, IF(B12<=90000,0.295, IF(B12<=100000,0.29, IF(B12<=110000,0.285, IF(B12<=120000,0.28, IF(B12<=130000,0.28, IF(B12<=140000,0.28, IF(B12<=150000,0.28, ))))))))))))))))))) -> 0.37
A13: 10 | B13: =A13*p_mod -> 6050 | C13: =IF(B13<=3000,0.4, IF(B13<=3000,0.4, IF(B13<=4000,0.39, IF(B13<=5000,0.38, IF(B13<=10000,0.37, IF(B13<=20000,0.36, IF(B13<=30000,0.35, IF(B13<=40000,0.34, IF(B13<=50000,0.33, IF(B13<=60000,0.32, IF(B13<=70000,0.31, IF(B13<=80000,0.3, IF(B13<=90000,0.295, IF(B13<=100000,0.29, IF(B13<=110000,0.285, IF(B13<=120000,0.28, IF(B13<=130000,0.28, IF(B13<=140000,0.28, IF(B13<=150000,0.28, ))))))))))))))))))) -> 0.37
A14: 11 | B14: =A14*p_mod -> 6655 | C14: =IF(B14<=3000,0.4, IF(B14<=3000,0.4, IF(B14<=4000,0.39, IF(B14<=5000,0.38, IF(B14<=10000,0.37, IF(B14<=20000,0.36, IF(B14<=30000,0.35, IF(B14<=40000,0.34, IF(B14<=50000,0.33, IF(B14<=60000,0.32, IF(B14<=70000,0.31, IF(B14<=80000,0.3, IF(B14<=90000,0.295, IF(B14<=100000,0.29, IF(B14<=110000,0.285, IF(B14<=120000,0.28, IF(B14<=130000,0.28, IF(B14<=140000,0.28, IF(B14<=150000,0.28, ))))))))))))))))))) -> 0.37
... A263: 260 | B263: =A263*p_mod -> 157300 | C263: =IF(B263<=3000,0.4, IF(B263<=3000,0.4, IF(B263<=4000,0.39, IF(B263<=5000,0.38, IF(B263<=10000,0.37, IF(B263<=20000,0.36, IF(B263<=30000,0.35, IF(B263<=40000,0.34, IF(B263<=50000,0.33, IF(B263<=60000,0.32, IF(B263<=70000,0.31, IF(B263<=80000,0.3, IF(B263<=90000,0.295, IF(B263<=100000,0.29, IF(B263<=110000,0.285, IF(B263<=120000,0.28, IF(B263<=130000,0.28, IF(B263<=140000,0.28, IF(B263<=150000,0.28, ))))))))))))))))))) -> 0

Sheet t.coi
A1: tabla_costes_indirecto
A2: Número de Módulos | C2: Potencia Pico Generador (Wp) | E2: Gastos de Gestión Solay (€)
A3: 0 | C3: =A3*datos!$C$63 -> 0 | E3: =IF(C3<=3000,700, IF(C3<=4000,800, IF(C3<=5000,850, IF(C3<=6000,900, IF(C3<=7000,950, IF(C3<=8000,1000, IF(C3<=9000,1100, IF(C3<=10000,1200, IF(C3<=15000,1300, IF(C3<=20000,1400, IF(C3<=25000,1500, IF(C3<=30000,1600, IF(C3<=35000,1700, IF(C3<=40000,1800, IF(C3<=45000,1900, IF(C3<=50000,2100, IF(C3<=55000,2200, IF(C3<=60000,2300, IF(C3<=65000,2400, IF(C3<=70000,2500, IF(C3<=75000,2750, IF(C3<=80000,3000, IF(C3<=85000,3250, IF(C3<=90000,3500, IF(C3<=95000,3750, IF(C3<=100000,4000, IF(C3<=105000,4250, IF(C3<=110000,4500, IF(C3<=115000,4750, IF(C3<=120000,5000, )))))))))))))))))))))))))))))) -> 700
A4: 1 | C4: =A4*datos!$C$63 -> 605 | E4: =IF(C4<=3000,700, IF(C4<=4000,800, IF(C4<=5000,850, IF(C4<=6000,900, IF(C4<=7000,950, IF(C4<=8000,1000, IF(C4<=9000,1100, IF(C4<=10000,1200, IF(C4<=15000,1300, IF(C4<=20000,1400, IF(C4<=25000,1500, IF(C4<=30000,1600, IF(C4<=35000,1700, IF(C4<=40000,1800, IF(C4<=45000,1900, IF(C4<=50000,2100, IF(C4<=55000,2200, IF(C4<=60000,2300, IF(C4<=65000,2400, IF(C4<=70000,2500, IF(C4<=75000,2750, IF(C4<=80000,3000, IF(C4<=85000,3250, IF(C4<=90000,3500, IF(C4<=95000,3750, IF(C4<=100000,4000, IF(C4<=105000,4250, IF(C4<=110000,4500, IF(C4<=115000,4750, IF(C4<=120000,5000, )))))))))))))))))))))))))))))) -> 700
A5: 2 | C5: =A5*datos!$C$63 -> 1210 | E5: =IF(C5<=3000,700, IF(C5<=4000,800, IF(C5<=5000,850, IF(C5<=6000,900, IF(C5<=7000,950, IF(C5<=8000,1000, IF(C5<=9000,1100, IF(C5<=10000,1200, IF(C5<=15000,1300, IF(C5<=20000,1400, IF(C5<=25000,1500, IF(C5<=30000,1600, IF(C5<=35000,1700, IF(C5<=40000,1800, IF(C5<=45000,1900, IF(C5<=50000,2100, IF(C5<=55000,2200, IF(C5<=60000,2300, IF(C5<=65000,2400, IF(C5<=70000,2500, IF(C5<=75000,2750, IF(C5<=80000,3000, IF(C5<=85000,3250, IF(C5<=90000,3500, IF(C5<=95000,3750, IF(C5<=100000,4000, IF(C5<=105000,4250, IF(C5<=110000,4500, IF(C5<=115000,4750, IF(C5<=120000,5000, )))))))))))))))))))))))))))))) -> 700
A6: 3 | C6: =A6*datos!$C$63 -> 1815 | E6: =IF(C6<=3000,700, IF(C6<=4000,800, IF(C6<=5000,850, IF(C6<=6000,900, IF(C6<=7000,950, IF(C6<=8000,1000, IF(C6<=9000,1100, IF(C6<=10000,1200, IF(C6<=15000,1300, IF(C6<=20000,1400, IF(C6<=25000,1500, IF(C6<=30000,1600, IF(C6<=35000,1700, IF(C6<=40000,1800, IF(C6<=45000,1900, IF(C6<=50000,2100, IF(C6<=55000,2200, IF(C6<=60000,2300, IF(C6<=65000,2400, IF(C6<=70000,2500, IF(C6<=75000,2750, IF(C6<=80000,3000, IF(C6<=85000,3250, IF(C6<=90000,3500, IF(C6<=95000,3750, IF(C6<=100000,4000, IF(C6<=105000,4250, IF(C6<=110000,4500, IF(C6<=115000,4750, IF(C6<=120000,5000, )))))))))))))))))))))))))))))) -> 700
A7: 4 | C7: =A7*datos!$C$63 -> 2420 | E7: =IF(C7<=3000,700, IF(C7<=4000,800, IF(C7<=5000,850, IF(C7<=6000,900, IF(C7<=7000,950, IF(C7<=8000,1000, IF(C7<=9000,1100, IF(C7<=10000,1200, IF(C7<=15000,1300, IF(C7<=20000,1400, IF(C7<=25000,1500, IF(C7<=30000,1600, IF(C7<=35000,1700, IF(C7<=40000,1800, IF(C7<=45000,1900, IF(C7<=50000,2100, IF(C7<=55000,2200, IF(C7<=60000,2300, IF(C7<=65000,2400, IF(C7<=70000,2500, IF(C7<=75000,2750, IF(C7<=80000,3000, IF(C7<=85000,3250, IF(C7<=90000,3500, IF(C7<=95000,3750, IF(C7<=100000,4000, IF(C7<=105000,4250, IF(C7<=110000,4500, IF(C7<=115000,4750, IF(C7<=120000,5000, )))))))))))))))))))))))))))))) -> 700
A8: 5 | C8: =A8*datos!$C$63 -> 3025 | E8: =IF(C8<=3000,700, IF(C8<=4000,800, IF(C8<=5000,850, IF(C8<=6000,900, IF(C8<=7000,950, IF(C8<=8000,1000, IF(C8<=9000,1100, IF(C8<=10000,1200, IF(C8<=15000,1300, IF(C8<=20000,1400, IF(C8<=25000,1500, IF(C8<=30000,1600, IF(C8<=35000,1700, IF(C8<=40000,1800, IF(C8<=45000,1900, IF(C8<=50000,2100, IF(C8<=55000,2200, IF(C8<=60000,2300, IF(C8<=65000,2400, IF(C8<=70000,2500, IF(C8<=75000,2750, IF(C8<=80000,3000, IF(C8<=85000,3250, IF(C8<=90000,3500, IF(C8<=95000,3750, IF(C8<=100000,4000, IF(C8<=105000,4250, IF(C8<=110000,4500, IF(C8<=115000,4750, IF(C8<=120000,5000, )))))))))))))))))))))))))))))) -> 800
A9: 6 | C9: =A9*datos!$C$63 -> 3630 | E9: =IF(C9<=3000,700, IF(C9<=4000,800, IF(C9<=5000,850, IF(C9<=6000,900, IF(C9<=7000,950, IF(C9<=8000,1000, IF(C9<=9000,1100, IF(C9<=10000,1200, IF(C9<=15000,1300, IF(C9<=20000,1400, IF(C9<=25000,1500, IF(C9<=30000,1600, IF(C9<=35000,1700, IF(C9<=40000,1800, IF(C9<=45000,1900, IF(C9<=50000,2100, IF(C9<=55000,2200, IF(C9<=60000,2300, IF(C9<=65000,2400, IF(C9<=70000,2500, IF(C9<=75000,2750, IF(C9<=80000,3000, IF(C9<=85000,3250, IF(C9<=90000,3500, IF(C9<=95000,3750, IF(C9<=100000,4000, IF(C9<=105000,4250, IF(C9<=110000,4500, IF(C9<=115000,4750, IF(C9<=120000,5000, )))))))))))))))))))))))))))))) -> 800
A10: 7 | C10: =A10*datos!$C$63 -> 4235 | E10: =IF(C10<=3000,700, IF(C10<=4000,800, IF(C10<=5000,850, IF(C10<=6000,900, IF(C10<=7000,950, IF(C10<=8000,1000, IF(C10<=9000,1100, IF(C10<=10000,1200, IF(C10<=15000,1300, IF(C10<=20000,1400, IF(C10<=25000,1500, IF(C10<=30000,1600, IF(C10<=35000,1700, IF(C10<=40000,1800, IF(C10<=45000,1900, IF(C10<=50000,2100, IF(C10<=55000,2200, IF(C10<=60000,2300, IF(C10<=65000,2400, IF(C10<=70000,2500, IF(C10<=75000,2750, IF(C10<=80000,3000, IF(C10<=85000,3250, IF(C10<=90000,3500, IF(C10<=95000,3750, IF(C10<=100000,4000, IF(C10<=105000,4250, IF(C10<=110000,4500, IF(C10<=115000,4750, IF(C10<=120000,5000, )))))))))))))))))))))))))))))) -> 850
A11: 8 | C11: =A11*datos!$C$63 -> 4840 | E11: =IF(C11<=3000,700, IF(C11<=4000,800, IF(C11<=5000,850, IF(C11<=6000,900, IF(C11<=7000,950, IF(C11<=8000,1000, IF(C11<=9000,1100, IF(C11<=10000,1200, IF(C11<=15000,1300, IF(C11<=20000,1400, IF(C11<=25000,1500, IF(C11<=30000,1600, IF(C11<=35000,1700, IF(C11<=40000,1800, IF(C11<=45000,1900, IF(C11<=50000,2100, IF(C11<=55000,2200, IF(C11<=60000,2300, IF(C11<=65000,2400, IF(C11<=70000,2500, IF(C11<=75000,2750, IF(C11<=80000,3000, IF(C11<=85000,3250, IF(C11<=90000,3500, IF(C11<=95000,3750, IF(C11<=100000,4000, IF(C11<=105000,4250, IF(C11<=110000,4500, IF(C11<=115000,4750, IF(C11<=120000,5000, )))))))))))))))))))))))))))))) -> 850
A12: 9 | C12: =A12*datos!$C$63 -> 5445 | E12: =IF(C12<=3000,700, IF(C12<=4000,800, IF(C12<=5000,850, IF(C12<=6000,900, IF(C12<=7000,950, IF(C12<=8000,1000, IF(C12<=9000,1100, IF(C12<=10000,1200, IF(C12<=15000,1300, IF(C12<=20000,1400, IF(C12<=25000,1500, IF(C12<=30000,1600, IF(C12<=35000,1700, IF(C12<=40000,1800, IF(C12<=45000,1900, IF(C12<=50000,2100, IF(C12<=55000,2200, IF(C12<=60000,2300, IF(C12<=65000,2400, IF(C12<=70000,2500, IF(C12<=75000,2750, IF(C12<=80000,3000, IF(C12<=85000,3250, IF(C12<=90000,3500, IF(C12<=95000,3750, IF(C12<=100000,4000, IF(C12<=105000,4250, IF(C12<=110000,4500, IF(C12<=115000,4750, IF(C12<=120000,5000, )))))))))))))))))))))))))))))) -> 900
A13: 10 | C13: =A13*datos!$C$63 -> 6050 | E13: =IF(C13<=3000,700, IF(C13<=4000,800, IF(C13<=5000,850, IF(C13<=6000,900, IF(C13<=7000,950, IF(C13<=8000,1000, IF(C13<=9000,1100, IF(C13<=10000,1200, IF(C13<=15000,1300, IF(C13<=20000,1400, IF(C13<=25000,1500, IF(C13<=30000,1600, IF(C13<=35000,1700, IF(C13<=40000,1800, IF(C13<=45000,1900, IF(C13<=50000,2100, IF(C13<=55000,2200, IF(C13<=60000,2300, IF(C13<=65000,2400, IF(C13<=70000,2500, IF(C13<=75000,2750, IF(C13<=80000,3000, IF(C13<=85000,3250, IF(C13<=90000,3500, IF(C13<=95000,3750, IF(C13<=100000,4000, IF(C13<=105000,4250, IF(C13<=110000,4500, IF(C13<=115000,4750, IF(C13<=120000,5000, )))))))))))))))))))))))))))))) -> 950
A14: 11 | C14: =A14*datos!$C$63 -> 6655 | E14: =IF(C14<=3000,700, IF(C14<=4000,800, IF(C14<=5000,850, IF(C14<=6000,900, IF(C14<=7000,950, IF(C14<=8000,1000, IF(C14<=9000,1100, IF(C14<=10000,1200, IF(C14<=15000,1300, IF(C14<=20000,1400, IF(C14<=25000,1500, IF(C14<=30000,1600, IF(C14<=35000,1700, IF(C14<=40000,1800, IF(C14<=45000,1900, IF(C14<=50000,2100, IF(C14<=55000,2200, IF(C14<=60000,2300, IF(C14<=65000,2400, IF(C14<=70000,2500, IF(C14<=75000,2750, IF(C14<=80000,3000, IF(C14<=85000,3250, IF(C14<=90000,3500, IF(C14<=95000,3750, IF(C14<=100000,4000, IF(C14<=105000,4250, IF(C14<=110000,4500, IF(C14<=115000,4750, IF(C14<=120000,5000, )))))))))))))))))))))))))))))) -> 950
... A263: 260 | C263: =A263*datos!$C$63 -> 157300 | E263: =IF(C263<=3000,700, IF(C263<=4000,800, IF(C263<=5000,850, IF(C263<=6000,900, IF(C263<=7000,950, IF(C263<=8000,1000, IF(C263<=9000,1100, IF(C263<=10000,1200, IF(C263<=15000,1300, IF(C263<=20000,1400, IF(C263<=25000,1500, IF(C263<=30000,1600, IF(C263<=35000,1700, IF(C263<=40000,1800, IF(C263<=45000,1900, IF(C263<=50000,2100, IF(C263<=55000,2200, IF(C263<=60000,2300, IF(C263<=65000,2400, IF(C263<=70000,2500, IF(C263<=75000,2750, IF(C263<=80000,3000, IF(C263<=85000,3250, IF(C263<=90000,3500, IF(C263<=95000,3750, IF(C263<=100000,4000, IF(C263<=105000,4250, IF(C263<=110000,4500, IF(C263<=115000,4750, IF(C263<=120000,5000, )))))))))))))))))))))))))))))) -> 0

Sheet t.com
A1: tabla_comerciales
A2: Nombre y Apellidos | B2: Teléfono | C2: Email | D2: usuario | E2: contraseña | F2: Localidades Asignadas
